Workbook
Name AR5_Ratio: [1]Lookups!$J$33:$K$37
Name AR5_TruFal: [1]Lookups!$G$33:$H$73

Sheet gDP
A1: Data Source | B1: World Development Indicators
A3: Last Updated Date | B3: 45609
A5: Country Name | B5: Country Code | C5: Indicator Name | D5: Indicator Code | E5: 1960 | F5: 1961 | G5: 1962 | H5: 1963 | I5: 1964 | J5: 1965 | K5: 1966 | L5: 1967 | M5: 1968 | N5: 1969 | O5: 1970 | P5: 1971 | Q5: 1972 | R5: 1973 | S5: 1974 | T5: 1975 | U5: 1976 | V5: 1977 | W5: 1978 | X5: 1979 | Y5: 1980 | Z5: 1981 | AA5: 1982 | AB5: 1983 | AC5: 1984 | AD5: 1985 | AE5: 1986 | AF5: 1987 | AG5: 1988 | AH5: 1989 | AI5: 1990 | AJ5: 1991 | AK5: 1992 | AL5: 1993 | AM5: 1994 | AN5: 1995 | AO5: 1996 | AP5: 1997 | AQ5: 1998 | AR5: 1999 | AS5: 2000 | AT5: 2001 | AU5: 2002 | AV5: 2003 | AW5: 2004 | AX5: 2005 | AY5: 2006 | AZ5: 2007 | BA5: 2008 | BB5: 2009 | BC5: 2010 | BD5: 2011 | BE5: 2012 | BF5: 2013 | BG5: 2014 | BH5: 2015 | BI5: 2016 | BJ5: 2017 | BK5: 2018 | BL5: 2019 | BM5: 2020 | BN5: 2021 | BO5: 2022 | BP5: 2023
A6: Aruba | B6: ABW | C6: GDP (current US$) | D6: NY.GDP.MKTP.CD | AE6: 4.0558659e+08 | AF6: 4.877095e+08 | AG6: 5.9664804e+08 | AH6: 6.9553073e+08 | AI6: 7.6480447e+08 | AJ6: 8.7206704e+08 | AK6: 9.5865922e+08 | AL6: 1.0832402e+09 | AM6: 1.2458101e+09 | AN6: 1.3206704e+09 | AO6: 1.3798883e+09 | AP6: 1.5318436e+09 | AQ6: 1.6653631e+09 | AR6: 1.722905e+09 | AS6: 1.8734525e+09 | AT6: 1.896457e+09 | AU6: 1.9618436e+09 | AV6: 2.0441117e+09 | AW6: 2.2548307e+09 | AX6: 2.3600173e+09 | AY6: 2.4697827e+09 | AZ6: 2.6776413e+09 | BA6: 2.8430246e+09 | BB6: 2.5537933e+09 | BC6: 2.4535972e+09 | BD6: 2.6378592e+09 | BE6: 2.6152084e+09 | BF6: 2.7278497e+09 | BG6: 2.7908497e+09 | BH6: 2.9629073e+09 | BI6: 2.9836352e+09 | BJ6: 3.0924291e+09 | BK6: 3.2761844e+09 | BL6: 3.3957989e+09 | BM6: 2.5589063e+09 | BN6: 3.1031841e+09 | BO6: 3.5447078e+09
A7: Africa Eastern and Southern | B7: AFE | C7: GDP (current US$) | D7: NY.GDP.MKTP.CD | E7: 2.1216962e+10 | F7: 2.2307471e+10 | G7: 2.3702472e+10 | H7: 2.5779377e+10 | I7: 2.8049537e+10 | J7: 3.037491e+10 | K7: 3.3049155e+10 | L7: 3.5933757e+10 | M7: 3.8749865e+10 | N7: 4.2964345e+10 | O7: 4.3702318e+10 | P7: 4.7632994e+10 | Q7: 5.1627512e+10 | R7: 6.6610918e+10 | S7: 8.1658052e+10 | T7: 8.6883553e+10 | U7: 8.8290756e+10 | V7: 9.8868135e+10 | W7: 1.1080241e+11 | X7: 1.2978097e+11 | Y7: 1.6816516e+11 | Z7: 1.777501e+11 | AA7: 1.6930277e+11 | AB7: 1.7989783e+11 | AC7: 1.662081e+11 | AD7: 1.4324952e+11 | AE7: 1.5479261e+11 | AF7: 1.8581246e+11 | AG7: 2.0209261e+11 | AH7: 2.144735e+11 | AI7: 2.5121184e+11 | AJ7: 2.735426e+11 | AK7: 2.3943317e+11 | AL7: 2.4027139e+11 | AM7: 2.4356481e+11 | AN7: 2.7343306e+11 | AO7: 2.7251934e+11 | AP7: 2.8840528e+11 | AQ7: 2.6883364e+11 | AR7: 2.6542929e+11 | AS7: 2.8720165e+11 | AT7: 2.6099223e+11 | AU7: 2.6781504e+11 | AV7: 3.5571637e+11 | AW7: 4.4269619e+11 | AX7: 5.1666107e+11 | AY7: 5.8024075e+11 | AZ7: 6.655987e+11 | BA7: 7.1350211e+11 | BB7: 7.1548533e+11 | BC7: 8.4940966e+11 | BD7: 9.4543915e+11 | BE7: 9.5267559e+11 | BF7: 9.6334728e+11 | BG7: 9.7968966e+11 | BH7: 8.9929568e+11 | BI7: 8.2982996e+11 | BJ7: 9.4010548e+11 | BK7: 1.0127193e+12 | BL7: 1.0065273e+12 | BM7: 9.2907409e+11 | BN7: 1.0867722e+12 | BO7: 1.1839621e+12 | BP7: 1.236163e+12
A8: Afghanistan | B8: AFG | C8: GDP (current US$) | D8: NY.GDP.MKTP.CD | AS8: 3.5214181e+09 | AT8: 2.8135718e+09 | AU8: 3.8257014e+09 | AV8: 4.5209468e+09 | AW8: 5.2248967e+09 | AX8: 6.2032565e+09 | AY8: 6.9717583e+09 | AZ8: 9.7478862e+09 | BA8: 1.0109297e+10 | BB8: 1.2416153e+10 | BC8: 1.5856669e+10 | BD8: 1.7805098e+10 | BE8: 1.990733e+10 | BF8: 2.0146417e+10 | BG8: 2.0497129e+10 | BH8: 1.9134222e+10 | BI8: 1.8116572e+10 | BJ8: 1.8753456e+10 | BK8: 1.8053223e+10 | BL8: 1.8799444e+10 | BM8: 1.9955929e+10 | BN8: 1.4266499e+10 | BO8: 1.4502158e+10
A9: Africa Western and Central | B9: AFW | C9: GDP (current US$) | D9: NY.GDP.MKTP.CD | E9: 1.1884128e+10 | F9: 1.2685662e+10 | G9: 1.3606829e+10 | H9: 1.4439975e+10 | I9: 1.5769108e+10 | J9: 1.693448e+10 | K9: 1.8048039e+10 | L9: 1.6495768e+10 | M9: 1.7022696e+10 | N9: 1.9301308e+10 | O9: 2.6697108e+10 | P9: 2.4507116e+10 | Q9: 2.9493915e+10 | R9: 3.6902673e+10 | S9: 4.9688194e+10 | T9: 5.7280847e+10 | U9: 6.838632e+10 | V9: 7.1790696e+10 | W9: 7.87791e+10 | X9: 9.6682239e+10 | Y9: 1.2050108e+11 | Z9: 2.1691103e+11 | AA9: 1.9591794e+11 | AB9: 1.5122276e+11 | AC9: 1.3121816e+11 | AD9: 1.3780292e+11 | AE9: 1.09237e+11 | AF9: 1.1229477e+11 | AG9: 1.1122715e+11 | AH9: 1.0393437e+11 | AI9: 1.2371132e+11 | AJ9: 1.29942e+11 | AK9: 1.2459939e+11 | AL9: 1.2973255e+11 | AM9: 1.347769e+11 | AN9: 2.0717699e+11 | AO9: 2.6260091e+11 | AP9: 2.7574224e+11 | AQ9: 2.9615244e+11 | AR9: 1.3946835e+11 | AS9: 1.4214008e+11 | AT9: 1.4945186e+11 | AU9: 1.7869244e+11 | AV9: 2.0698205e+11 | AW9: 2.5610064e+11 | AX9: 3.1240932e+11 | AY9: 3.9708879e+11 | AZ9: 4.6568351e+11 | BA9: 5.6793796e+11 | BB9: 5.0855258e+11 | BC9: 5.9869771e+11 | BD9: 6.8223332e+11 | BE9: 7.3779965e+11 | BF9: 8.3416061e+11 | BG9: 8.9458544e+11 | BH9: 7.6936732e+11 | BI9: 6.9218109e+11 | BJ9: 6.8575016e+11 | BK9: 7.6818959e+11 | BL9: 8.2393363e+11 | BM9: 7.8714672e+11 | BN9: 8.4599305e+11 | BO9: 8.7714081e+11 | BP9: 7.9658616e+11
A10: Angola | B10: AGO | C10: GDP (current US$) | D10: NY.GDP.MKTP.CD | AL10: 5880000000 | AM10: 4.4320261e+09 | AN10: 5.5386573e+09 | AO10: 6.5354584e+09 | AP10: 7.6754238e+09 | AQ10: 6.5063872e+09 | AR10: 6.1529233e+09 | AS10: 9.129595e+09 | AT10: 8.9360791e+09 | AU10: 1.5285592e+10 | AV10: 1.7812705e+10 | AW10: 2.3552058e+10 | AX10: 3.6970901e+10 | AY10: 5.2381025e+10 | AZ10: 6.5266415e+10 | BA10: 8.8538665e+10 | BB10: 7.0307196e+10 | BC10: 8.3799474e+10 | BD10: 1.1178975e+11 | BE10: 1.2805292e+11 | BF10: 1.3233911e+11 | BG10: 1.359668e+11 | BH10: 9.0496421e+10 | BI10: 5.2761617e+10 | BJ10: 7.3690155e+10 | BK10: 7.9450688e+10 | BL10: 7.0897963e+10 | BM10: 4.8501561e+10 | BN10: 6.650513e+10 | BO10: 1.0439975e+11 | BP10: 8.4722958e+10
A11: Albania | B11: ALB | C11: GDP (current US$) | D11: NY.GDP.MKTP.CD | AC11: 1.857338e+09 | AD11: 1.8970501e+09 | AE11: 2097326250 | AF11: 2080796250 | AG11: 2051236250 | AH11: 2253090000 | AI11: 2028553750 | AJ11: 1.099559e+09 | AK11: 6.5217499e+08 | AL11: 1.1853155e+09 | AM11: 1.8809509e+09 | AN11: 2.3927649e+09 | AO11: 3.1996408e+09 | AP11: 2.258514e+09 | AQ11: 2.5459645e+09 | AR11: 3.2121217e+09 | AS11: 3.4803553e+09 | AT11: 3.9221008e+09 | AU11: 4.3480682e+09 | AV11: 5.6114963e+09 | AW11: 7.1846858e+09 | AX11: 8.0520772e+09 | AY11: 8.896075e+09 | AZ11: 1.0677325e+10 | BA11: 1.2881353e+10 | BB11: 1.2044206e+10 | BC11: 1.1926927e+10 | BD11: 1.289076e+10 | BE11: 1.2319834e+10 | BF11: 1.2776224e+10 | BG11: 1.3228148e+10 | BH11: 1.1386853e+10 | BI11: 1.18612e+10 | BJ11: 1.3019726e+10 | BK11: 1.5156424e+10 | BL11: 1.5401826e+10 | BM11: 1.5162734e+10 | BN11: 1.7930565e+10 | BO11: 1.8916379e+10 | BP11: 2.2977678e+10
A12: Andorra | B12: AND | C12: GDP (current US$) | D12: NY.GDP.MKTP.CD | O12: 78617711 | P12: 89406608 | Q12: 1.134144e+08 | R12: 1.5084164e+08 | S12: 1.8655708e+08 | T12: 2.2011257e+08 | U12: 2.2728385e+08 | V12: 2.539979e+08 | W12: 3.0802026e+08 | X12: 4.1154875e+08 | Y12: 4.4637778e+08 | Z12: 3.8898327e+08 | AA12: 3.7591474e+08 | AB12: 3.2785004e+08 | AC12: 3.3007308e+08 | AD12: 3.4674271e+08 | AE12: 4.8199601e+08 | AF12: 6.1129992e+08 | AG12: 7.2142594e+08 | AH12: 7.9548958e+08 | AI12: 1.0289897e+09 | AJ12: 1.1068914e+09 | AK12: 1.209992e+09 | AL12: 1.0070903e+09 | AM12: 1.0175441e+09 | AN12: 1.1787453e+09 | AO12: 1.2240241e+09 | AP12: 1.1806456e+09 | AQ12: 1.211954e+09 | AR12: 1.2402951e+09 | AS12: 1.4326062e+09 | AT12: 1.5482658e+09 | AU12: 1.7642798e+09 | AV12: 2.3669418e+09 | AW12: 2.9002453e+09 | AX12: 3.1610841e+09 | AY12: 3.459338e+09 | AZ12: 3.9576254e+09 | BA12: 4.1023194e+09 | BB12: 3.6889763e+09 | BC12: 3.4499257e+09 | BD12: 3.6291336e+09 | BE12: 3.1886528e+09 | BF12: 3.193513e+09 | BG12: 3.2716856e+09 | BH12: 2.7898813e+09 | BI12: 2.8966105e+09 | BJ12: 3.0001621e+09 | BK12: 3.2184199e+09 | BL12: 3.1551493e+09 | BM12: 2.8910011e+09 | BN12: 3.324683e+09 | BO12: 3.380602e+09 | BP12: 3.7276736e+09
A13: Arab World | B13: ARB | C13: GDP (current US$) | D13: NY.GDP.MKTP.CD | J13: 2.6772088e+10 | K13: 2.8352061e+10 | L13: 3.0601968e+10 | M13: 3.4974202e+10 | N13: 3.8564894e+10 | O13: 4.3095586e+10 | P13: 4.9931741e+10 | Q13: 5.9972469e+10 | R13: 7.9132917e+10 | S13: 1.5220208e+11 | T13: 1.681736e+11 | U13: 2.100121e+11 | V13: 2.422925e+11 | W13: 2.6542751e+11 | X13: 3.5814057e+11 | Y13: 4.8644098e+11 | Z13: 4.9494936e+11 | AA13: 4.6311678e+11 | AB13: 4.3750279e+11 | AC13: 4.4021396e+11 | AD13: 4.3289957e+11 | AE13: 4.055025e+11 | AF13: 4.3128883e+11 | AG13: 4.2941386e+11 | AH13: 4.5740211e+11 | AI13: 6.4009092e+11 | AJ13: 4.6637435e+11 | AK13: 4.6606266e+11 | AL13: 4.771896e+11 | AM13: 4.9808376e+11 | AN13: 5.2656085e+11 | AO13: 5.6878541e+11 | AP13: 6.1239463e+11 | AQ13: 5.9674229e+11 | AR13: 6.6317606e+11 | AS13: 7.6065953e+11 | AT13: 7.4197482e+11 | AU13: 7.4372648e+11 | AV13: 8.269765e+11 | AW13: 9.8370079e+11 | AX13: 1.2055959e+12 | AY13: 1.4341092e+12 | AZ13: 1.668426e+12 | BA13: 2.1091718e+12 | BB13: 1.8227838e+12 | BC13: 2.1542523e+12 | BD13: 2.5598552e+12 | BE13: 2.7937757e+12 | BF13: 2.857872e+12 | BG13: 2.9050759e+12 | BH13: 2.5441363e+12 | BI13: 2.4999659e+12 | BJ13: 2.5710537e+12 | BK13: 2.8655436e+12 | BL13: 2.8986687e+12 | BM13: 2.5765533e+12 | BN13: 2.9691168e+12 | BO13: 3.6136824e+12 | BP13: 3.4915169e+12
A14: United Arab Emirates | B14: ARE | C14: GDP (current US$) | D14: NY.GDP.MKTP.CD | O14: 6.859867e+08 | P14: 9.398936e+08 | Q14: 1.4150869e+09 | R14: 4.2312436e+09 | S14: 1.1651506e+10 | T14: 1.4720728e+10 | U14: 1.9213159e+10 | V14: 2.4871775e+10 | W14: 2.3775764e+10 | X14: 3.122566e+10 | Y14: 4.359916e+10 | Z14: 4.9333424e+10 | AA14: 4.6622719e+10 | AB14: 4.2803323e+10 | AC14: 4.1807954e+10 | AD14: 4.060365e+10 | AE14: 3.3943612e+10 | AF14: 3.6384909e+10 | AG14: 3.6275674e+10 | AH14: 4.1464996e+10 | AI14: 5.0701444e+10 | AJ14: 5.1552166e+10 | AK14: 5.4239172e+10 | AL14: 5.562517e+10 | AM14: 5.9305094e+10 | AN14: 6.5743667e+10 | AO14: 7.3571234e+10 | AP14: 7.8839008e+10 | AQ14: 7.5674336e+10 | AR14: 8.4445473e+10 | AS14: 1.0433737e+11 | AT14: 1.0331164e+11 | AU14: 1.098162e+11 | AV14: 1.2434636e+11 | AW14: 1.4782437e+11 | AX14: 1.8061747e+11 | AY14: 2.2211654e+11 | AZ14: 2.5791613e+11 | BA14: 3.1547462e+11 | BB14: 2.5354736e+11 | BC14: 3.0018905e+11 | BD14: 3.6083274e+11 | BE14: 3.8461013e+11 | BF14: 4.0021853e+11 | BG14: 4.1410537e+11 | BH14: 3.7027547e+11 | BI14: 3.6925533e+11 | BJ14: 3.905168e+11 | BK14: 4.2704943e+11 | BL14: 4.1798972e+11 | BM14: 3.4947302e+11 | BN14: 4.1517879e+11 | BO14: 5.0706397e+11 | BP14: 5.0417345e+11
A15: Argentina | B15: ARG | C15: GDP (current US$) | D15: NY.GDP.MKTP.CD | AB15: 109490000000 | AC15: 1.1298857e+11 | AD15: 8.8416667e+10 | AE15: 1.0621383e+11 | AF15: 1.0902944e+11 | AG15: 126928000000 | AH15: 7.6629658e+10 | AI15: 1.4135265e+11 | AJ15: 1.8971998e+11 | AK15: 2.2877892e+11 | AL15: 2.3674172e+11 | AM15: 257440000000 | AN15: 258031750000 | AO15: 272149750000 | AP15: 292859000000 | AQ15: 298948250000 | AR15: 283523000000 | AS15: 284203750000 | AT15: 268696750000 | AU15: 9.7724004e+10 | AV15: 1.2758697e+11 | AW15: 1.6465793e+11 | AX15: 1.987371e+11 | AY15: 2.3255726e+11 | AZ15: 2.8753051e+11 | BA15: 3.6155804e+11 | BB15: 3.3297648e+11 | BC15: 4.2362742e+11 | BD15: 5.3015812e+11 | BE15: 5.4598238e+11 | BF15: 5.5202514e+11 | BG15: 5.2631967e+11 | BH15: 5.9474929e+11 | BI15: 5.5753232e+11 | BJ15: 6.4362839e+11 | BK15: 5.2481989e+11 | BL15: 4.4775468e+11 | BM15: 3.8574051e+11 | BN15: 4.8790257e+11 | BO15: 6.3113338e+11 | BP15: 6.4059141e+11
A16: Armenia | B16: ARM | C16: GDP (current US$) | D16: NY.GDP.MKTP.CD | AI16: 2.2568634e+09 | AJ16: 2.0698701e+09 | AK16: 1.2728355e+09 | AL16: 1.2013128e+09 | AM16: 1.3151586e+09 | AN16: 1.4683174e+09 | AO16: 1.5969689e+09 | AP16: 1.6394924e+09 | AQ16: 1.8937264e+09 | AR16: 1.8454822e+09 | AS16: 1.9115637e+09 | AT16: 2.1184679e+09 | AU16: 2.376335e+09 | AV16: 2.807061e+09 | AW16: 3.5766152e+09 | AX16: 4.9004695e+09 | AY16: 6.3844521e+09 | AZ16: 9.2063013e+09 | BA16: 1.1662041e+10 | BB16: 8.6479371e+09 | BC16: 9.2602858e+09 | BD16: 1.0142112e+10 | BE16: 1.0619321e+10 | BF16: 1.1121464e+10 | BG16: 1.1609513e+10 | BH16: 1.0553338e+10 | BI16: 1.0546136e+10 | BJ16: 1.1527459e+10 | BK16: 1.2457941e+10 | BL16: 1.3619291e+10 | BM16: 1.2641699e+10 | BN16: 1.3878909e+10 | BO16: 1.9513475e+10 | BP16: 2.4212135e+10
A17: American Samoa | B17: ASM | C17: GDP (current US$) | D17: NY.GDP.MKTP.CD | AU17: 512000000 | AV17: 524000000 | AW17: 509000000 | AX17: 500000000 | AY17: 493000000 | AZ17: 518000000 | BA17: 560000000 | BB17: 675000000 | BC17: 573000000 | BD17: 570000000 | BE17: 640000000 | BF17: 638000000 | BG17: 643000000 | BH17: 673000000 | BI17: 671000000 | BJ17: 612000000 | BK17: 639000000 | BL17: 647000000 | BM17: 721000000 | BN17: 750000000 | BO17: 871000000
A18: Antigua and Barbuda | B18: ATG | C18: GDP (current US$) | D18: NY.GDP.MKTP.CD | V18: 77496296 | W18: 88033333 | X18: 1.0958519e+08 | Y18: 1.3244074e+08 | Z18: 1.4937778e+08 | AA18: 1.6642593e+08 | AB18: 1.8484815e+08 | AC18: 2.1219259e+08 | AD18: 2.4634444e+08 | AE18: 2.9753704e+08 | AF18: 3.4684074e+08 | AG18: 4.1137407e+08 | AH18: 4.5514815e+08 | AI18: 4.7869259e+08 | AJ18: 5.0430741e+08 | AK18: 5.251037e+08 | AL18: 5.6563333e+08 | AM18: 6.2505185e+08 | AN18: 6.1601481e+08 | AO18: 6.7911111e+08 | AP18: 7.3439259e+08 | AQ18: 7.8976296e+08 | AR18: 8.3551481e+08 | AS18: 9.0055185e+08 | AT18: 8.7751481e+08 | AU18: 8.9798889e+08 | AV18: 9.4795556e+08 | AW18: 1.0261815e+09 | AX18: 1.1437148e+09 | AY18: 1.3035481e+09 | AZ18: 1487300000 | BA18: 1.5575407e+09 | BB18: 1.3864444e+09 | BC18: 1.2982556e+09 | BD18: 1.281337e+09 | BE18: 1.3271074e+09 | BF18: 1.3254259e+09 | BG18: 1.3788296e+09 | BH18: 1.4377556e+09 | BI18: 1.4896926e+09 | BJ18: 1.5311519e+09 | BK18: 1.6615296e+09 | BL18: 1.7253519e+09 | BM18: 1.4107963e+09 | BN18: 1.6013667e+09 | BO18: 1.8677333e+09 | BP18: 2.0330852e+09
A19: Australia | B19: AUS | C19: GDP (current US$) | D19: NY.GDP.MKTP.CD | E19: 1.8606563e+10 | F19: 1.9682883e+10 | G19: 1.9922563e+10 | H19: 2.1539843e+10 | I19: 2.3801124e+10 | J19: 2.5976164e+10 | K19: 2.7307844e+10 | L19: 3.0442725e+10 | M19: 3.2714085e+10 | N19: 3.6683366e+10 | O19: 4.1333607e+10 | P19: 4.5216647e+10 | Q19: 5.2040888e+10 | R19: 6.3830878e+10 | S19: 8.8963891e+10 | T19: 9.7303018e+10 | U19: 1.0505936e+11 | V19: 1.1034985e+11 | W19: 1.1849163e+11 | X19: 1.3489833e+11 | Y19: 1.4998552e+11 | Z19: 1.7689307e+11 | AA19: 1.940384e+11 | AB19: 1.7726542e+11 | AC19: 1.93519e+11 | AD19: 1.8063713e+11 | AE19: 1.8247552e+11 | AF19: 1.8948716e+11 | AG19: 2.3615404e+11 | AH19: 2.9987184e+11 | AI19: 3.1142051e+11 | AJ19: 3.2596669e+11 | AK19: 3.2551846e+11 | AL19: 3.121283e+11 | AM19: 3.2280249e+11 | AN19: 3.6816602e+11 | AO19: 4.0134188e+11 | AP19: 4.3564261e+11 | AQ19: 3.9967442e+11 | AR19: 3.8965221e+11 | AS19: 4.1616782e+11 | AT19: 3.796293e+11 | AU19: 3.957887e+11 | AV19: 4.6773908e+11 | AW19: 6.1465998e+11 | AX19: 6.956929e+11 | AY19: 7.4841756e+11 | AZ19: 8.5500746e+11 | BA19: 1.0561124e+12 | BB19: 9.2876212e+11 | BC19: 1.1488902e+12 | BD19: 1.3987013e+12 | BE19: 1.5476498e+12 | BF19: 1.5773018e+12 | BG19: 1.4685977e+12 | BH19: 1.3517689e+12 | BI19: 1.2075809e+12 | BJ19: 1326882104817 | BK19: 1.4297337e+12 | BL19: 1.3946713e+12 | BM19: 1.3303815e+12 | BN19: 1.5590338e+12 | BO19: 1.6929566e+12 | BP19: 1.7238272e+12
A20: Austria | B20: AUT | C20: GDP (current US$) | D20: NY.GDP.MKTP.CD | E20: 6.6501339e+09 | F20: 7.3754546e+09 | G20: 7.8236868e+09 | H20: 8.4471368e+09 | I20: 9.2498791e+09 | J20: 1.0081146e+10 | K20: 1.0982543e+10 | L20: 1.168032e+10 | M20: 1.2549017e+10 | N20: 1.3701141e+10 | O20: 1.5373006e+10 | P20: 1.7858486e+10 | Q20: 2.2059612e+10 | R20: 2.9515468e+10 | S20: 3.51893e+10 | T20: 4.0059207e+10 | U20: 4.2959976e+10 | V20: 5.1545759e+10 | W20: 6.2052259e+10 | X20: 7.3937297e+10 | Y20: 8.2058913e+10 | Z20: 7.1034228e+10 | AA20: 7.1275288e+10 | AB20: 7.2121017e+10 | AC20: 6.7985345e+10 | AD20: 6.9386774e+10 | AE20: 9.9036165e+10 | AF20: 1.2416844e+11 | AG20: 1.333394e+11 | AH20: 1.3310581e+11 | AI20: 1.6646339e+11 | AJ20: 1.7379418e+11 | AK20: 1.9507813e+11 | AL20: 1.9037972e+11 | AM20: 2.0353524e+11 | AN20: 2.4103828e+11 | AO20: 2.3725095e+11 | AP20: 2.1279035e+11 | AQ20: 2.182599e+11 | AR20: 2.1725915e+11 | AS20: 1.9728963e+11 | AT20: 1.9750877e+11 | AU20: 2.1439487e+11 | AV20: 2.6227363e+11 | AW20: 3.0145756e+11 | AX20: 3.1609227e+11 | AY20: 3.3628006e+11 | AZ20: 3.8918557e+11 | BA20: 4.3205194e+11 | BB20: 4.0175874e+11 | BC20: 3.9227511e+11 | BD20: 4.3168522e+11 | BE20: 4.0940182e+11 | BF20: 4.3019098e+11 | BG20: 4.4258482e+11 | BH20: 3.8197115e+11 | BI20: 3.9583735e+11 | BJ20: 4.1726115e+11 | BK20: 4.5499117e+11 | BL20: 4.4459616e+11 | BM20: 4.3504932e+11 | BN20: 4.7929536e+11 | BO20: 4.7094193e+11 | BP20: 5.1603414e+11
A21: Azerbaijan | B21: AZE | C21: GDP (current US$) | D21: NY.GDP.MKTP.CD | AI21: 8.8848485e+09 | AJ21: 5344000000 | AK21: 4.4465867e+08 | AL21: 1.5703926e+09 | AM21: 1.1931411e+09 | AN21: 2.4173312e+09 | AO21: 3.1765074e+09 | AP21: 3.9623624e+09 | AQ21: 4.4463686e+09 | AR21: 4.5812486e+09 | AS21: 5.2726157e+09 | AT21: 5.7076162e+09 | AU21: 6.2360877e+09 | AV21: 7.2764131e+09 | AW21: 8.6804057e+09 | AX21: 1.3245422e+10 | AY21: 2.0981929e+10 | AZ21: 3.3049419e+10 | BA21: 4.8851294e+10 | BB21: 4.4292427e+10 | BC21: 5.2909295e+10 | BD21: 6.5952796e+10 | BE21: 6.9679945e+10 | BF21: 7.416056e+10 | BG21: 7.5239785e+10 | BH21: 5.3076235e+10 | BI21: 3.7866997e+10 | BJ21: 4.0866627e+10 | BK21: 4.711247e+10 | BL21: 4.8174235e+10 | BM21: 42693000000 | BN21: 5.4825412e+10 | BO21: 7.8807471e+10 | BP21: 7.2356176e+10
A22: Burundi | B22: BDI | C22: GDP (current US$) | D22: NY.GDP.MKTP.CD | E22: 195999990 | F22: 202999992 | G22: 213500006 | H22: 232749998 | I22: 260750008 | J22: 1.5899496e+08 | K22: 1.6544457e+08 | L22: 1.7829714e+08 | M22: 183200000 | N22: 1.9020571e+08 | O22: 2.4273257e+08 | P22: 2.5284229e+08 | Q22: 2.4680457e+08 | R22: 3.0433984e+08 | S22: 3.4526349e+08 | T22: 4.2098667e+08 | U22: 4.4841275e+08 | V22: 5.4753556e+08 | W22: 6.1022556e+08 | X22: 7.8249667e+08 | Y22: 9.1972667e+08 | Z22: 9.6904667e+08 | AA22: 1.0132222e+09 | AB22: 1.0829263e+09 | AC22: 9.8714393e+08 | AD22: 1.1499793e+09 | AE22: 1.2017255e+09 | AF22: 1.1314665e+09 | AG22: 1.0824032e+09 | AH22: 1.1139241e+09 | AI22: 1.1321013e+09 | AJ22: 1.1673985e+09 | AK22: 1.0830377e+09 | AL22: 9.3863261e+08 | AM22: 9.2503059e+08 | AN22: 1.0004284e+09 | AO22: 8.6903386e+08 | AP22: 9.7289627e+08 | AQ22: 8.9377074e+08 | AR22: 8.0807722e+08 | AS22: 8.7048607e+08 | AT22: 8.7679472e+08 | AU22: 8.2539452e+08 | AV22: 7.8465442e+08 | AW22: 9.1525732e+08 | AX22: 1.1171131e+09 | AY22: 1.2733751e+09 | AZ22: 1.3561994e+09 | BA22: 1.6118359e+09 | BB22: 1.7814551e+09 | BC22: 2.0321352e+09 | BD22: 2.2358208e+09 | BE22: 2.3333413e+09 | BF22: 2.4516066e+09 | BG22: 2.7057833e+09 | BH22: 3.1040035e+09 | BI22: 2.6444878e+09 | BJ22: 2.723587e+09 | BK22: 2.6671822e+09 | BL22: 2.5765189e+09 | BM22: 2.6496803e+09 | BN22: 2.7757987e+09 | BO22: 3.3387228e+09 | BP22: 2.6421617e+09
A23: Belgium | B23: BEL | C23: GDP (current US$) | D23: NY.GDP.MKTP.CD | E23: 1.1810619e+10 | F23: 1.2561702e+10 | G23: 1.3436827e+10 | H23: 1.4445805e+10 | I23: 1.6168044e+10 | J23: 1.7597783e+10 | K23: 1.8894891e+10 | L23: 2.0252509e+10 | M23: 2.1654857e+10 | N23: 2.4019653e+10 | O23: 2.6706196e+10 | P23: 2.9821662e+10 | Q23: 3.7209418e+10 | R23: 4.7743801e+10 | S23: 5.6033078e+10 | T23: 6.5678189e+10 | U23: 7.1113883e+10 | V23: 8.2839905e+10 | W23: 1.0124653e+11 | X23: 1.1631546e+11 | Y23: 1.2682931e+11 | Z23: 1.0473002e+11 | AA23: 9.2095926e+10 | AB23: 8.7184239e+10 | AC23: 8.334953e+10 | AD23: 8.6268264e+10 | AE23: 1.2001879e+11 | AF23: 1.493944e+11 | AG23: 1.622991e+11 | AH23: 1.6422106e+11 | AI23: 2.0533175e+11 | AJ23: 2.10511e+11 | AK23: 2.3478165e+11 | AL23: 2.247218e+11 | AM23: 2.4488413e+11 | AN23: 2.8802559e+11 | AO23: 2.7920143e+11 | AP23: 2.5270805e+11 | AQ23: 2.5852834e+11 | AR23: 2.5824573e+11 | AS23: 2.3679246e+11 | AT23: 2.3674614e+11 | AU23: 2.583836e+11 | AV23: 3.1808253e+11 | AW23: 3.6921471e+11 | AX23: 3.8571476e+11 | AY23: 4.0825984e+11 | AZ23: 4.7092216e+11 | BA23: 5.1732809e+11 | BB23: 4.8325417e+11 | BC23: 4.8142088e+11 | BD23: 5.2333035e+11 | BE23: 4.9615288e+11 | BF23: 5.2179102e+11 | BG23: 5.353902e+11 | BH23: 4.6233557e+11 | BI23: 4.7606276e+11 | BJ23: 5.0276472e+11 | BK23: 5.4329907e+11 | BL23: 5.358658e+11 | BM23: 5.2602151e+11 | BN23: 6.0090446e+11 | BO23: 5.8361398e+11 | BP23: 6.3221658e+11
A24: Benin | B24: BEN | C24: GDP (current US$) | D24: NY.GDP.MKTP.CD | E24: 2.2619558e+08 | F24: 2.3566822e+08 | G24: 2.3643495e+08 | H24: 2.539277e+08 | I24: 2.6981901e+08 | J24: 2.8990868e+08 | K24: 3.0292524e+08 | L24: 3.0622195e+08 | M24: 3.2632311e+08 | N24: 3.3074824e+08 | O24: 3.3362771e+08 | P24: 3.3507303e+08 | Q24: 4.1033186e+08 | R24: 5.0437607e+08 | S24: 5.5465486e+08 | T24: 6.7687014e+08 | U24: 6.9840826e+08 | V24: 7.5004978e+08 | W24: 9.2884347e+08 | X24: 1.186231e+09 | Y24: 1.4052518e+09 | Z24: 1.2911202e+09 | AA24: 1.2677787e+09 | AB24: 1.0953482e+09 | AC24: 1.051134e+09 | AD24: 1.0457128e+09 | AE24: 1.336102e+09 | AF24: 1.5624122e+09 | AG24: 1.6202461e+09 | AH24: 1.5022944e+09 | AI24: 1.9599653e+09 | AJ24: 1.9864378e+09 | AK24: 1.6953153e+09 | AL24: 2.2745581e+09 | AM24: 1.5980759e+09 | AN24: 2.1696271e+09 | AO24: 2.3611164e+09 | AP24: 2.2683016e+09 | AQ24: 2.4550927e+09 | AR24: 3.677394e+09 | AS24: 3.5199914e+09 | AT24: 3.6662226e+09 | AU24: 4.1943427e+09 | AV24: 5.3492581e+09 | AW24: 6.1902704e+09 | AX24: 6.567655e+09 | AY24: 7.0341113e+09 | AZ24: 8.1690484e+09 | BA24: 9.7877345e+09 | BB24: 9.7386265e+09 | BC24: 9.535345e+09 | BD24: 1.0693321e+10 | BE24: 1.1141358e+10 | BF24: 1.2517845e+10 | BG24: 1.3284528e+10 | BH24: 1.1388161e+10 | BI24: 1.1821066e+10 | BJ24: 1.2701656e+10 | BK24: 1.4262408e+10 | BL24: 1.4390709e+10 | BM24: 1.5686742e+10 | BN24: 1.7687624e+10 | BO24: 1.7425418e+10 | BP24: 1.9673285e+10
A25: Burkina Faso | B25: BFA | C25: GDP (current US$) | D25: NY.GDP.MKTP.CD | E25: 3.3044282e+08 | F25: 3.5024723e+08 | G25: 3.795671e+08 | H25: 3.9404067e+08 | I25: 4.1032164e+08 | J25: 4.2291679e+08 | K25: 4.3388977e+08 | L25: 4.5075392e+08 | M25: 4.6044269e+08 | N25: 4.7829865e+08 | O25: 4.5840427e+08 | P25: 4.8241118e+08 | Q25: 5.7859552e+08 | R25: 6.7477357e+08 | S25: 7.5113343e+08 | T25: 9.399727e+08 | U25: 9.7654719e+08 | V25: 1.1312249e+09 | W25: 1.4755836e+09 | X25: 1.7484806e+09 | Y25: 1.9287199e+09 | Z25: 1.7758423e+09 | AA25: 1.7544501e+09 | AB25: 1.6002786e+09 | AC25: 1.4598801e+09 | AD25: 1.5524932e+09 | AE25: 2.0363034e+09 | AF25: 2.3698349e+09 | AG25: 2.6160405e+09 | AH25: 2.6155877e+09 | AI25: 3.1013008e+09 | AJ25: 3.1350456e+09 | AK25: 3.3566925e+09 | AL25: 3.1995365e+09 | AM25: 1.8952906e+09 | AN25: 2.379518e+09 | AO25: 2.5865506e+09 | AP25: 2.4476691e+09 | AQ25: 2.8049024e+09 | AR25: 3.3895667e+09 | AS25: 2.9683701e+09 | AT25: 3.1903711e+09 | AU25: 3.6223501e+09 | AV25: 4.7407681e+09 | AW25: 5.4516885e+09 | AX25: 6.1463532e+09 | AY25: 6.5474198e+09 | AZ25: 7.6257228e+09 | BA25: 9.4514355e+09 | BB25: 9.4506969e+09 | BC25: 1.010962e+10 | BD25: 1.2080296e+10 | BE25: 1.2561015e+10 | BF25: 1.34443e+10 | BG25: 1.3943016e+10 | BH25: 1.1832159e+10 | BI25: 1.2833363e+10 | BJ25: 1.4106956e+10 | BK25: 1.5890066e+10 | BL25: 1.6032814e+10 | BM25: 1.7725011e+10 | BN25: 1.9643167e+10 | BO25: 1.8820219e+10 | BP25: 2.0324618e+10
A26: Bangladesh | B26: BGD | C26: GDP (current US$) | D26: NY.GDP.MKTP.CD | E26: 4.2748941e+09 | F26: 4817580375 | G26: 5.0814135e+09 | H26: 5.3194586e+09 | I26: 5.3860548e+09 | J26: 5.9066368e+09 | K26: 6.4396879e+09 | L26: 7.2535757e+09 | M26: 7.4836858e+09 | N26: 8.4710064e+09 | O26: 8.9927222e+09 | P26: 8.7518432e+09 | Q26: 6.2882459e+09 | R26: 8.0867257e+09 | S26: 1.2512461e+10 | T26: 1.9448348e+10 | U26: 1.0117113e+10 | V26: 9.6511493e+09 | W26: 1.3281767e+10 | X26: 1.556548e+10 | Y26: 1.8138049e+10 | Z26: 2.0249694e+10 | AA26: 1.8525399e+10 | AB26: 1.7609049e+10 | AC26: 18920840000 | AD26: 2.2278423e+10 | AE26: 2.1774033e+10 | AF26: 2.4298032e+10 | AG26: 2.6579006e+10 | AH26: 2.8781715e+10 | AI26: 3.1598341e+10 | AJ26: 3.0957484e+10 | AK26: 3.1708875e+10 | AL26: 3.3166519e+10 | AM26: 3.3768661e+10 | AN26: 3.7939749e+10 | AO26: 4.6438484e+10 | AP26: 4.8244309e+10 | AQ26: 4.9984559e+10 | AR26: 5.127057e+10 | AS26: 5.3369787e+10 | AT26: 5.399129e+10 | AU26: 5.4724081e+10 | AV26: 6.0158929e+10 | AW26: 6.5108544e+10 | AX26: 6.9476001e+10 | AY26: 7.1795736e+10 | AZ26: 7.9611645e+10 | BA26: 9.1636997e+10 | BB26: 1.0247516e+11 | BC26: 1.1527554e+11 | BD26: 1.2860748e+11 | BE26: 1.3331075e+11 | BF26: 1.4999896e+11 | BG26: 1.7288661e+11 | BH26: 1.9514661e+11 | BI26: 2.6522451e+11 | BJ26: 2.9373245e+11 | BK26: 3.2136275e+11 | BL26: 3.5123166e+11 | BM26: 3.7397944e+11 | BN26: 4.1627165e+11 | BO26: 4.6013169e+11 | BP26: 4.3741533e+11
A27: Bulgaria | B27: BGR | C27: GDP (current US$) | D27: NY.GDP.MKTP.CD | Y27: 1.9839231e+10 | Z27: 19870000000 | AA27: 19342000000 | AB27: 1.6563667e+10 | AC27: 1.7594944e+10 | AD27: 1.7155421e+10 | AE27: 2.0249294e+10 | AF27: 28101000000 | AG27: 2.2555941e+10 | AH27: 2.1988444e+10 | AI27: 2.0632091e+10 | AJ27: 1.0943548e+10 | AK27: 1.0350515e+10 | AL27: 1.0832065e+10 | AM27: 9.697417e+09 | AN27: 1.8991484e+10 | AO27: 1.2294965e+10 | AP27: 1.1316127e+10 | AQ27: 1.5031055e+10 | AR27: 1.3627325e+10 | AS27: 1.324599e+10 | AT27: 1.4183446e+10 | AU27: 1.6403044e+10 | AV27: 2.1144958e+10 | AW27: 2.6157743e+10 | AX27: 2.9868658e+10 | AY27: 3.4380536e+10 | AZ27: 4.4432812e+10 | BA27: 5.4480684e+10 | BB27: 5.2023801e+10 | BC27: 5.0760929e+10 | BD27: 5.7737041e+10 | BE27: 5.4288135e+10 | BF27: 5.5852124e+10 | BG27: 5.7157783e+10 | BH27: 5.0811996e+10 | BI27: 5.3964253e+10 | BJ27: 5.9309748e+10 | BK27: 6.6370132e+10 | BL27: 6.888101e+10 | BM27: 7.0368758e+10 | BN27: 8.4041493e+10 | BO27: 9.034617e+10 | BP27: 1.0158438e+11
A28: Bahrain | B28: BHR | C28: GDP (current US$) | D28: NY.GDP.MKTP.CD | O28: 3.9157736e+08 | P28: 4.2218156e+08 | Q28: 5.3408118e+08 | R28: 7.6113254e+08 | S28: 1.0421769e+09 | T28: 1.0991076e+09 | U28: 1.5817095e+09 | V28: 1.9890603e+09 | W28: 2.272043e+09 | X28: 2.7101607e+09 | Y28: 3.4938345e+09 | Z28: 3.9431095e+09 | AA28: 4.1454211e+09 | AB28: 4.2470305e+09 | AC28: 4.4408746e+09 | AD28: 4.1523765e+09 | AE28: 3.4707468e+09 | AF28: 3.8569227e+09 | AG28: 4.2098342e+09 | AH28: 4.393094e+09 | AI28: 4.809511e+09 | AJ28: 5.2489112e+09 | AK28: 5.4022324e+09 | AL28: 5.9130011e+09 | AM28: 6.3306279e+09 | AN28: 6.6511809e+09 | AO28: 6.9381668e+09 | AP28: 7.2194077e+09 | AQ28: 7.031309e+09 | AR28: 7.5284691e+09 | AS28: 9.0628989e+09 | AT28: 8.9761968e+09 | AU28: 9.5935106e+09 | AV28: 1.1074814e+10 | AW28: 1.315016e+10 | AX28: 1.5968723e+10 | AY28: 1.8504761e+10 | AZ28: 21730000000 | BA28: 2.5710904e+10 | BB28: 2.2938218e+10 | BC28: 2.5713271e+10 | BD28: 2.8776596e+10 | BE28: 3.0749309e+10 | BF28: 3.2539468e+10 | BG28: 3.3387713e+10 | BH28: 3.1125851e+10 | BI28: 3.2250133e+10 | BJ28: 3.5423644e+10 | BK28: 3.7802005e+10 | BL28: 3.8653318e+10 | BM28: 3.4621808e+10 | BN28: 3.928867e+10 | BO28: 4.4383298e+10 | BP28: 43205000000
A29: Bahamas, The | B29: BHS | C29: GDP (current US$) | D29: NY.GDP.MKTP.CD | E29: 1.6980392e+08 | F29: 1.9009804e+08 | G29: 2.122549e+08 | H29: 2.377451e+08 | I29: 2.6666667e+08 | J29: 3.0039216e+08 | K29: 340000000 | L29: 3.9019608e+08 | M29: 4.4490196e+08 | N29: 5.2813725e+08 | O29: 5.3842315e+08 | P29: 573400000 | Q29: 590900000 | R29: 670900000 | S29: 632400000 | T29: 596200000 | U29: 642100000 | V29: 713000000 | W29: 832400000 | X29: 1139800100 | Y29: 1335300000 | Z29: 1426500000 | AA29: 1578300000 | AB29: 1732800000 | AC29: 2041100000 | AD29: 2320699900 | AE29: 2472500000 | AF29: 2713999900 | AG29: 2817900000 | AH29: 3062000000 | AI29: 3166000000 | AJ29: 3111160000 | AK29: 3109000000 | AL29: 3092000000 | AM29: 3259000000 | AN29: 3429000000 | AO29: 3609000000 | AP29: 6332360000 | AQ29: 6833220000 | AR29: 7683870000 | AS29: 8076470000 | AT29: 8317830000 | AU29: 8881160000 | AV29: 8870090000 | AW29: 9055290000 | AX29: 9836200000 | AY29: 10167250000 | AZ29: 10618340000 | BA29: 10526000000 | BB29: 9981960000 | BC29: 10095760000 | BD29: 10070450000 | BE29: 10720500000 | BF29: 10395800000 | BG29: 10974100000 | BH29: 11671900000 | BI29: 11745100000 | BJ29: 12236700000 | BK29: 12615800000 | BL29: 13016200000 | BM29: 9958200000 | BN29: 11368900000 | BO29: 13136400000 | BP29: 14338500000
A30: Bosnia and Herzegovina | B30: BIH | C30: GDP (current US$) | D30: NY.GDP.MKTP.CD | AI30: 7.7534783e+09 | AJ30: 6.1229592e+09 | AK30: 4.7350447e+09 | AL30: 3.6306689e+09 | AM30: 1.2558025e+09 | AN30: 1.866573e+09 | AO30: 2.7860453e+09 | AP30: 3.6719097e+09 | AQ30: 4.1167743e+09 | AR30: 4.6862564e+09 | AS30: 5.5677728e+09 | AT30: 5.8006155e+09 | AU30: 6.7282209e+09 | AV30: 8.4988944e+09 | AW30: 1.0156542e+10 | AX30: 1.1222796e+10 | AY30: 1.2864842e+10 | AZ30: 1.5778734e+10 | BA30: 1.9112797e+10 | BB30: 1.7613949e+10 | BC30: 1.7176316e+10 | BD30: 1.8644234e+10 | BE30: 1.7226736e+10 | BF30: 1.8179109e+10 | BG30: 1.8558734e+10 | BH30: 1.6404349e+10 | BI30: 1.7116926e+10 | BJ30: 1.8326373e+10 | BK30: 2.0484054e+10 | BL30: 2.0482609e+10 | BM30: 2.0226037e+10 | BN30: 2.3672712e+10 | BO30: 2.4534664e+10 | BP30: 2.7054889e+10
A31: Belarus | B31: BLR | C31: GDP (current US$) | D31: NY.GDP.MKTP.CD | AK31: 9200000000 | AL31: 1.6416667e+10 | AM31: 1.4952101e+10 | AN31: 1.3970426e+10 | AO31: 1.4756846e+10 | AP31: 1.4130586e+10 | AQ31: 1.5221353e+10 | AR31: 1.2138243e+10 | AS31: 1.273678e+10 | AT31: 1.235482e+10 | AU31: 1.4594901e+10 | AV31: 1.7825445e+10 | AW31: 2.3141566e+10 | AX31: 3.0210092e+10 | AY31: 3.6961894e+10 | AZ31: 4.5275712e+10 | BA31: 6.0752106e+10 | BB31: 5.0873167e+10 | BC31: 5.7231905e+10 | BD31: 6.1762382e+10 | BE31: 6.568589e+10 | BF31: 7.5527559e+10 | BG31: 7.8812805e+10 | BH31: 5.6454889e+10 | BI31: 4.7723545e+10 | BJ31: 5.4725302e+10 | BK31: 6.0031174e+10 | BL31: 6.4410123e+10 | BM31: 6.1371755e+10 | BN31: 6.9673747e+10 | BO31: 7.377518e+10 | BP31: 7.1857383e+10
A32: Belize | B32: BLZ | C32: GDP (current US$) | D32: NY.GDP.MKTP.CD | E32: 28072478 | F32: 29965000 | G32: 31857592 | H32: 33750114 | I32: 36194586 | J32: 40110040 | K32: 44450044 | L32: 47431256 | M32: 44999910 | N32: 47399905 | O32: 53339893 | P32: 59074687 | Q32: 65998069 | R32: 78214768 | S32: 1.0316045e+08 | T32: 1.1819403e+08 | U32: 97094227 | V32: 117650000 | W32: 136300000 | X32: 151800000 | Y32: 1.9793822e+08 | Z32: 1.9608985e+08 | AA32: 1.8220633e+08 | AB32: 1.9210319e+08 | AC32: 2.1438195e+08 | AD32: 2.1264374e+08 | AE32: 2.3163832e+08 | AF32: 2.8108256e+08 | AG32: 3.2009336e+08 | AH32: 3.6913389e+08 | AI32: 5.4568637e+08 | AJ32: 5.949757e+08 | AK32: 6.9362517e+08 | AL32: 7.5001877e+08 | AM32: 7.6964951e+08 | AN32: 8.1649162e+08 | AO32: 8.4820528e+08 | AP32: 8.7086112e+08 | AQ32: 9.2655076e+08 | AR32: 9.9690647e+08 | AS32: 1.1347568e+09 | AT32: 1.168128e+09 | AU32: 1.2400595e+09 | AV32: 1.3033819e+09 | AW32: 1.394274e+09 | AX32: 1.468146e+09 | AY32: 1.5842074e+09 | AZ32: 1.6992143e+09 | BA32: 1.7319216e+09 | BB32: 1.6814733e+09 | BC32: 1.7390703e+09 | BD32: 1.8188319e+09 | BE32: 1.8995032e+09 | BF32: 2.0217574e+09 | BG32: 2.1251256e+09 | BH32: 2.1947093e+09 | BI32: 2.2405935e+09 | BJ32: 2.2666648e+09 | BK32: 2.2927873e+09 | BL32: 2.3867925e+09 | BM32: 2.0477278e+09 | BN32: 2.4245752e+09 | BO32: 2.8305076e+09 | BP32: 3281500000
A33: Bermuda | B33: BMU | C33: GDP (current US$) | D33: NY.GDP.MKTP.CD | E33: 84466653 | F33: 89249985 | G33: 94149984 | H33: 96366651 | I33: 1.0756665e+08 | J33: 1.1433905e+08 | K33: 1.3417338e+08 | L33: 1.5510298e+08 | M33: 150000000 | N33: 164900000 | O33: 186300000 | P33: 211100000 | Q33: 235400000 | R33: 269500000 | S33: 312600000 | T33: 345000000 | U33: 386300000 | V33: 447000000 | W33: 475800000 | X33: 517200000 | Y33: 613299968 | Z33: 739100032 | AA33: 785500032 | AB33: 889400000 | AC33: 985699968 | AD33: 1039500032 | AE33: 1173500032 | AF33: 1296499968 | AG33: 1415100032 | AH33: 1501500032 | AI33: 1592400000 | AJ33: 1634900000 | AK33: 1679900000 | AL33: 1820359900 | AM33: 1867160100 | AN33: 2030750000 | AO33: 2695390000 | AP33: 2932827000 | AQ33: 3130748000 | AR33: 3324433000 | AS33: 3480219000 | AT33: 3680483000 | AU33: 3937228000 | AV33: 4186525000 | AW33: 4484703000 | AX33: 4868136000 | AY33: 6144000000 | AZ33: 6767000000 | BA33: 6980000000 | BB33: 6656000000 | BC33: 6634526000 | BD33: 6312691000 | BE33: 6378188000 | BF33: 6465756000 | BG33: 6413988000 | BH33: 6654541000 | BI33: 6899911000 | BJ33: 7142316000 | BK33: 7225977000 | BL33: 7423465000 | BM33: 6887147000 | BN33: 7286607000 | BO33: 7827980000
A34: Bolivia | B34: BOL | C34: GDP (current US$) | D34: NY.GDP.MKTP.CD | E34: 373250000 | F34: 406000000 | G34: 4.4391667e+08 | H34: 478000000 | I34: 5.3858333e+08 | J34: 5.9833333e+08 | K34: 662500000 | L34: 748250000 | M34: 8.4933333e+08 | N34: 9.2033333e+08 | O34: 1.0068333e+09 | P34: 1.0846667e+09 | Q34: 1.2861538e+09 | R34: 1263600000 | S34: 2101300000 | T34: 2405900000 | U34: 2733350000 | V34: 3229050000 | W34: 3760100000 | X34: 4510500000 | Y34: 4.450368e+09 | Z34: 5.7784878e+09 | AA34: 5.6003856e+09 | AB34: 5.4140081e+09 | AC34: 6.1693045e+09 | AD34: 5.3772767e+09 | AE34: 3.9593835e+09 | AF34: 4.3479563e+09 | AG34: 4.5976117e+09 | AH34: 4.7159734e+09 | AI34: 4.8675826e+09 | AJ34: 5.3432625e+09 | AK34: 5.6438687e+09 | AL34: 5.7346995e+09 | AM34: 5.9812229e+09 | AN34: 6.7151617e+09 | AO34: 7.3969491e+09 | AP34: 7.9257368e+09 | AQ34: 8.4974947e+09 | AR34: 8.2850644e+09 | AS34: 8.3978555e+09 | AT34: 8.1415169e+09 | AU34: 7.9054851e+09 | AV34: 8.0823996e+09 | AW34: 8.7734518e+09 | AX34: 9.5491229e+09 | AY34: 1.1451845e+10 | AZ34: 1.3120108e+10 | BA34: 1.6674276e+10 | BB34: 1.7339992e+10 | BC34: 1.9649724e+10 | BD34: 2.3963165e+10 | BE34: 2.7084497e+10 | BF34: 3.0659339e+10 | BG34: 3.2996188e+10 | BH34: 3.3000198e+10 | BI34: 3.3941126e+10 | BJ34: 3.7508642e+10 | BK34: 4.0287648e+10 | BL34: 4.0895323e+10 | BM34: 3.6629844e+10 | BN34: 4.0406112e+10 | BO34: 4.4008283e+10 | BP34: 4.5849833e+10
A35: Brazil | B35: BRA | C35: GDP (current US$) | D35: NY.GDP.MKTP.CD | AH35: 4.2559531e+11 | AI35: 3.8495982e+11 | AJ35: 3.4253409e+11 | AK35: 3.2819191e+11 | AL35: 3.6829203e+11 | AM35: 5.2536947e+11 | AN35: 7.6933305e+11 | AO35: 8.5042643e+11 | AP35: 8.8320618e+11 | AQ35: 8.6371076e+11 | AR35: 5.9964202e+11 | AS35: 6.5544823e+11 | AT35: 5.5998363e+11 | AU35: 5.0979527e+11 | AV35: 5.5823375e+11 | AW35: 6.6928942e+11 | AX35: 8.9163384e+11 | AY35: 1.1076265e+12 | AZ35: 1.3971145e+12 | BA35: 1.6958551e+12 | BB35: 1.6669964e+12 | BC35: 2.2088377e+12 | BD35: 2.6161562e+12 | BE35: 2.4652278e+12 | BF35: 2.4728195e+12 | BG35: 2.4560437e+12 | BH35: 1.8022122e+12 | BI35: 1.7956935e+12 | BJ35: 2.063515e+12 | BK35: 1.9169339e+12 | BL35: 1.8732882e+12 | BM35: 1.4761072e+12 | BN35: 1.6706474e+12 | BO35: 1.9519239e+12 | BP35: 2.1736657e+12
A36: Barbados | B36: BRB | C36: GDP (current US$) | D36: NY.GDP.MKTP.CD | E36: 80021380 | F36: 85363261 | G36: 88782065 | H36: 99893178 | I36: 99252153 | J36: 1.0502138e+08 | K36: 1.1319446e+08 | L36: 1.2555394e+08 | M36: 1.2573367e+08 | N36: 1.4139314e+08 | O36: 1.662102e+08 | P36: 1.8682423e+08 | Q36: 2.137231e+08 | R36: 2.6077062e+08 | S36: 3.1180934e+08 | T36: 4.0217861e+08 | U36: 4.3591127e+08 | V36: 4.9509767e+08 | W36: 5.5288371e+08 | X36: 6.7036245e+08 | Y36: 1.0122806e+09 | Z36: 1.1142047e+09 | AA36: 1.1639238e+09 | AB36: 1.2360165e+09 | AC36: 1.3468901e+09 | AD36: 1.4095361e+09 | AE36: 1.5477552e+09 | AF36: 1.7043703e+09 | AG36: 1.8127579e+09 | AH36: 2.0061652e+09 | AI36: 2.0121315e+09 | AJ36: 2.0205837e+09 | AK36: 1957000000 | AL36: 2.0633421e+09 | AM36: 2.1513449e+09 | AN36: 2.2169741e+09 | AO36: 2.3636454e+09 | AP36: 2.4983841e+09 | AQ36: 2.8170835e+09 | AR36: 2.9518222e+09 | AS36: 3059500000 | AT36: 3054500000 | AU36: 3106500000 | AV36: 3209500000 | AW36: 3444500000 | AX36: 3819500000 | AY36: 4217323400 | AZ36: 4675767950 | BA36: 4790410400 | BB36: 4466809600 | BC36: 4534772750 | BD36: 4662343500 | BE36: 4622687600 | BF36: 4693452700 | BG36: 4711838650 | BH36: 4738650450 | BI36: 4848210350 | BJ36: 5000457800 | BK36: 5128345200 | BL36: 5367139250 | BM36: 4779756550 | BN36: 4945276000 | BO36: 5840673700 | BP36: 6.3935642e+09
A37: Brunei Darussalam | B37: BRN | C37: GDP (current US$) | D37: NY.GDP.MKTP.CD | J37: 1.140395e+08 | K37: 1.3275753e+08 | L37: 1.3902954e+08 | M37: 1.6081824e+08 | N37: 1.6121024e+08 | O37: 1.7907893e+08 | P37: 1.9752577e+08 | Q37: 2.7082278e+08 | R37: 4.3309553e+08 | S37: 1.0735916e+09 | T37: 1.1683043e+09 | U37: 1.4230372e+09 | V37: 1.7327212e+09 | W37: 1.9415794e+09 | X37: 2.8038342e+09 | Y37: 4.9288065e+09 | Z37: 4.3662304e+09 | AA37: 4.2642025e+09 | AB37: 3.8446322e+09 | AC37: 3.7825532e+09 | AD37: 3.5235325e+09 | AE37: 2.3585744e+09 | AF37: 2.7544857e+09 | AG37: 2.6906841e+09 | AH37: 2.9855323e+09 | AI37: 3.5204876e+09 | AJ37: 3.7017742e+09 | AK37: 4.1836329e+09 | AL37: 4.105729e+09 | AM37: 4.0872202e+09 | AN37: 4.7341035e+09 | AO37: 5.1154541e+09 | AP37: 5.197312e+09 | AQ37: 4.0511424e+09 | AR37: 4.6001167e+09 | AS37: 6.0012821e+09 | AT37: 5.6010187e+09 | AU37: 5.8433683e+09 | AV37: 6.5573971e+09 | AW37: 7.8722028e+09 | AX37: 9.53142e+09 | AY37: 1.1470465e+10 | AZ37: 1.2247678e+10 | BA37: 1.4393434e+10 | BB37: 1.0732595e+10 | BC37: 1.370728e+10 | BD37: 1.8525129e+10 | BE37: 1.9048443e+10 | BF37: 1.8094322e+10 | BG37: 1.7097803e+10 | BH37: 1.2930291e+10 | BI37: 1.1400466e+10 | BJ37: 1.2128184e+10 | BK37: 1.3566938e+10 | BL37: 1.3469235e+10 | BM37: 1.20058e+10 | BN37: 1.4006497e+10 | BO37: 1.6681536e+10 | BP37: 1.5128293e+10
A38: Bhutan | B38: BTN | C38: GDP (current US$) | D38: NY.GDP.MKTP.CD | O38: 61812113 | P38: 66289450 | Q38: 70139867 | R38: 78900289 | S38: 92901785 | T38: 86820762 | U38: 88461263 | V38: 97884434 | W38: 94086228 | X38: 1.05378e+08 | Y38: 1.286692e+08 | Z38: 1.3917418e+08 | AA38: 1.4143932e+08 | AB38: 1.5670429e+08 | AC38: 1.6042349e+08 | AD38: 1.6328882e+08 | AE38: 1.9121812e+08 | AF38: 2.4274277e+08 | AG38: 2.7229807e+08 | AH38: 2.6479863e+08 | AI38: 2.8776501e+08 | AJ38: 2.4029429e+08 | AK38: 2.4023353e+08 | AL38: 2.2597369e+08 | AM38: 2.5895471e+08 | AN38: 2.9049098e+08 | AO38: 3.0340835e+08 | AP38: 3.5222908e+08 | AQ38: 3.6345838e+08 | AR38: 3.993112e+08 | AS38: 4.6073342e+08 | AT38: 4.9611023e+08 | AU38: 5.5934526e+08 | AV38: 6.5193543e+08 | AW38: 7.3534849e+08 | AX38: 8.60391e+08 | AY38: 9.4287988e+08 | AZ38: 1.255768e+09 | BA38: 1.3175178e+09 | BB38: 1.3313438e+09 | BC38: 1.6734643e+09 | BD38: 1.9384413e+09 | BE38: 1.9397307e+09 | BF38: 1.9131625e+09 | BG38: 2.0573309e+09 | BH38: 2.154921e+09 | BI38: 2.3227305e+09 | BJ38: 2.5913581e+09 | BK38: 2.5833357e+09 | BL38: 2.7356834e+09 | BM38: 2.457604e+09 | BN38: 2.7688028e+09 | BO38: 2.8982277e+09
A39: Botswana | B39: BWA | C39: GDP (current US$) | D39: NY.GDP.MKTP.CD | E39: 30411414 | F39: 32902613 | G39: 35644957 | H39: 38091843 | I39: 41616348 | J39: 45788696 | K39: 51465655 | L39: 58642354 | M39: 66248441 | N39: 77361547 | O39: 96243234 | P39: 1.2744861e+08 | Q39: 1.6446091e+08 | R39: 2.4412416e+08 | S39: 3.0604421e+08 | T39: 3.5516857e+08 | U39: 3.7202509e+08 | V39: 4.5162478e+08 | W39: 5.9040737e+08 | X39: 8.1987026e+08 | Y39: 1.0608897e+09 | Z39: 1.0738128e+09 | AA39: 1.0149457e+09 | AB39: 1.1722304e+09 | AC39: 1.2408222e+09 | AD39: 1.1147833e+09 | AE39: 1.3926022e+09 | AF39: 1.9652269e+09 | AG39: 2.6445542e+09 | AH39: 3.0838221e+09 | AI39: 3.7906363e+09 | AJ39: 3.9428767e+09 | AK39: 4.1464646e+09 | AL39: 4.1601292e+09 | AM39: 4.2592596e+09 | AN39: 4.7305991e+09 | AO39: 4.8477572e+09 | AP39: 5.0202656e+09 | AQ39: 4.7904815e+09 | AR39: 5.4842633e+09 | AS39: 5.7883296e+09 | AT39: 5.4896083e+09 | AU39: 5.438864e+09 | AV39: 7.5115822e+09 | AW39: 8.9574677e+09 | AX39: 9.9189071e+09 | AY39: 9.9191585e+09 | AZ39: 1.0567271e+10 | BA39: 1.0730829e+10 | BB39: 1.0118459e+10 | BC39: 1.2637273e+10 | BD39: 1.5110644e+10 | BE39: 1.3907465e+10 | BF39: 1.4271739e+10 | BG39: 1.5470089e+10 | BH39: 1.3530749e+10 | BI39: 1.5082637e+10 | BJ39: 1.6105156e+10 | BK39: 1.7031943e+10 | BL39: 1.6725908e+10 | BM39: 1.4960291e+10 | BN39: 1.8750947e+10 | BO39: 2.0321959e+10 | BP39: 1.9395765e+10
A40: Central African Republic | B40: CAF | C40: GDP (current US$) | D40: NY.GDP.MKTP.CD | E40: 1.121556e+08 | F40: 1.2313458e+08 | G40: 1.2448277e+08 | H40: 1.2937912e+08 | I40: 1.4202508e+08 | J40: 1.505748e+08 | K40: 1.5793002e+08 | L40: 1.6382051e+08 | M40: 1.9176744e+08 | N40: 1.8803921e+08 | O40: 1.8910653e+08 | P40: 2.014508e+08 | Q40: 2.3031788e+08 | R40: 2.7118308e+08 | S40: 2.8139871e+08 | T40: 3.7866002e+08 | U40: 4.5115246e+08 | V40: 5.0729815e+08 | W40: 6.1057863e+08 | X40: 7.0076475e+08 | Y40: 7.970482e+08 | Z40: 6.9480362e+08 | AA40: 7.4831239e+08 | AB40: 6.5867933e+08 | AC40: 6.3782067e+08 | AD40: 8.6484984e+08 | AE40: 1.122265e+09 | AF40: 1.200992e+09 | AG40: 1.2648993e+09 | AH40: 1.2339303e+09 | AI40: 1.4407115e+09 | AJ40: 1.377375e+09 | AK40: 1.4119176e+09 | AL40: 1.2787813e+09 | AM40: 8.5117436e+08 | AN40: 1.1153897e+09 | AO40: 1.0077911e+09 | AP40: 9.3774151e+08 | AQ40: 9.6733839e+08 | AR40: 9.9947751e+08 | AS40: 9.1677728e+08 | AT40: 9.326486e+08 | AU40: 9.9606814e+08 | AV40: 1.1423155e+09 | AW40: 1.2723605e+09 | AX40: 1.3378944e+09 | AY40: 1.4618598e+09 | AZ40: 1.6998113e+09 | BA40: 1.9934079e+09 | BB40: 2.0673817e+09 | BC40: 2.1425915e+09 | BD40: 2.4379827e+09 | BE40: 2.5101265e+09 | BF40: 1.6915441e+09 | BG40: 1.8948134e+09 | BH40: 1.6958257e+09 | BI40: 1.8250181e+09 | BJ40: 2.07235e+09 | BK40: 2.2209791e+09 | BL40: 2.2213014e+09 | BM40: 2.3267209e+09 | BN40: 2.5164984e+09 | BO40: 2.3826186e+09 | BP40: 2.5554921e+09
A41: Canada | B41: CAN | C41: GDP (current US$) | D41: NY.GDP.MKTP.CD | E41: 4.0563769e+10 | F41: 4.1038193e+10 | G41: 4.2336212e+10 | H41: 4.5140338e+10 | I41: 4.9503664e+10 | J41: 5.464941e+10 | K41: 6.1252415e+10 | L41: 6.5856924e+10 | M41: 7.2048833e+10 | N41: 7.9405011e+10 | O41: 8.8192258e+10 | P41: 9.9606455e+10 | Q41: 1.1346385e+11 | R41: 1.3176434e+11 | S41: 1.6094919e+11 | T41: 1.7441976e+11 | U41: 2.0727161e+11 | V41: 2.1232518e+11 | W41: 2.1936954e+11 | X41: 2.4389112e+11 | Y41: 2.7477657e+11 | Z41: 3.0724664e+11 | AA41: 3.1464781e+11 | AB41: 3.4186628e+11 | AC41: 3.567184e+11 | AD41: 3.6618601e+11 | AE41: 3.7900684e+11 | AF41: 4.3313424e+11 | AG41: 5.0938003e+11 | AH41: 5.6721199e+11 | AI41: 5.9607559e+11 | AJ41: 6.1252771e+11 | AK41: 5.9438736e+11 | AL41: 5.7905356e+11 | AM41: 5.7994435e+11 | AN41: 6.0596109e+11 | AO41: 6.3060799e+11 | AP41: 6.54987e+11 | AQ41: 634000000000 | AR41: 6.784122e+11 | AS41: 7.4477342e+11 | AT41: 7.3898179e+11 | AU41: 7.6064933e+11 | AV41: 8.9554065e+11 | AW41: 1.0266902e+12 | AX41: 1.1731086e+12 | AY41: 1.3192648e+12 | AZ41: 1.4688204e+12 | BA41: 1.5529897e+12 | BB41: 1.3746251e+12 | BC41: 1.6173434e+12 | BD41: 1.7933266e+12 | BE41: 1.8283665e+12 | BF41: 1.8465974e+12 | BG41: 1.8057499e+12 | BH41: 1.5565088e+12 | BI41: 1.5279947e+12 | BJ41: 1.6492656e+12 | BK41: 1.7253292e+12 | BL41: 1.7437252e+12 | BM41: 1.6556847e+12 | BN41: 2.0074722e+12 | BO41: 2.1614834e+12 | BP41: 2.1400856e+12
A42: Central Europe and the Baltics | B42: CEB | C42: GDP (current US$) | D42: NY.GDP.MKTP.CD | AI42: 2.7163712e+11 | AJ42: 2.4977019e+11 | AK42: 2.5644433e+11 | AL42: 2.6982667e+11 | AM42: 3.0802066e+11 | AN42: 3.9341819e+11 | AO42: 4.1619542e+11 | AP42: 4.1016936e+11 | AQ42: 4.4889452e+11 | AR42: 4.3506569e+11 | AS42: 4.2859756e+11 | AT42: 4.6861417e+11 | AU42: 5.2807438e+11 | AV42: 6.3439399e+11 | AW42: 7.6309045e+11 | AX42: 8.8607234e+11 | AY42: 1.0016372e+12 | AZ42: 1.2655657e+12 | BA42: 1.5307189e+12 | BB42: 1.2898536e+12 | BC42: 1.316548e+12 | BD42: 1.4547324e+12 | BE42: 1.3590529e+12 | BF42: 1.4175573e+12 | BG42: 1.463823e+12 | BH42: 1.2936233e+12 | BI42: 1.3168216e+12 | BJ42: 1.4615677e+12 | BK42: 1.6490142e+12 | BL42: 1.6748159e+12 | BM42: 1.6658175e+12 | BN42: 1.9082035e+12 | BO42: 1.943576e+12 | BP42: 2.2529709e+12
A43: Switzerland | B43: CHE | C43: GDP (current US$) | D43: NY.GDP.MKTP.CD | E43: 1.0412233e+10 | F43: 1.1713349e+10 | G43: 1.298965e+10 | H43: 1.4283872e+10 | I43: 1.5833134e+10 | J43: 1.6780226e+10 | K43: 1.8019402e+10 | L43: 1.9397045e+10 | M43: 2.0712103e+10 | N43: 2.2442043e+10 | O43: 2.4998067e+10 | P43: 3.0040172e+10 | Q43: 3.6844319e+10 | R43: 4.9550006e+10 | S43: 5.7103011e+10 | T43: 6.5466082e+10 | U43: 6.8476525e+10 | V43: 7.3135771e+10 | W43: 1.0228047e+11 | X43: 1.1497009e+11 | Y43: 1.2255784e+11 | Z43: 1.1224481e+11 | AA43: 1.1504337e+11 | AB43: 1.1463436e+11 | AC43: 1.0945531e+11 | AD43: 1.1098031e+11 | AE43: 1.5908992e+11 | AF43: 1.9923637e+11 | AG43: 2.1554063e+11 | AH43: 2.0810585e+11 | AI43: 2.6576357e+11 | AJ43: 2.6890169e+11 | AK43: 2.7992143e+11 | AL43: 2.7223753e+11 | AM43: 3.0137506e+11 | AN43: 3.5283581e+11 | AO43: 3.4010396e+11 | AP43: 2.947882e+11 | AQ43: 3.0345901e+11 | AR43: 2.9787364e+11 | AS43: 2.7921603e+11 | AT43: 2.8658267e+11 | AU43: 3.0930142e+11 | AV43: 3.6207509e+11 | AW43: 4.0391289e+11 | AX43: 4.1828487e+11 | AY43: 4.4163467e+11 | AZ43: 4.9074072e+11 | BA43: 5.6726777e+11 | BB43: 5.5421292e+11 | BC43: 5.9885103e+11 | BD43: 7.1588813e+11 | BE43: 6.8642022e+11 | BF43: 7.0623494e+11 | BG43: 726537808338 | BH43: 6.9411819e+11 | BI43: 6.8789546e+11 | BJ43: 6.9520083e+11 | BK43: 7.2556872e+11 | BL43: 7.2136911e+11 | BM43: 7.4199941e+11 | BN43: 8.1340879e+11 | BO43: 8.1842655e+11 | BP43: 8.849404e+11
A44: Channel Islands | B44: CHI | C44: GDP (current US$) | D44: NY.GDP.MKTP.CD | AQ44: 5.9456774e+09 | AR44: 6.2627407e+09 | AS44: 6.4397034e+09 | AT44: 6.2329063e+09 | AU44: 6.6636691e+09 | AV44: 7.3322449e+09 | AW44: 8.5536434e+09 | AX44: 8.8272727e+09 | AY44: 9.676173e+09 | AZ44: 1.1514606e+10 | BI44: 9.0720597e+09 | BJ44: 9.0709808e+09 | BK44: 9.9407666e+09 | BL44: 9.9213865e+09 | BM44: 9.3013492e+09 | BN44: 1.1138491e+10 | BO44: 1.1228317e+10
A45: Chile | B45: CHL | C45: GDP (current US$) | D45: NY.GDP.MKTP.CD | E45: 4110000000 | F45: 4.8292381e+09 | G45: 5.6312854e+09 | H45: 5.591307e+09 | I45: 5.9641959e+09 | J45: 6.1086791e+09 | K45: 7.1626331e+09 | L45: 7.0574783e+09 | M45: 7.192103e+09 | N45: 8.3595962e+09 | O45: 9.1441124e+09 | P45: 1.0876091e+10 | Q45: 1.1833904e+10 | R45: 1.6826391e+10 | S45: 1.6209693e+10 | T45: 7.6215701e+09 | U45: 1.0338624e+10 | V45: 1.3965595e+10 | W45: 1.5992039e+10 | X45: 2.1806136e+10 | Y45: 2.903671e+10 | Z45: 3.4509878e+10 | AA45: 1.9529291e+10 | AB45: 2.0362017e+10 | AC45: 1.9671768e+10 | AD45: 1.7717662e+10 | AE45: 1.8897111e+10 | AF45: 2.225073e+10 | AG45: 2.6042572e+10 | AH45: 2.9936735e+10 | AI45: 3.3137825e+10 | AJ45: 3.7846188e+10 | AK45: 4.5949609e+10 | AL45: 4.9287379e+10 | AM45: 5.6998601e+10 | AN45: 7.3444832e+10 | AO45: 7.8584099e+10 | AP45: 8.5741415e+10 | AQ45: 8.1990011e+10 | AR45: 7.5578686e+10 | AS45: 7.8339751e+10 | AT45: 7.157474e+10 | AU45: 7.0264046e+10 | AV45: 7.649258e+10 | AW45: 9.9075986e+10 | AX45: 1.2229415e+11 | AY45: 1.5384352e+11 | AZ45: 1.7249108e+11 | BA45: 1.7989459e+11 | BB45: 1.717779e+11 | BC45: 2.1705121e+11 | BD45: 2.5138257e+11 | BE45: 2.6702478e+11 | BF45: 2.7739502e+11 | BG45: 2.5956098e+11 | BH45: 2.4245036e+11 | BI45: 2.4934486e+11 | BJ45: 2.7615426e+11 | BK45: 2.9585756e+11 | BL45: 2.7828506e+11 | BM45: 2.5404216e+11 | BN45: 3.1551501e+11 | BO45: 3.0211654e+11 | BP45: 3.3553333e+11
A46: China | B46: CHN | C46: GDP (current US$) | D46: NY.GDP.MKTP.CD | E46: 5.9716249e+10 | F46: 5.0056686e+10 | G46: 4.7209186e+10 | H46: 5.0706615e+10 | I46: 5.9708125e+10 | J46: 7.0436009e+10 | K46: 7.6720005e+10 | L46: 7.2881365e+10 | M46: 7.0846276e+10 | N46: 7.9705615e+10 | O46: 9.2602635e+10 | P46: 9.9800594e+10 | Q46: 1.1368931e+11 | R46: 1.3854317e+11 | S46: 1.4418897e+11 | T46: 1.6342953e+11 | U46: 1.5393927e+11 | V46: 1.7493593e+11 | W46: 1.4954075e+11 | X46: 1.7828059e+11 | Y46: 191149211575 | Z46: 1.9586638e+11 | AA46: 2.050897e+11 | AB46: 2.3068675e+11 | AC46: 2.5994651e+11 | AD46: 3.0948803e+11 | AE46: 3.007581e+11 | AF46: 2.7297297e+11 | AG46: 3.1235363e+11 | AH46: 3.4776805e+11 | AI46: 3.6085791e+11 | AJ46: 3.8337332e+11 | AK46: 4.2691571e+11 | AL46: 4.4473128e+11 | AM46: 5.6432185e+11 | AN46: 7.3448483e+11 | AO46: 8.6374931e+11 | AP46: 9.6160198e+11 | AQ46: 1.0290607e+12 | AR46: 1.0940039e+12 | AS46: 1.2113317e+12 | AT46: 1.3394009e+12 | AU46: 1.4705577e+12 | AV46: 1.6602805e+12 | AW46: 1.9553468e+12 | AX46: 2.2859611e+12 | AY46: 2.7521187e+12 | AZ46: 3.5503278e+12 | BA46: 4.5943368e+12 | BB46: 5.1016911e+12 | BC46: 6.0871917e+12 | BD46: 7.5515457e+12 | BE46: 8.5321854e+12 | BF46: 9.5704711e+12 | BG46: 1.0475625e+13 | BH46: 1.1061573e+13 | BI46: 1.1233314e+13 | BJ46: 1.2310491e+13 | BK46: 1.3894908e+13 | BL46: 1.4279969e+13 | BM46: 14687744162801 | BN46: 1.782046e+13 | BO46: 1.7881783e+13 | BP46: 1.7794782e+13
A47: Cote d'Ivoire | B47: CIV | C47: GDP (current US$) | D47: NY.GDP.MKTP.CD | E47: 5.4620356e+08 | F47: 6.1824563e+08 | G47: 6.4528447e+08 | H47: 7.610472e+08 | I47: 9.2106333e+08 | J47: 9.1977123e+08 | K47: 1.0241029e+09 | L47: 1.0829227e+09 | M47: 1.2812813e+09 | N47: 1.3613603e+09 | O47: 1.4554828e+09 | P47: 1.5841285e+09 | Q47: 1.8494004e+09 | R47: 2.5084214e+09 | S47: 3.0701523e+09 | T47: 3.8938392e+09 | U47: 4.6620538e+09 | V47: 6.2650682e+09 | W47: 7.9005263e+09 | X47: 9.142934e+09 | Y47: 1.0175618e+10 | Z47: 8.4325899e+09 | AA47: 7.5671108e+09 | AB47: 6.8381848e+09 | AC47: 6.8416392e+09 | AD47: 6.9776506e+09 | AE47: 9.1583021e+09 | AF47: 1.0087654e+10 | AG47: 1.025517e+10 | AH47: 9.7574106e+09 | AI47: 1.0795851e+10 | AJ47: 1.0492629e+10 | AK47: 1.1152971e+10 | AL47: 1.104576e+10 | AM47: 8.3135575e+09 | AN47: 1.1000146e+10 | AO47: 1.8071153e+10 | AP47: 1.8047558e+10 | AQ47: 1.9619655e+10 | AR47: 1.8870992e+10 | AS47: 1.6577534e+10 | AT47: 1.6810537e+10 | AU47: 1.8054383e+10 | AV47: 2.1251754e+10 | AW47: 2.3510576e+10 | AX47: 2.4036919e+10 | AY47: 2.5281413e+10 | AZ47: 2.8760091e+10 | BA47: 3.407824e+10 | BB47: 3.3886813e+10 | BC47: 3.4936308e+10 | BD47: 3.6693711e+10 | BE47: 3.6302303e+10 | BF47: 4.2760235e+10 | BG47: 4.8843006e+10 | BH47: 4.5815005e+10 | BI47: 4.8407761e+10 | BJ47: 5.2512344e+10 | BK47: 5.8522478e+10 | BL47: 6.0382895e+10 | BM47: 6.3027853e+10 | BN47: 7.2794637e+10 | BO47: 7.017314e+10 | BP47: 7.8788829e+10
A48: Cameroon | B48: CMR | C48: GDP (current US$) | D48: NY.GDP.MKTP.CD | E48: 6.1420607e+08 | F48: 6.5277761e+08 | G48: 6.9424786e+08 | H48: 7.1832085e+08 | I48: 7.7665018e+08 | J48: 8.1408327e+08 | K48: 8.5111253e+08 | L48: 9.3617526e+08 | M48: 1.0461912e+09 | N48: 1.1005515e+09 | O48: 1.151217e+09 | P48: 1.2369414e+09 | Q48: 1.4982519e+09 | R48: 1.9013934e+09 | S48: 2.1574155e+09 | T48: 2.8570374e+09 | U48: 2.89809e+09 | V48: 3.394664e+09 | W48: 4.6628526e+09 | X48: 5.919003e+09 | Y48: 6.674569e+09 | Z48: 6.6109386e+09 | AA48: 6.611256e+09 | AB48: 6.8702e+09 | AC48: 7.311938e+09 | AD48: 8.5448105e+09 | AE48: 1.1857056e+10 | AF48: 1.304966e+10 | AG48: 1.2236057e+10 | AH48: 1.1012566e+10 | AI48: 1.2314483e+10 | AJ48: 1.1840192e+10 | AK48: 1.2071775e+10 | AL48: 1.6181815e+10 | AM48: 8.9024463e+09 | AN48: 1.0864772e+10 | AO48: 1.1093539e+10 | AP48: 1.0789458e+10 | AQ48: 1.1298145e+10 | AR48: 1.1565826e+10 | AS48: 1.0566579e+10 | AT48: 1.0953485e+10 | AU48: 1.2417251e+10 | AV48: 1.5970315e+10 | AW48: 1.8826214e+10 | AX48: 1.9509852e+10 | AY48: 2.0910513e+10 | AZ48: 2.392825e+10 | BA48: 2.7715142e+10 | BB48: 2.793297e+10 | BC48: 2.7507502e+10 | BD48: 3.0630911e+10 | BE48: 3.0155062e+10 | BF48: 3.3728621e+10 | BG48: 3.6386545e+10 | BH48: 3.2210233e+10 | BI48: 3.3814337e+10 | BJ48: 3.6098547e+10 | BK48: 3.9955552e+10 | BL48: 3.9667758e+10 | BM48: 4.0773241e+10 | BN48: 4.4993522e+10 | BO48: 4.3644068e+10 | BP48: 4.794551e+10
A49: Congo, Dem. Rep. | B49: COD | C49: GDP (current US$) | D49: NY.GDP.MKTP.CD | AK49: 8850000000 | AL49: 10768000000 | AM49: 5.8204757e+09 | AN49: 5.6434166e+09 | AO49: 5.771457e+09 | AP49: 6.0908387e+09 | AQ49: 6.2178058e+09 | AR49: 4.7112594e+09 | AS49: 1.9088046e+10 | AT49: 7.4381891e+09 | AU49: 8.7280385e+09 | AV49: 8.9375671e+09 | AW49: 1.0297483e+10 | AX49: 1.1964484e+10 | AY49: 1.4451902e+10 | AZ49: 1.6737072e+10 | BA49: 1.9788516e+10 | BB49: 1.8648373e+10 | BC49: 2.1565721e+10 | BD49: 2.5839749e+10 | BE49: 2.9306235e+10 | BF49: 3.2679745e+10 | BG49: 3.5909041e+10 | BH49: 3.7917706e+10 | BI49: 3.7134802e+10 | BJ49: 3.8019265e+10 | BK49: 4.756821e+10 | BL49: 5.177583e+10 | BM49: 4.8716962e+10 | BN49: 5.5328483e+10 | BO49: 6.5801548e+10 | BP49: 6.6383287e+10
A50: Congo, Rep. | B50: COG | C50: GDP (current US$) | D50: NY.GDP.MKTP.CD | E50: 1.3173186e+08 | F50: 1.5167574e+08 | G50: 1.6652124e+08 | H50: 1.7223343e+08 | I50: 1.8569372e+08 | J50: 1.9831806e+08 | K50: 2.2061358e+08 | L50: 2.3739743e+08 | M50: 2.5124746e+08 | N50: 2.6504004e+08 | O50: 2.749607e+08 | P50: 3.2212802e+08 | Q50: 4.1066926e+08 | R50: 5.4197336e+08 | S50: 5.8536463e+08 | T50: 7.6710268e+08 | U50: 7.545496e+08 | V50: 7.6522403e+08 | W50: 8.7877177e+08 | X50: 1.1987497e+09 | Y50: 1.7057969e+09 | Z50: 1.9935123e+09 | AA50: 2.1606406e+09 | AB50: 2.0972743e+09 | AC50: 2.1935814e+09 | AD50: 2.1608725e+09 | AE50: 1.8492682e+09 | AF50: 2.2977537e+09 | AG50: 2.2125363e+09 | AH50: 2.389593e+09 | AI50: 2.7987461e+09 | AJ50: 2.7248535e+09 | AK50: 2.9332227e+09 | AL50: 2.6843236e+09 | AM50: 1.7693654e+09 | AN50: 2.1160039e+09 | AO50: 2.5406975e+09 | AP50: 2.3227191e+09 | AQ50: 1.9494814e+09 | AR50: 2.354773e+09 | AS50: 3.2279277e+09 | AT50: 2.7967046e+09 | AU50: 3.0342509e+09 | AV50: 3.5037231e+09 | AW50: 4.6569749e+09 | AX50: 6.6500017e+09 | AY50: 8.072305e+09 | AZ50: 8.7827034e+09 | BA50: 1.1649858e+10 | BB50: 9.7232999e+09 | BC50: 1.3148396e+10 | BD50: 1.5655384e+10 | BE50: 1.7692911e+10 | BF50: 1.7958721e+10 | BG50: 1.7919321e+10 | BH50: 1.2434794e+10 | BI50: 1.0931328e+10 | BJ50: 1.1834473e+10 | BK50: 1.47739e+10 | BL50: 1.3976637e+10 | BM50: 1.1468688e+10 | BN50: 1.482569e+10 | BO50: 1.581703e+10 | BP50: 1.5321056e+10
A51: Colombia | B51: COL | C51: GDP (current US$) | D51: NY.GDP.MKTP.CD | E51: 4.031153e+09 | F51: 4.5404478e+09 | G51: 4.9555382e+09 | H51: 4.8361667e+09 | I51: 5.9733667e+09 | J51: 5.7607619e+09 | K51: 5.4285185e+09 | L51: 5.8251704e+09 | M51: 5.9602129e+09 | N51: 6.4501752e+09 | O51: 7.1983605e+09 | P51: 7.820381e+09 | Q51: 8.6713587e+09 | R51: 1.031576e+10 | S51: 1.237003e+10 | T51: 1.3098634e+10 | U51: 1.5341404e+10 | V51: 1.9470961e+10 | W51: 2.3263512e+10 | X51: 2.7940411e+10 | Y51: 3.3400736e+10 | Z51: 3.6388367e+10 | AA51: 3.896804e+10 | AB51: 3.8729823e+10 | AC51: 3.8253121e+10 | AD51: 3.4894419e+10 | AE51: 3.494249e+10 | AF51: 3.6373307e+10 | AG51: 3.921255e+10 | AH51: 3.954008e+10 | AI51: 4.7844091e+10 | AJ51: 4.9637994e+10 | AK51: 5.8394443e+10 | AL51: 6.6474101e+10 | AM51: 8.1705498e+10 | AN51: 9.2495971e+10 | AO51: 9.7153389e+10 | AP51: 1.0665649e+11 | AQ51: 9.8486359e+10 | AR51: 8.6278948e+10 | AS51: 9.9875075e+10 | AT51: 9.8200641e+10 | AU51: 9.7945813e+10 | AV51: 9.4644969e+10 | AW51: 1.1709242e+11 | AX51: 1.4560053e+11 | AY51: 1.6179296e+11 | AZ51: 2.0622954e+11 | BA51: 2.4250415e+11 | BB51: 2.3246866e+11 | BC51: 2.8649853e+11 | BD51: 3.3496613e+11 | BE51: 3.7069114e+11 | BF51: 3.820937e+11 | BG51: 3.8124086e+11 | BH51: 2.9349237e+11 | BI51: 2.827201e+11 | BJ51: 3.1186688e+11 | BK51: 3.3419822e+11 | BL51: 3.230317e+11 | BM51: 2.7034834e+11 | BN51: 3.1852463e+11 | BO51: 3.4532988e+11 | BP51: 3.6354016e+11
A52: Comoros | B52: COM | C52: GDP (current US$) | D52: NY.GDP.MKTP.CD | Y52: 2.1221826e+08 | Z52: 1.9634993e+08 | AA52: 1.8400901e+08 | AB52: 1.9162195e+08 | AC52: 1.8469723e+08 | AD52: 1.967261e+08 | AE52: 2.7919772e+08 | AF52: 3.3752585e+08 | AG52: 3.5650003e+08 | AH52: 3.4147677e+08 | AI52: 4.2962218e+08 | AJ52: 4.2410877e+08 | AK52: 4.5738865e+08 | AL52: 4.5288148e+08 | AM52: 3.1918918e+08 | AN52: 3.984618e+08 | AO52: 3.9605381e+08 | AP52: 3.644456e+08 | AQ52: 3.7010675e+08 | AR52: 3.8245499e+08 | AS52: 3.5113658e+08 | AT52: 3.7851202e+08 | AU52: 4.2596468e+08 | AV52: 5.4688522e+08 | AW52: 6.3370611e+08 | AX52: 6.5384517e+08 | AY52: 6.9843179e+08 | AZ52: 7.9567315e+08 | BA52: 9.1565911e+08 | BB52: 9.0534117e+08 | BC52: 9.0797873e+08 | BD52: 1.0230863e+09 | BE52: 1.0158435e+09 | BF52: 1.1162241e+09 | BG52: 1.1495877e+09 | BH52: 9.660296e+08 | BI52: 1.0128355e+09 | BJ52: 1.0774398e+09 | BK52: 1.1887974e+09 | BL52: 1.1950195e+09 | BM52: 1.2250392e+09 | BN52: 1.2960895e+09 | BO52: 1.2425194e+09 | BP52: 1.352381e+09
A53: Cabo Verde | B53: CPV | C53: GDP (current US$) | D53: NY.GDP.MKTP.CD | Y53: 1.4224682e+08 | Z53: 1.3946821e+08 | AA53: 1.4063068e+08 | AB53: 1.3847618e+08 | AC53: 1.3201904e+08 | AD53: 1.377282e+08 | AE53: 1.9065117e+08 | AF53: 2.3525306e+08 | AG53: 2.6430814e+08 | AH53: 2.6744857e+08 | AI53: 3.0689096e+08 | AJ53: 3.1982706e+08 | AK53: 3.5716099e+08 | AL53: 4.9041739e+08 | AM53: 4.0658065e+08 | AN53: 4.8714899e+08 | AO53: 5.0197927e+08 | AP53: 4.9060866e+08 | AQ53: 5.2191056e+08 | AR53: 5.924167e+08 | AS53: 5.3922728e+08 | AT53: 5.6309049e+08 | AU53: 6.2050739e+08 | AV53: 8.1326047e+08 | AW53: 9.2494001e+08 | AX53: 9.7224168e+08 | AY53: 1.1075715e+09 | AZ53: 1.6496217e+09 | BA53: 1.9596206e+09 | BB53: 1.8523346e+09 | BC53: 1.8247515e+09 | BD53: 2.046818e+09 | BE53: 1.9130812e+09 | BF53: 2.0289109e+09 | BG53: 2.0419301e+09 | BH53: 1.7498576e+09 | BI53: 1.84979e+09 | BJ53: 1.9967415e+09 | BK53: 2.2050995e+09 | BL53: 2.2521771e+09 | BM53: 1.8215656e+09 | BN53: 2.0518426e+09 | BO53: 2.303738e+09 | BP53: 2.5872521e+09
A54: Costa Rica | B54: CRI | C54: GDP (current US$) | D54: NY.GDP.MKTP.CD | E54: 5.0751383e+08 | F54: 4.9032518e+08 | G54: 4.7918082e+08 | H54: 5.1190214e+08 | I54: 5.4257837e+08 | J54: 5.9298116e+08 | K54: 6.4730563e+08 | L54: 6.9945662e+08 | M54: 7.7384149e+08 | N54: 8.536302e+08 | O54: 9.8483016e+08 | P54: 1.0771475e+09 | Q54: 1.2382517e+09 | R54: 1.5289258e+09 | S54: 1.6665448e+09 | T54: 1.9608635e+09 | U54: 2.4125554e+09 | V54: 3.072427e+09 | W54: 3.5232088e+09 | X54: 4.0355193e+09 | Y54: 4.831447e+09 | Z54: 2.6238031e+09 | AA54: 2.6066236e+09 | AB54: 3.1467726e+09 | AC54: 3.6604779e+09 | AD54: 3.919204e+09 | AE54: 4.4189839e+09 | AF54: 4.532952e+09 | AG54: 4.6146299e+09 | AH54: 5.2510258e+09 | AI54: 5.7116878e+09 | AJ54: 7.1962761e+09 | AK54: 8.5640419e+09 | AL54: 9.5828685e+09 | AM54: 1.0486787e+10 | AN54: 1.1578594e+10 | AO54: 1.1678425e+10 | AP54: 1.2614602e+10 | AQ54: 1.3684256e+10 | AR54: 1.4254866e+10 | AS54: 1.501363e+10 | AT54: 1.5976174e+10 | AU54: 1.6578821e+10 | AV54: 1.7271761e+10 | AW54: 1.8610595e+10 | AX54: 2.0040642e+10 | AY54: 2.271554e+10 | AZ54: 2.68847e+10 | BA54: 3.0801745e+10 | BB54: 3.0745714e+10 | BC54: 3.7658615e+10 | BD54: 4.2762614e+10 | BE54: 4.7231655e+10 | BF54: 5.0949669e+10 | BG54: 5.2016409e+10 | BH54: 5.6441921e+10 | BI54: 5.884702e+10 | BJ54: 6.0516045e+10 | BK54: 6.2420165e+10 | BL54: 6.4417671e+10 | BM54: 6.2395611e+10 | BN54: 6.4960726e+10 | BO54: 6.9243626e+10 | BP54: 8.6497941e+10
A55: Caribbean small states | B55: CSS | C55: GDP (current US$) | D55: NY.GDP.MKTP.CD | E55: 6.415392e+08 | F55: 7.0003215e+08 | G55: 7.5107076e+08 | H55: 7.8305522e+08 | I55: 8.5001307e+08 | J55: 9.419558e+08 | K55: 1.0602117e+09 | L55: 1.1938093e+09 | M55: 1.2498272e+09 | N55: 1.4084161e+09 | O55: 1.4946448e+09 | P55: 1.6139573e+09 | Q55: 1.6995304e+09 | R55: 1.9147149e+09 | S55: 2.1887792e+09 | T55: 2.3990295e+09 | U55: 2.4599921e+09 | V55: 2.8103592e+09 | W55: 3.2279774e+09 | X55: 3.8135129e+09 | Y55: 4.5810347e+09 | Z55: 4.9207087e+09 | AA55: 5.085934e+09 | AB55: 5.3552364e+09 | AC55: 5.8559968e+09 | AD55: 6.3440265e+09 | AE55: 6.899365e+09 | AF55: 7.446648e+09 | AG55: 8.147438e+09 | AH55: 8.1612217e+09 | AI55: 8.5042766e+09 | AJ55: 8.6372548e+09 | AK55: 8.8012884e+09 | AL55: 9.1440762e+09 | AM55: 9.8391996e+09 | AN55: 1.0400848e+10 | AO55: 1.1180259e+10 | AP55: 1.4335075e+10 | AQ55: 1.5597596e+10 | AR55: 1.6582094e+10 | AS55: 1.7467368e+10 | AT55: 1.7638376e+10 | AU55: 1.8687789e+10 | AV55: 1.9248879e+10 | AW55: 2.0281938e+10 | AX55: 2.2208371e+10 | AY55: 2.5923715e+10 | AZ55: 2.8067234e+10 | BA55: 2.939628e+10 | BB55: 2.8708191e+10 | BC55: 2.9715534e+10 | BD55: 3.0344564e+10 | BE55: 3.2052386e+10 | BF55: 3.2390809e+10 | BG55: 3.3462282e+10 | BH55: 3.4538256e+10 | BI55: 3.3451253e+10 | BJ55: 3.4921587e+10 | BK55: 3.6225417e+10 | BL55: 3.762101e+10 | BM55: 3.137803e+10 | BN55: 3.6706593e+10 | BO55: 4.8138054e+10 | BP55: 5.3252638e+10
A56: Cuba | B56: CUB | C56: GDP (current US$) | D56: NY.GDP.MKTP.CD | O56: 5693005200 | P56: 6914658400 | Q56: 8.1351509e+09 | R56: 9.9877097e+09 | S56: 1.1405957e+10 | T56: 1.3027415e+10 | U56: 1.378958e+10 | V56: 1.4206159e+10 | W56: 1.7844705e+10 | X56: 1.9584443e+10 | Y56: 1.991289e+10 | Z56: 2.0150254e+10 | AA56: 2.095351e+10 | AB56: 2.2204941e+10 | AC56: 2.4039384e+10 | AD56: 2.2920491e+10 | AE56: 2.4226575e+10 | AF56: 2.5213935e+10 | AG56: 2.7458999e+10 | AH56: 2.7023469e+10 | AI56: 2.8645437e+10 | AJ56: 2.4316556e+10 | AK56: 2.2085858e+10 | AL56: 2.2367255e+10 | AM56: 2.8448327e+10 | AN56: 3.0429804e+10 | AO56: 25017368700 | AP56: 25365908100 | AQ56: 25736331200 | AR56: 28364615200 | AS56: 30565400000 | AT56: 31682400000 | AU56: 33590500000 | AV56: 35901200000 | AW56: 38203000000 | AX56: 42643836100 | AY56: 4.8835926e+10 | AZ56: 5.426287e+10 | BA56: 5.630213e+10 | BB56: 5.7481481e+10 | BC56: 5.9562963e+10 | BD56: 68990000000 | BE56: 73141000000 | BF56: 77148000000 | BG56: 80656100000 | BH56: 87132800000 | BI56: 9.1370408e+10 | BJ56: 9.685065e+10 | BK56: 1.0005004e+11 | BL56: 103427600000 | BM56: 107351800000
A57: Curacao | B57: CUW | C57: GDP (current US$) | D57: NY.GDP.MKTP.CD | BD57: 2.9300922e+09 | BE57: 3.0128363e+09 | BF57: 3.0335686e+09 | BG57: 3.059407e+09 | BH57: 3.0587792e+09 | BI57: 3.0246902e+09 | BJ57: 3.0334332e+09 | BK57: 3.0463648e+09 | BL57: 3.0261241e+09 | BM57: 2.5343276e+09 | BN57: 2.7396081e+09 | BO57: 3.0738403e+09
A58: Cayman Islands | B58: CYM | C58: GDP (current US$) | D58: NY.GDP.MKTP.CD | AY58: 4.2002883e+09 | AZ58: 4.466278e+09 | BA58: 4.585949e+09 | BB58: 4.2817146e+09 | BC58: 4.1568412e+09 | BD58: 4.1860732e+09 | BE58: 4.2910045e+09 | BF58: 4.4057961e+09 | BG58: 4.5628536e+09 | BH58: 4.7081673e+09 | BI58: 4.9093222e+09 | BJ58: 5.1662813e+09 | BK58: 5.5301785e+09 | BL58: 5.9418966e+09 | BM58: 5.655358e+09 | BN58: 6.0600265e+09 | BO58: 6.600844e+09
A59: Cyprus | B59: CYP | C59: GDP (current US$) | D59: NY.GDP.MKTP.CD | T59: 4.8991476e+08 | U59: 5.7609007e+08 | V59: 7.3488797e+08 | W59: 9.6402651e+08 | X59: 1.2887152e+09 | Y59: 2.1543113e+09 | Z59: 2.0874964e+09 | AA59: 2.1592424e+09 | AB59: 2.1603641e+09 | AC59: 2.278249e+09 | AD59: 2.4304119e+09 | AE59: 3.0907345e+09 | AF59: 3.7048139e+09 | AG59: 4.2787926e+09 | AH59: 4.5634826e+09 | AI59: 5.5911302e+09 | AJ59: 5.7701973e+09 | AK59: 6.9121505e+09 | AL59: 6.590291e+09 | AM59: 7.4257039e+09 | AN59: 9.9331332e+09 | AO59: 1.0011918e+10 | AP59: 9.5478187e+09 | AQ59: 1.0248618e+10 | AR59: 1.0497908e+10 | AS59: 9.9858445e+09 | AT59: 1.0397897e+10 | AU59: 1.1420228e+10 | AV59: 1.4547325e+10 | AW59: 17320552500 | AX59: 1.8433411e+10 | AY59: 2.0072786e+10 | AZ59: 2.3968764e+10 | BA59: 2.7844699e+10 | BB59: 2.6048249e+10 | BC59: 2.579994e+10 | BD59: 2.7641552e+10 | BE59: 2.5047433e+10 | BF59: 2.3959709e+10 | BG59: 2.3225912e+10 | BH59: 1.9909269e+10 | BI59: 2.1046452e+10 | BJ59: 2.2946583e+10 | BK59: 2.5597301e+10 | BL59: 2.594702e+10 | BM59: 2.522719e+10 | BN59: 2.9482913e+10 | BO59: 2.9250532e+10 | BP59: 3.2229623e+10
A60: Czechia | B60: CZE | C60: GDP (current US$) | D60: NY.GDP.MKTP.CD | AI60: 4.0728951e+10 | AJ60: 2.9859921e+10 | AK60: 3.4805013e+10 | AL60: 4.0866749e+10 | AM60: 4.7850204e+10 | AN60: 6.0147174e+10 | AO60: 6.7387789e+10 | AP60: 6.2180159e+10 | AQ60: 6.680743e+10 | AR60: 6.5173131e+10 | AS60: 6.1828166e+10 | AT60: 6.7808033e+10 | AU60: 8.2196001e+10 | AV60: 1.0009047e+11 | AW60: 1.1981443e+11 | AX60: 1.3714347e+11 | AY60: 1.562641e+11 | AZ60: 1.901838e+11 | BA60: 2.3681649e+11 | BB60: 2.074343e+11 | BC60: 2.0906994e+11 | BD60: 2.2956273e+11 | BE60: 2.0885772e+11 | BF60: 2.1168562e+11 | BG60: 2.0935883e+11 | BH60: 1.8803305e+11 | BI60: 1.9627207e+11 | BJ60: 2.1862894e+11 | BK60: 2.4900054e+11 | BL60: 2.5254818e+11 | BM60: 2.4597456e+11 | BN60: 2.8179122e+11 | BO60: 2.9056565e+11 | BP60: 3.3085834e+11
A61: Germany | B61: DEU | C61: GDP (current US$) | D61: NY.GDP.MKTP.CD | E61: 8.431095e+10 | F61: 9.6205729e+10 | G61: 1.0550888e+11 | H61: 1.1182281e+11 | I61: 1.228802e+11 | J61: 1.3428271e+11 | K61: 1.4278116e+11 | L61: 1.4457099e+11 | M61: 1.5595591e+11 | N61: 1.7708469e+11 | O61: 2.1583845e+11 | P61: 2.4998506e+11 | Q61: 2.9980154e+11 | R61: 3.9837402e+11 | S61: 4.4530348e+11 | T61: 4.9063652e+11 | U61: 5.1975445e+11 | V61: 6.0049824e+11 | W61: 7.4046998e+11 | X61: 8.8134518e+11 | Y61: 9.5029086e+11 | Z61: 8.0047206e+11 | AA61: 7.7657644e+11 | AB61: 7.7068432e+11 | AC61: 7.2511112e+11 | AD61: 7.3253489e+11 | AE61: 1.0462594e+12 | AF61: 1.2981761e+12 | AG61: 1.4012332e+12 | AH61: 1.3989674e+12 | AI61: 1.7716712e+12 | AJ61: 1.8689452e+12 | AK61: 2.1315717e+12 | AL61: 2.0713238e+12 | AM61: 2.2050741e+12 | AN61: 2.5857923e+12 | AO61: 2.4972446e+12 | AP61: 2.2119896e+12 | AQ61: 2.2389908e+12 | AR61: 2.1949453e+12 | AS61: 1.947982e+12 | AT61: 1.945791e+12 | AU61: 2.0784845e+12 | AV61: 2.5016404e+12 | AW61: 2.8143539e+12 | AX61: 2.8468642e+12 | AY61: 2.9947036e+12 | AZ61: 3.4255784e+12 | BA61: 3.7452641e+12 | BB61: 3.4112612e+12 | BC61: 3.3996678e+12 | BD61: 3.749315e+12 | BE61: 3.5271432e+12 | BF61: 3.7338046e+12 | BG61: 3.8890931e+12 | BH61: 3.3575857e+12 | BI61: 3.4698535e+12 | BJ61: 3.6908492e+12 | BK61: 3.9744434e+12 | BL61: 3.8891776e+12 | BM61: 3.8877272e+12 | BN61: 4.2785039e+12 | BO61: 4.0824695e+12 | BP61: 4.456081e+12
A62: Djibouti | B62: DJI | C62: GDP (current US$) | D62: NY.GDP.MKTP.CD | AD62: 3.4098953e+08 | AF62: 3.7337174e+08 | AG62: 3.9579454e+08 | AH62: 4.0922009e+08 | AI62: 4.5232809e+08 | AJ62: 4.62422e+08 | AK62: 4.780583e+08 | AL62: 4.6604847e+08 | AM62: 4.9168922e+08 | AN62: 4.9772396e+08 | AO62: 4.9400465e+08 | AP62: 5.0267554e+08 | AQ62: 5.1426787e+08 | AR62: 5.3608015e+08 | AS62: 5.5123086e+08 | AT62: 5.7241744e+08 | AU62: 5.9112204e+08 | AV62: 6.2204467e+08 | AW62: 6.660721e+08 | AX62: 7.0863319e+08 | AY62: 7.6887368e+08 | AZ62: 8.4791893e+08 | BA62: 9.9910534e+08 | BB62: 1.0491107e+09 | BC62: 1.1286117e+09 | BD62: 1.2391445e+09 | BE62: 1.3536329e+09 | BF62: 2.0428172e+09 | BG62: 2.2146791e+09 | BH62: 2.4243918e+09 | BI62: 2.6049552e+09 | BJ62: 2.7625813e+09 | BK62: 2.9134667e+09 | BL62: 3.0888536e+09 | BM62: 3.185151e+09 | BN62: 3.3858252e+09 | BO62: 3.6742985e+09 | BP62: 4.0985305e+09
A63: Dominica | B63: DMA | C63: GDP (current US$) | D63: NY.GDP.MKTP.CD | V63: 45872947 | W63: 57130216 | X63: 55017759 | Y63: 72804653 | Z63: 82107391 | AA63: 89527577 | AB63: 98665191 | AC63: 1.0915707e+08 | AD63: 1.1949193e+08 | AE63: 1.3516196e+08 | AF63: 1.5186875e+08 | AG63: 1.7110618e+08 | AH63: 1.8513724e+08 | AI63: 2.0142963e+08 | AJ63: 2.1976296e+08 | AK63: 2.3405926e+08 | AL63: 2.4552593e+08 | AM63: 2.6437407e+08 | AN63: 2.7452222e+08 | AO63: 2.9228519e+08 | AP63: 3.0298889e+08 | AQ63: 3.2241111e+08 | AR63: 3.3175926e+08 | AS63: 3.3347037e+08 | AT63: 3.402037e+08 | AU63: 3.331963e+08 | AV63: 3.4331111e+08 | AW63: 367200000 | AX63: 3.6425556e+08 | AY63: 3.9025185e+08 | AZ63: 4.2137407e+08 | BA63: 4.5818889e+08 | BB63: 4.8907407e+08 | BC63: 4.9382593e+08 | BD63: 5.0102593e+08 | BE63: 4.859963e+08 | BF63: 4.982963e+08 | BG63: 5.2042963e+08 | BH63: 5.4073704e+08 | BI63: 5.7622963e+08 | BJ63: 5.2155185e+08 | BK63: 5.5477037e+08 | BL63: 6.1153704e+08 | BM63: 5.0421481e+08 | BN63: 5.5526667e+08 | BO63: 6.0715926e+08 | BP63: 6.5399259e+08
A64: Denmark | B64: DNK | C64: GDP (current US$) | D64: NY.GDP.MKTP.CD | E64: 6.3611663e+09 | F64: 7.058361e+09 | G64: 7.9532745e+09 | H64: 8.4660447e+09 | I64: 9.677401e+09 | J64: 1.087067e+10 | K64: 1.193174e+10 | L64: 1.3059064e+10 | M64: 1.3505574e+10 | N64: 1.5414902e+10 | O64: 17075457600 | P64: 1.9085731e+10 | Q64: 2.323238e+10 | R64: 3.0730627e+10 | S64: 3.4160445e+10 | T64: 4.0474406e+10 | U64: 4.4575892e+10 | V64: 4.9784339e+10 | W64: 6.0362932e+10 | X64: 7.0366242e+10 | Y64: 7.1127529e+10 | Z64: 6.1877814e+10 | AA64: 6.0412845e+10 | AB64: 6.0644782e+10 | AC64: 5.9105237e+10 | AD64: 6.2658568e+10 | AE64: 8.807876e+10 | AF64: 1.0941442e+11 | AG64: 1.1555285e+11 | AH64: 1.1240922e+11 | AI64: 1.3824729e+11 | AJ64: 1.3922469e+11 | AK64: 1.5291565e+11 | AL64: 1.4319563e+11 | AM64: 1.5616239e+11 | AN64: 1.8500688e+11 | AO64: 1.8763235e+11 | AP64: 1.7353765e+11 | AQ64: 1.7699193e+11 | AR64: 1.7796519e+11 | AS64: 1.6415874e+11 | AT64: 1.6479144e+11 | AU64: 1.7863516e+11 | AV64: 2.1809603e+11 | AW64: 2.51373e+11 | AX64: 2.6446734e+11 | AY64: 2.8288495e+11 | AZ64: 3.1942342e+11 | BA64: 3.5336104e+11 | BB64: 3.212413e+11 | BC64: 3.2199528e+11 | BD64: 3.4400314e+11 | BE64: 3.2714894e+11 | BF64: 3.4358439e+11 | BG64: 3.5299363e+11 | BH64: 3.0267307e+11 | BI64: 3.1311593e+11 | BJ64: 3.3212106e+11 | BK64: 3.5684122e+11 | BL64: 3.4649874e+11 | BM64: 3.5476275e+11 | BN64: 4.05688e+11 | BO64: 4.001672e+11 | BP64: 4.0419876e+11
A65: Dominican Republic | B65: DOM | C65: GDP (current US$) | D65: NY.GDP.MKTP.CD | E65: 672399700 | F65: 654100200 | G65: 824100000 | H65: 940799900 | I65: 1025599900 | J65: 888100000 | K65: 983900000 | L65: 1034800000 | M65: 1079100000 | N65: 1230500000 | O65: 1485500000 | P65: 1666500000 | Q65: 1987400000 | R65: 2344800000 | S65: 2925700000 | T65: 3599200000 | U65: 3951500000 | V65: 4587100000 | W65: 4734400000 | X65: 5498800000 | Y65: 6761300000 | Z65: 7561300000 | AA65: 8267400000 | AB65: 9220600000 | AC65: 11594000000 | AD65: 5.04458e+09 | AE65: 6.1221286e+09 | AF65: 5.8270508e+09 | AG65: 5.3743e+09 | AH65: 6.6865931e+09 | AI65: 7.0736755e+09 | AJ65: 9.8244833e+09 | AK65: 11605382504 | AL65: 13081042400 | AM65: 1.4644735e+10 | AN65: 1.6637371e+10 | AO65: 1.8241623e+10 | AP65: 2.001745e+10 | AQ65: 2.1672216e+10 | AR65: 2.2136579e+10 | AS65: 2.4305781e+10 | AT65: 2.5601824e+10 | AU65: 2.7137441e+10 | AV65: 2.1403168e+10 | AW65: 2.2322387e+10 | AX65: 3.5777561e+10 | AY65: 3.787983e+10 | AZ65: 4.3965459e+10 | BA65: 4.8122602e+10 | BB65: 4.8261079e+10 | BC65: 5.3860187e+10 | BD65: 5.8029774e+10 | BE65: 6.0681536e+10 | BF65: 6.2682159e+10 | BG65: 6.7179956e+10 | BH65: 7.1164827e+10 | BI65: 7.5704648e+10 | BJ65: 7.9998046e+10 | BK65: 8.555539e+10 | BL65: 8.8941373e+10 | BM65: 7.8844656e+10 | BN65: 9.4243426e+10 | BO65: 1.1353737e+11 | BP65: 1.2144428e+11
A66: Algeria | B66: DZA | C66: GDP (current US$) | D66: NY.GDP.MKTP.CD | E66: 2.7236155e+09 | F66: 2.4347471e+09 | G66: 2.0014445e+09 | H66: 2.702982e+09 | I66: 2.9093164e+09 | J66: 3.1362843e+09 | K66: 3.0398592e+09 | L66: 3.3708704e+09 | M66: 3.852147e+09 | N66: 4.2572533e+09 | O66: 4.8635269e+09 | P66: 5.0771831e+09 | Q66: 6.766744e+09 | R66: 8.7078589e+09 | S66: 1.3209872e+10 | T66: 1.5557903e+10 | U66: 1.7728241e+10 | V66: 2.0972114e+10 | W66: 2.6364491e+10 | X66: 3.3243707e+10 | Y66: 4.2345829e+10 | Z66: 4.434859e+10 | AA66: 4.5207167e+10 | AB66: 4.880137e+10 | AC66: 5.3698548e+10 | AD66: 5.7937869e+10 | AE66: 6.3692008e+10 | AF66: 6.6745818e+10 | AG66: 5.9089397e+10 | AH66: 5.5634722e+10 | AI66: 6.2048508e+10 | AJ66: 4.5715676e+10 | AK66: 4.8003133e+10 | AL66: 4.9945584e+10 | AM66: 4.2543177e+10 | AN66: 4.1764292e+10 | AO66: 4.6941554e+10 | AP66: 4.8177612e+10 | AQ66: 4.8187782e+10 | AR66: 4.8640672e+10 | AS66: 5.4790399e+10 | AT66: 5.9413401e+10 | AU66: 6.1516103e+10 | AV66: 7.3482264e+10 | AW66: 9.1913681e+10 | AX66: 1.0704662e+11 | AY66: 1.2308426e+11 | AZ66: 1.4248274e+11 | BA66: 1.8038385e+11 | BB66: 1.5031729e+11 | BC66: 1.7778505e+11 | BD66: 2.1833195e+11 | BE66: 2.2714375e+11 | BF66: 2.2970143e+11 | BG66: 2.3894266e+11 | BH66: 1.8749386e+11 | BI66: 1.8076384e+11 | BJ66: 1.898809e+11 | BK66: 1.9455448e+11 | BL66: 1.9345966e+11 | BM66: 1.6487342e+11 | BN66: 1.8626542e+11 | BO66: 2.2556026e+11 | BP66: 2.3989949e+11
A67: East Asia & Pacific (excluding high income) | B67: EAP | C67: GDP (current US$) | D67: NY.GDP.MKTP.CD | E67: 8.0767959e+10 | F67: 7.1153219e+10 | G67: 6.4897471e+10 | H67: 7.0193946e+10 | I67: 8.1084336e+10 | J67: 9.4481208e+10 | K67: 1.0336773e+11 | L67: 1.0036307e+11 | M67: 1.0146507e+11 | N67: 1.1409675e+11 | O67: 1.2705593e+11 | P67: 1.3644738e+11 | Q67: 1.5536511e+11 | R67: 1.9543417e+11 | S67: 2.2149089e+11 | T67: 2.4856776e+11 | U67: 2.5273681e+11 | V67: 2.9129981e+11 | W67: 2.8273009e+11 | X67: 3.2736171e+11 | Y67: 3.7767512e+11 | Z67: 4.0320226e+11 | AA67: 4.2346078e+11 | AB67: 4.4339666e+11 | AC67: 4.8041879e+11 | AD67: 5.2602314e+11 | AE67: 5.2463008e+11 | AF67: 5.1855054e+11 | AG67: 5.7559095e+11 | AH67: 6.2222309e+11 | AI67: 6.667072e+11 | AJ67: 7.2351641e+11 | AK67: 8.1140624e+11 | AL67: 8.9061818e+11 | AM67: 1.071871e+12 | AN67: 1.3220312e+12 | AO67: 1.5183294e+12 | AP67: 1.5706086e+12 | AQ67: 1.4332033e+12 | AR67: 1.5779181e+12 | AS67: 1.736143e+12 | AT67: 1.8471195e+12 | AU67: 2.0443603e+12 | AV67: 2.3138626e+12 | AW67: 2.6829371e+12 | AX67: 3.1076948e+12 | AY67: 3.7427743e+12 | AZ67: 4.7317731e+12 | BA67: 5.9870964e+12 | BB67: 6.4912585e+12 | BC67: 7.9005415e+12 | BD67: 9.6506937e+12 | BE67: 10759908112898 | BF67: 1.187006e+13 | BG67: 1.2800187e+13 | BH67: 13323235973753 | BI67: 1.3614573e+13 | BJ67: 1.4881098e+13 | BK67: 1.6640355e+13 | BL67: 1.7213216e+13 | BM67: 1.7487335e+13 | BN67: 2.0840018e+13 | BO67: 2.1113809e+13 | BP67: 2.1150248e+13
A68: Early-demographic dividend | B68: EAR | C68: GDP (current US$) | D68: NY.GDP.MKTP.CD | E68: 1.3163708e+11 | F68: 1.4003672e+11 | G68: 1.4418989e+11 | H68: 1.6180103e+11 | I68: 1.80039e+11 | J68: 1.9412879e+11 | K68: 1.905069e+11 | L68: 2.0804384e+11 | M68: 2.2793469e+11 | N68: 2.5286927e+11 | O68: 2.7034419e+11 | P68: 2.915239e+11 | Q68: 3.2386039e+11 | R68: 4.0659066e+11 | S68: 5.7305351e+11 | T68: 6.383902e+11 | U68: 7.0647297e+11 | V68: 7.9402596e+11 | W68: 8.8644086e+11 | X68: 1.081198e+12 | Y68: 1.3554261e+12 | Z68: 1.5068706e+12 | AA68: 1.4255683e+12 | AB68: 1.4219352e+12 | AC68: 1.4383976e+12 | AD68: 1.4362097e+12 | AE68: 1.4433015e+12 | AF68: 1.4651392e+12 | AG68: 1.5489148e+12 | AH68: 1.5783445e+12 | AI68: 1.8404933e+12 | AJ68: 1.953004e+12 | AK68: 2.1458908e+12 | AL68: 2.3823835e+12 | AM68: 2502116964681 | AN68: 2.5515036e+12 | AO68: 2.7679125e+12 | AP68: 2.9562093e+12 | AQ68: 2.9214522e+12 | AR68: 3.09057e+12 | AS68: 3377700768682 | AT68: 3.3511392e+12 | AU68: 3.2549992e+12 | AV68: 3.6229876e+12 | AW68: 4.2100797e+12 | AX68: 4.8958739e+12 | AY68: 5.5967413e+12 | AZ68: 6.6248253e+12 | BA68: 7.4600939e+12 | BB68: 7.17273e+12 | BC68: 8.7082087e+12 | BD68: 9.8138006e+12 | BE68: 1.0261754e+13 | BF68: 1.0406754e+13 | BG68: 10766609704140 | BH68: 1.023702e+13 | BI68: 1.0537029e+13 | BJ68: 1.1393448e+13 | BK68: 1.1524428e+13 | BL68: 1.1767657e+13 | BM68: 1.0981013e+13 | BN68: 1.2771307e+13 | BO68: 1.4131149e+13 | BP68: 1.4847824e+13
A69: East Asia & Pacific | B69: EAS | C69: GDP (current US$) | D69: NY.GDP.MKTP.CD | E69: 1.5714809e+11 | F69: 1.5840861e+11 | G69: 1.621353e+11 | H69: 1.8095586e+11 | I69: 2.0776728e+11 | J69: 2.3125875e+11 | K69: 2.5876488e+11 | L69: 2.8122166e+11 | M69: 3.106957e+11 | N69: 3.582684e+11 | O69: 4.126311e+11 | P69: 4.5854646e+11 | Q69: 5.7011635e+11 | R69: 7.5151207e+11 | S69: 8.6580285e+11 | T69: 9.475507e+11 | U69: 1.0420889e+12 | V69: 1.241834e+12 | W69: 1.5690541e+12 | X69: 1.7030769e+12 | Y69: 1.840088e+12 | Z69: 2.0282628e+12 | AA69: 1.9868831e+12 | AB69: 2.1155938e+12 | AC69: 2.2635781e+12 | AD69: 2.3880768e+12 | AE69: 3.1237434e+12 | AF69: 3.6674818e+12 | AG69: 4.4091148e+12 | AH69: 4.5907254e+12 | AI69: 4.7909501e+12 | AJ69: 5.4128276e+12 | AK69: 5.9172372e+12 | AL69: 6.6194437e+12 | AM69: 7.4043859e+12 | AN69: 8.4076017e+12 | AO69: 8.1015015e+12 | AP69: 7.7438094e+12 | AQ69: 6.9317232e+12 | AR69: 7.7434026e+12 | AS69: 8.3773634e+12 | AT69: 7.7895132e+12 | AU69: 7.9127593e+12 | AV69: 8.702214e+12 | AW69: 9.75844e+12 | AX69: 1.0411321e+13 | AY69: 1.103481e+13 | AZ69: 1.2331151e+13 | BA69: 1.4220149e+13 | BB69: 1.4630641e+13 | BC69: 1.7078057e+13 | BD69: 1.9796933e+13 | BE69: 2.1174179e+13 | BF69: 2.1411284e+13 | BG69: 2.2089702e+13 | BH69: 2.1995274e+13 | BI69: 2.2776013e+13 | BJ69: 24329094912610 | BK69: 2.648786e+13 | BL69: 2.7032495e+13 | BM69: 2.7156482e+13 | BN69: 3.1148241e+13 | BO69: 3.066375e+13 | BP69: 3.0775659e+13
A70: Europe & Central Asia (excluding high income) | B70: ECA | C70: GDP (current US$) | D70: NY.GDP.MKTP.CD | AF70: 2.3171977e+11 | AG70: 2.5583406e+11 | AH70: 2.8909763e+11 | AI70: 3.4694094e+11 | AJ70: 3.3372538e+11 | AK70: 3.2322805e+11 | AL70: 3.4253232e+11 | AM70: 2.7336097e+11 | AN70: 3.0649714e+11 | AO70: 3.2489175e+11 | AP70: 3.4475542e+11 | AQ70: 4.1969387e+11 | AR70: 3.8264878e+11 | AS70: 3.9025464e+11 | AT70: 3.3443349e+11 | AU70: 3.8902855e+11 | AV70: 4.9599612e+11 | AW70: 6.3912869e+11 | AX70: 7.9604719e+11 | AY70: 9.2598401e+11 | AZ70: 1.1654814e+12 | BA70: 1.3950642e+12 | BB70: 1.1631412e+12 | BC70: 1.3776294e+12 | BD70: 1.5667991e+12 | BE70: 1.6525067e+12 | BF70: 1.8022859e+12 | BG70: 1.7297142e+12 | BH70: 1.5076469e+12 | BI70: 1.4473953e+12 | BJ70: 1.4851083e+12 | BK70: 1.4599813e+12 | BL70: 1.4887702e+12 | BM70: 1.4283272e+12 | BN70: 1.6594408e+12 | BO70: 1.8030382e+12 | BP70: 2.0983497e+12
A71: Europe & Central Asia | B71: ECS | C71: GDP (current US$) | D71: NY.GDP.MKTP.CD | E71: 4.2644319e+11 | F71: 4.6928e+11 | G71: 5.1321998e+11 | H71: 5.612763e+11 | I71: 6.2034095e+11 | J71: 6.7646095e+11 | K71: 7.3165166e+11 | L71: 7.7741283e+11 | M71: 8.1898456e+11 | N71: 9.0830058e+11 | O71: 1.0208178e+12 | P71: 1.1520091e+12 | Q71: 1.3815351e+12 | R71: 1.7576639e+12 | S71: 1.9864561e+12 | T71: 2.3207249e+12 | U71: 2.4129842e+12 | V71: 2.7290664e+12 | W71: 3.3457841e+12 | X71: 4.0790209e+12 | Y71: 4.6116235e+12 | Z71: 4.1081509e+12 | AA71: 3.9600258e+12 | AB71: 3.8403282e+12 | AC71: 3.6910457e+12 | AD71: 3.819245e+12 | AE71: 5.2077266e+12 | AF71: 6.4313995e+12 | AG71: 7.1596102e+12 | AH71: 7.2547653e+12 | AI71: 8.8689689e+12 | AJ71: 9.1378989e+12 | AK71: 9.7888307e+12 | AL71: 9.0009998e+12 | AM71: 9.4119545e+12 | AN71: 1.0868922e+13 | AO71: 1.1093789e+13 | AP71: 1.0521843e+13 | AQ71: 1.0794474e+13 | AR71: 1.0676208e+13 | AS71: 1.0065925e+13 | AT71: 10168292808351 | AU71: 1.1134331e+13 | AV71: 1.3534599e+13 | AW71: 1.5775505e+13 | AX71: 1.6780904e+13 | AY71: 1.8167738e+13 | AZ71: 2.1227702e+13 | BA71: 2.3363341e+13 | BB71: 2.054511e+13 | BC71: 2.1016513e+13 | BD71: 2.3305973e+13 | BE71: 2.2453705e+13 | BF71: 2.345499e+13 | BG71: 2.3784373e+13 | BH71: 2.048146e+13 | BI71: 2.0408606e+13 | BJ71: 2.1652843e+13 | BK71: 2.3188736e+13 | BL71: 2.2908223e+13 | BM71: 2.2156549e+13 | BN71: 2.5331394e+13 | BO71: 25389267749916 | BP71: 2.7240629e+13
A72: Ecuador | B72: ECU | C72: GDP (current US$) | D72: NY.GDP.MKTP.CD | E72: 2.0694649e+09 | F72: 1.753851e+09 | G72: 1.5182077e+09 | H72: 1.8243439e+09 | I72: 2.2441461e+09 | J72: 2.3870474e+09 | K72: 2.4293086e+09 | L72: 2.5535952e+09 | M72: 2.5821799e+09 | N72: 3.1121657e+09 | O72: 2.8625031e+09 | P72: 2.7542193e+09 | Q72: 3.1859861e+09 | R72: 3.8917542e+09 | S72: 6.599257e+09 | T72: 7.7316745e+09 | U72: 9.091921e+09 | V72: 1.1026343e+10 | W72: 1.1922498e+10 | X72: 1.4175161e+10 | Y72: 1.7881508e+10 | Z72: 2.1810759e+10 | AA72: 1.9929846e+10 | AB72: 1.7152477e+10 | AC72: 1.6912509e+10 | AD72: 1.7149088e+10 | AE72: 1.5314138e+10 | AF72: 1.3945427e+10 | AG72: 1.3051882e+10 | AH72: 1.3890824e+10 | AI72: 1.5239273e+10 | AJ72: 1.6988535e+10 | AK72: 1.8094238e+10 | AL72: 1.8938717e+10 | AM72: 2.2708673e+10 | AN72: 2.4432884e+10 | AO72: 2.5226393e+10 | AP72: 2.8162053e+10 | AQ72: 2.7981897e+10 | AR72: 1.9645273e+10 | AS72: 1.7539455e+10 | AT72: 23127055000 | AU72: 27054197000 | AV72: 30965208000 | AW72: 35194947000 | AX72: 40278849000 | AY72: 45690762000 | AZ72: 49848725000 | BA72: 61139438000 | BB72: 60094978000 | BC72: 68151329000 | BD72: 78986648000 | BE72: 87735048000 | BF72: 96570334000 | BG72: 102717794000 | BH72: 97209558000 | BI72: 97671433000 | BJ72: 104467486000 | BK72: 107478962000 | BL72: 107595829000 | BM72: 95865472000 | BN72: 107435101000 | BO72: 116586079000 | BP72: 118844826000
A73: Egypt, Arab Rep. | B73: EGY | C73: GDP (current US$) | D73: NY.GDP.MKTP.CD | J73: 4.9486675e+09 | K73: 5.2780056e+09 | L73: 5.6054843e+09 | M73: 5.932243e+09 | N73: 6.5244552e+09 | O73: 8.0422005e+09 | P73: 8.6092833e+09 | Q73: 9.2996381e+09 | R73: 1.0098535e+10 | S73: 9.2289632e+09 | T73: 1.1632179e+10 | U73: 1.3315988e+10 | V73: 1.4400807e+10 | W73: 1.4811704e+10 | X73: 1.8020571e+10 | Y73: 2.1669908e+10 | Z73: 2.2136081e+10 | AA73: 2.7655172e+10 | AB73: 3.096624e+10 | AC73: 3.3971189e+10 | AD73: 3.9053502e+10 | AE73: 4.1253508e+10 | AF73: 4.0455617e+10 | AG73: 3.4980125e+10 | AH73: 3.9756299e+10 | AI73: 4.2978914e+10 | AJ73: 3.7387836e+10 | AK73: 4.1855987e+10 | AL73: 4.6578631e+10 | AM73: 5.1897983e+10 | AN73: 6.0159245e+10 | AO73: 6.7629717e+10 | AP73: 7.8436578e+10 | AQ73: 8.4828808e+10 | AR73: 9.0710705e+10 | AS73: 9.9838544e+10 | AT73: 9.6684636e+10 | AU73: 8.5146067e+10 | AV73: 8.0288462e+10 | AW73: 7.8782468e+10 | AX73: 8.9600666e+10 | AY73: 1.0742609e+11 | AZ73: 1.3043783e+11 | BA73: 1.6281818e+11 | BB73: 1.8914701e+11 | BC73: 2.1898367e+11 | BD73: 2.3598967e+11 | BE73: 2.7911667e+11 | BF73: 2.8843411e+11 | BG73: 3.0559541e+11 | BH73: 3.2936658e+11 | BI73: 3.3244172e+11 | BJ73: 2.4836277e+11 | BK73: 2.6258863e+11 | BL73: 3.1867882e+11 | BM73: 3.8381784e+11 | BN73: 4.2467177e+11 | BO73: 4.7674772e+11 | BP73: 3.9592608e+11
A74: Euro area | B74: EMU | C74: GDP (current US$) | D74: NY.GDP.MKTP.CD | E74: 2.5154794e+11 | F74: 2.8000121e+11 | G74: 3.0968284e+11 | H74: 3.4086742e+11 | I74: 3.7768878e+11 | J74: 4.1285233e+11 | K74: 4.4669679e+11 | L74: 4.7474044e+11 | M74: 5.1044478e+11 | N74: 5.7028164e+11 | O74: 6.4579749e+11 | P74: 7.3195412e+11 | Q74: 8.842195e+11 | R74: 1.1478879e+12 | S74: 1.30178e+12 | T74: 1.5094297e+12 | U74: 1.5752508e+12 | V74: 1.7917994e+12 | W74: 2.1941473e+12 | X74: 2.6579189e+12 | Y74: 2.9768362e+12 | Z74: 2.5871117e+12 | AA74: 2.5048267e+12 | AB74: 2.4436412e+12 | AC74: 2.3439425e+12 | AD74: 2.4080397e+12 | AE74: 3.379545e+12 | AF74: 4.1800098e+12 | AG74: 4.5971534e+12 | AH74: 4.695807e+12 | AI74: 5.9097821e+12 | AJ74: 6.1302687e+12 | AK74: 6.7516569e+12 | AL74: 6.1809296e+12 | AM74: 6.528765e+12 | AN74: 7.5384902e+12 | AO74: 7.6287432e+12 | AP74: 6.9764333e+12 | AQ74: 7.1751526e+12 | AR74: 7.1399495e+12 | AS74: 6.5176297e+12 | AT74: 6.6193826e+12 | AU74: 7.2266916e+12 | AV74: 8.8975459e+12 | AW74: 1.0202235e+13 | AX74: 1.056856e+13 | AY74: 1.1233647e+13 | AZ74: 1.2938432e+13 | BA74: 1.4226784e+13 | BB74: 1.3000703e+13 | BC74: 1.2700582e+13 | BD74: 1.3700832e+13 | BE74: 1.2695679e+13 | BF74: 1.3255654e+13 | BG74: 1.357007e+13 | BH74: 1.1727106e+13 | BI74: 1.2025904e+13 | BJ74: 12736901061170 | BK74: 1.3761117e+13 | BL74: 1.3481146e+13 | BM74: 1.3155164e+13 | BN74: 1.4754625e+13 | BO74: 1.4224347e+13 | BP74: 1.5544859e+13
A75: Eritrea | B75: ERI | C75: GDP (current US$) | D75: NY.GDP.MKTP.CD | AK75: 4.7710165e+08 | AL75: 4.6787271e+08 | AM75: 5.3168831e+08 | AN75: 578015625 | AO75: 6.9353595e+08 | AP75: 6.8649009e+08 | AQ75: 7.4552312e+08 | AR75: 6.8891854e+08 | AS75: 7.0637082e+08 | AT75: 7.5237169e+08 | AU75: 7.2932168e+08 | AV75: 8.7024827e+08 | AW75: 1.109054e+09 | AX75: 1.0984247e+09 | AY75: 1.2111619e+09 | AZ75: 1.3179745e+09 | BA75: 1380188800 | BB75: 1.8566956e+09 | BC75: 1.5895154e+09 | BD75: 2.0650016e+09
A76: Spain | B76: ESP | C76: GDP (current US$) | D76: NY.GDP.MKTP.CD | E76: 1.2433395e+10 | F76: 1.4248304e+10 | G76: 1.6621505e+10 | H76: 1.9645747e+10 | I76: 2.1982577e+10 | J76: 2.5497832e+10 | K76: 2.9580564e+10 | L76: 3.2594186e+10 | M76: 3.2417481e+10 | N76: 3.7117201e+10 | O76: 4.0992995e+10 | P76: 4.661942e+10 | Q76: 5.9132415e+10 | R76: 7.8639526e+10 | S76: 9.7274006e+10 | T76: 1.1477705e+11 | U76: 1.1850718e+11 | V76: 1.3244928e+11 | W76: 160599687500 | X76: 2.1460196e+11 | Y76: 2.3276682e+11 | Z76: 2.0280789e+11 | AA76: 1.9599675e+11 | AB76: 1.7095119e+11 | AC76: 1.7210291e+11 | AD76: 1.8079346e+11 | AE76: 2.5132108e+11 | AF76: 3.1874794e+11 | AG76: 3.7616041e+11 | AH76: 4.1475706e+11 | AI76: 5.3655859e+11 | AJ76: 5.7716617e+11 | AK76: 6.3091602e+11 | AL76: 5.2507564e+11 | AM76: 5.3056263e+11 | AN76: 6.1460902e+11 | AO76: 6.4258899e+11 | AP76: 5.9007727e+11 | AQ76: 6.1921483e+11 | AR76: 6.3490754e+11 | AS76: 5.9836331e+11 | AT76: 6.2783003e+11 | AU76: 7.0875668e+11 | AV76: 9.0749152e+11 | AW76: 1.0690557e+12 | AX76: 1.1537158e+12 | AY76: 1.260399e+12 | AZ76: 1474002579820 | BA76: 1.6318635e+12 | BB76: 1.4914729e+12 | BC76: 1.4221082e+12 | BD76: 1.4807105e+12 | BE76: 1324750738725 | BF76: 1.3555795e+12 | BG76: 1.3718205e+12 | BH76: 1.196157e+12 | BI76: 1.233555e+12 | BJ76: 1.3132453e+12 | BK76: 1.4217027e+12 | BL76: 1.3943201e+12 | BM76: 1.2781289e+12 | BN76: 1.4456517e+12 | BO76: 1.4178005e+12 | BP76: 1.5806947e+12
A77: Estonia | B77: EST | C77: GDP (current US$) | D77: NY.GDP.MKTP.CD | AL77: 4.0130917e+09 | AM77: 4.1230114e+09 | AN77: 4.5029709e+09 | AO77: 4.786019e+09 | AP77: 5.1544206e+09 | AQ77: 5.6740805e+09 | AR77: 5.7569123e+09 | AS77: 5.6865797e+09 | AT77: 6.2546495e+09 | AU77: 7.3679759e+09 | AV77: 9.8740131e+09 | AW77: 1.2145912e+10 | AX77: 1.410679e+10 | AY77: 1.702287e+10 | AZ77: 2.2449129e+10 | BA77: 2.4341679e+10 | BB77: 1.9633031e+10 | BC77: 1.9523477e+10 | BD77: 2.3213994e+10 | BE77: 2.301915e+10 | BF77: 2.5115753e+10 | BG77: 2.6634084e+10 | BH77: 2.2890762e+10 | BI77: 2.4072829e+10 | BJ77: 2.6924385e+10 | BK77: 3.062472e+10 | BL77: 3.1290453e+10 | BM77: 3.133042e+10 | BN77: 3.6864793e+10 | BO77: 3.7921481e+10 | BP77: 4.0744849e+10
A78: Ethiopia | B78: ETH | C78: GDP (current US$) | D78: NY.GDP.MKTP.CD | E78: 1.6105117e+09 | F78: 1.6808595e+09 | G78: 1.7475663e+09 | H78: 1.8250588e+09 | I78: 1.9841292e+09 | J78: 2.1599986e+09 | K78: 2.3244664e+09 | L78: 2.461762e+09 | M78: 2.6199489e+09 | N78: 2.7689874e+09 | O78: 3.0453545e+09 | P78: 3.2242808e+09 | Q78: 3.5202529e+09 | R78: 4.0705705e+09 | S78: 4.57721e+09 | T78: 4.5770479e+09 | U78: 4.9438061e+09 | V78: 5.6518406e+09 | W78: 6.0149614e+09 | X78: 6.5860484e+09 | Y78: 7.0125855e+09 | Z78: 7.5076636e+09 | AA78: 7.8999888e+09 | AB78: 8.7816644e+09 | AC78: 8.2983096e+09 | AD78: 9.7173927e+09 | AE78: 1.0094329e+10 | AF78: 1.0790002e+10 | AG78: 1.118112e+10 | AH78: 1.1762932e+10 | AI78: 1.2478944e+10 | AJ78: 1.3799799e+10 | AK78: 1.0754799e+10 | AL78: 9.0510439e+09 | AM78: 7.1008068e+09 | AN78: 7.8552052e+09 | AO78: 8.7612155e+09 | AP78: 8.80354e+09 | AQ78: 8.0132741e+09 | AR78: 7.8929735e+09 | AS78: 8.2423496e+09 | AT78: 8.231326e+09 | AU78: 7.8508095e+09 | AV78: 8.6236913e+09 | AW78: 1.0131187e+10 | AX78: 1.2401139e+10 | AY78: 1.5280862e+10 | AZ78: 1.9707617e+10 | BA78: 2.7066913e+10 | BB78: 3.2437389e+10 | BC78: 2.993379e+10 | BD78: 3.1952763e+10 | BE78: 4.3310721e+10 | BF78: 4.7648277e+10 | BG78: 5.5612228e+10 | BH78: 6.4589329e+10 | BI78: 7.4296745e+10 | BJ78: 8.1770887e+10 | BK78: 8.4269197e+10 | BL78: 9.5912608e+10 | BM78: 1.0765773e+11 | BN78: 1.1126188e+11 | BO78: 1.267727e+11 | BP78: 1.6369793e+11
A79: European Union | B79: EUU | C79: GDP (current US$) | D79: NY.GDP.MKTP.CD | E79: 2.8507305e+11 | F79: 3.1687041e+11 | G79: 3.5022181e+11 | H79: 3.8482162e+11 | I79: 4.2685775e+11 | J79: 4.6708251e+11 | K79: 5.0570386e+11 | L79: 5.3849976e+11 | M79: 5.7799846e+11 | N79: 6.4504263e+11 | O79: 7.2923021e+11 | P79: 8.2428843e+11 | Q79: 9.9440135e+11 | R79: 1.2867324e+12 | S79: 1.456742e+12 | T79: 1696431872318 | U79: 1.7772031e+12 | V79: 2.0127815e+12 | W79: 2.4515456e+12 | X79: 2.962559e+12 | Y79: 3.3148765e+12 | Z79: 2.8938509e+12 | AA79: 2.7920728e+12 | AB79: 2.7147373e+12 | AC79: 2.6157377e+12 | AD79: 2.6900057e+12 | AE79: 3.7558253e+12 | AF79: 4.6422932e+12 | AG79: 5.0963073e+12 | AH79: 5.2056591e+12 | AI79: 6.5098709e+12 | AJ79: 6.7336326e+12 | AK79: 7.3921864e+12 | AL79: 6.7512229e+12 | AM79: 7.1555033e+12 | AN79: 8.2960913e+12 | AO79: 8.4315911e+12 | AP79: 7.7338437e+12 | AQ79: 7.9698807e+12 | AR79: 7.9258446e+12 | AS79: 7.2763907e+12 | AT79: 7.393612e+12 | AU79: 8.0835197e+12 | AV79: 9.9321347e+12 | AW79: 1.14189e+13 | AX79: 1.1910069e+13 | AY79: 1.2712636e+13 | AZ79: 1.4727521e+13 | BA79: 1.6295391e+13 | BB79: 1.4762843e+13 | BC79: 1.4556122e+13 | BD79: 1.5765159e+13 | BE79: 1.4641635e+13 | BF79: 1.5294854e+13 | BG79: 1.5651373e+13 | BH79: 13553897260141 | BI79: 1.3888833e+13 | BJ79: 1.476588e+13 | BK79: 1.5981446e+13 | BL79: 1.569405e+13 | BM79: 1.5381419e+13 | BN79: 1.7315127e+13 | BO79: 1.6761497e+13 | BP79: 1.8349388e+13
A80: Fragile and conflict affected situations | B80: FCS | C80: GDP (current US$) | D80: NY.GDP.MKTP.CD | E80: 3.0738245e+10 | F80: 3.2690863e+10 | G80: 3.5607386e+10 | H80: 3.8028727e+10 | I80: 3.827477e+10 | J80: 4.0813675e+10 | K80: 4.3238592e+10 | L80: 4.4174622e+10 | M80: 4.8568839e+10 | N80: 5.3610326e+10 | O80: 6.5401455e+10 | P80: 6.6561389e+10 | Q80: 7.7479654e+10 | R80: 9.5510532e+10 | S80: 1.4690068e+11 | T80: 1.6151356e+11 | U80: 1.953045e+11 | V80: 2.1327835e+11 | W80: 2.3135688e+11 | X80: 2.9757e+11 | Y80: 3.8275505e+11 | Z80: 5.1280813e+11 | AA80: 4.8718769e+11 | AB80: 4.2177665e+11 | AC80: 3.8229504e+11 | AD80: 3.8979745e+11 | AE80: 3.5721874e+11 | AF80: 3.5976887e+11 | AG80: 3.8915419e+11 | AH80: 3.8242662e+11 | AI80: 5.5043183e+11 | AJ80: 3.865253e+11 | AK80: 3.4517186e+11 | AL80: 3.5121528e+11 | AM80: 3.5324029e+11 | AN80: 4.3176256e+11 | AO80: 4.6644087e+11 | AP80: 5.2232678e+11 | AQ80: 5.3610003e+11 | AR80: 4.0017116e+11 | AS80: 4.6803599e+11 | AT80: 4.5801748e+11 | AU80: 4.4692894e+11 | AV80: 4.7061792e+11 | AW80: 5.9696532e+11 | AX80: 7.5516091e+11 | AY80: 9.4595528e+11 | AZ80: 1.1593335e+12 | BA80: 1.4819462e+12 | BB80: 1.3427287e+12 | BC80: 1.5939811e+12 | BD80: 1.6643216e+12 | BE80: 1.8618138e+12 | BF80: 1.9355445e+12 | BG80: 2.0537889e+12 | BH80: 1.6173233e+12 | BI80: 1.4906337e+12 | BJ80: 1.5497122e+12 | BK80: 1.7351838e+12 | BL80: 1.8421549e+12 | BM80: 1.6909301e+12 | BN80: 1.7962744e+12 | BO80: 1.9500065e+12 | BP80: 1.9068012e+12
A81: Finland | B81: FIN | C81: GDP (current US$) | D81: NY.GDP.MKTP.CD | E81: 5.2790114e+09 | F81: 5.9839005e+09 | G81: 6.407225e+09 | H81: 6.9582964e+09 | I81: 7.8482884e+09 | J81: 8.6796203e+09 | K81: 9.3053129e+09 | L81: 9.4674286e+09 | M81: 8.9157705e+09 | N81: 1.0176618e+10 | O81: 1.1357517e+10 | P81: 1.2527406e+10 | Q81: 1.4743186e+10 | R81: 1.9472363e+10 | S81: 2.4848821e+10 | T81: 2.9472623e+10 | U81: 3.1849514e+10 | V81: 3.3499799e+10 | W81: 3.625616e+10 | X81: 4.4465256e+10 | Y81: 5.3645202e+10 | Z81: 5.2448333e+10 | AA81: 5.2797582e+10 | AB81: 5.0973527e+10 | AC81: 5.2888801e+10 | AD81: 5.5875863e+10 | AE81: 7.3531551e+10 | AF81: 9.1594752e+10 | AG81: 1.0905899e+11 | AH81: 1.1901205e+11 | AI81: 1.4143835e+11 | AJ81: 1.2777386e+11 | AK81: 1.1253252e+11 | AL81: 8.9214115e+10 | AM81: 1.0329994e+11 | AN81: 1.3418981e+11 | AO81: 1.3212917e+11 | AP81: 1.2691215e+11 | AQ81: 1.3403872e+11 | AR81: 1.3526408e+11 | AS81: 1.2601954e+11 | AT81: 1.2953311e+11 | AU81: 1.4040446e+11 | AV81: 1.7165246e+11 | AW81: 1.9747944e+11 | AX81: 2.0488549e+11 | AY81: 2.1708927e+11 | AZ81: 2.5637807e+11 | BA81: 2.8571631e+11 | BB81: 2.5349752e+11 | BC81: 2.4942431e+11 | BD81: 2.7560436e+11 | BE81: 2.5829006e+11 | BF81: 2.7136241e+11 | BG81: 2.7486283e+11 | BH81: 2.3453438e+11 | BI81: 2.4077135e+11 | BJ81: 2.5564798e+11 | BK81: 2.75708e+11 | BL81: 2.6851492e+11 | BM81: 2.7188608e+11 | BN81: 2.9647042e+11 | BO81: 2.8188743e+11 | BP81: 3.001872e+11
A82: Fiji | B82: FJI | C82: GDP (current US$) | D82: NY.GDP.MKTP.CD | E82: 1.1232842e+08 | F82: 1.1698778e+08 | G82: 1.2290643e+08 | H82: 1.2945473e+08 | I82: 1.4003274e+08 | J82: 1.4708475e+08 | K82: 1.5060393e+08 | L82: 1.6262589e+08 | M82: 1.6695294e+08 | N82: 1.8218207e+08 | O82: 2.1987848e+08 | P82: 2.4774933e+08 | Q82: 3.1665665e+08 | R82: 4.2595049e+08 | S82: 5.585871e+08 | T82: 6.8428243e+08 | U82: 6.9454081e+08 | V82: 7.1950177e+08 | W82: 8.2926789e+08 | X82: 1.0196915e+09 | Y82: 1.2026188e+09 | Z82: 1.2356268e+09 | AA82: 1.1940599e+09 | AB82: 1.1230852e+09 | AC82: 1.1780007e+09 | AD82: 1.1411689e+09 | AE82: 1.2902673e+09 | AF82: 1.177948e+09 | AG82: 1.1100095e+09 | AH82: 1.1826603e+09 | AI82: 1.3370176e+09 | AJ82: 1.3838832e+09 | AK82: 1.532411e+09 | AL82: 1.6361012e+09 | AM82: 1.8257321e+09 | AN82: 1.9703015e+09 | AO82: 2.1286966e+09 | AP82: 2.0902211e+09 | AQ82: 1.6531467e+09 | AR82: 1.93646e+09 | AS82: 1.6782195e+09 | AT82: 1.652462e+09 | AU82: 1.83328e+09 | AV82: 2.3004925e+09 | AW82: 2.7080785e+09 | AX82: 2.9804038e+09 | AY82: 3.0763055e+09 | AZ82: 3.3783146e+09 | BA82: 3.5231859e+09 | BB82: 2.8706246e+09 | BC82: 3.1401667e+09 | BD82: 3.7794119e+09 | BE82: 3.9720281e+09 | BF82: 4.189968e+09 | BG82: 4.8571048e+09 | BH82: 4.6824799e+09 | BI82: 4.9302136e+09 | BJ82: 5.3534692e+09 | BK82: 5.5814253e+09 | BL82: 5.4444072e+09 | BM82: 4.4324662e+09 | BN82: 4.3050316e+09 | BO82: 4.9799795e+09 | BP82: 5.4947975e+09
A83: France | B83: FRA | C83: GDP (current US$) | D83: NY.GDP.MKTP.CD | E83: 6.2225478e+10 | F83: 6.7461644e+10 | G83: 7.560753e+10 | H83: 8.4759195e+10 | I83: 9.4007851e+10 | J83: 1.0153725e+11 | K83: 1.1004585e+11 | L83: 1.1897298e+11 | M83: 1.2978544e+11 | N83: 1.4190307e+11 | O83: 1.4845636e+11 | P83: 1.6596662e+11 | Q83: 2.0349415e+11 | R83: 2.6442988e+11 | S83: 2.8555374e+11 | T83: 3.6083219e+11 | U83: 3.7231904e+11 | V83: 4.1027949e+11 | W83: 5.067093e+11 | X83: 6.1395313e+11 | Y83: 7.0128842e+11 | Z83: 6.155522e+11 | AA83: 5.8487773e+11 | AB83: 5.5986918e+11 | AC83: 5.3068378e+11 | AD83: 5.5313841e+11 | AE83: 7.7147078e+11 | AF83: 9.3417331e+11 | AG83: 1.018847e+12 | AH83: 1.0252118e+12 | AI83: 1.2691796e+12 | AJ83: 1.2692768e+12 | AK83: 1.4014659e+12 | AL83: 1322815612694 | AM83: 1.3939828e+12 | AN83: 1.6010948e+12 | AO83: 1.6056751e+12 | AP83: 1.4528849e+12 | AQ83: 1.5031087e+12 | AR83: 1.4931517e+12 | AS83: 1.3656397e+12 | AT83: 1.3776573e+12 | AU83: 1.5014094e+12 | AV83: 1.8445448e+12 | AW83: 2.1196332e+12 | AX83: 2.1969452e+12 | AY83: 2.3205362e+12 | AZ83: 2.6605912e+12 | BA83: 2.9303038e+12 | BB83: 2.7008874e+12 | BC83: 2.6451879e+12 | BD83: 2.8651575e+12 | BE83: 2.6836717e+12 | BF83: 2.8118769e+12 | BG83: 2.8559645e+12 | BH83: 2.4391886e+12 | BI83: 2.4729643e+12 | BJ83: 2.595151e+12 | BK83: 2.7909569e+12 | BL83: 2.7288702e+12 | BM83: 2.6474187e+12 | BN83: 2.9593558e+12 | BO83: 2.7790922e+12 | BP83: 3.0309041e+12
A84: Faroe Islands | B84: FRO | C84: GDP (current US$) | D84: NY.GDP.MKTP.CD | J84: 57954522 | K84: 64397131 | L84: 66225404 | M84: 65186667 | N84: 70106667 | O84: 84933333 | P84: 99219083 | Q84: 1.193359e+08 | R84: 1.6123647e+08 | S84: 1.9677107e+08 | T84: 2.2740444e+08 | U84: 2.7047035e+08 | V84: 3.477983e+08 | W84: 3.9783303e+08 | X84: 4.4856849e+08 | Y84: 4.930143e+08 | Z84: 4.5624492e+08 | AA84: 4.440475e+08 | AB84: 4.8660513e+08 | AC84: 4.2600886e+08 | AD84: 4.5930728e+08 | AE84: 6.8891429e+08 | AF84: 8.8650862e+08 | AG84: 9.6857696e+08 | AH84: 8.7193535e+08 | AI84: 9.6080541e+08 | AJ84: 9.0925321e+08 | AK84: 9.1267041e+08 | AL84: 7.6095719e+08 | AM84: 7.5873918e+08 | AN84: 9.0140471e+08 | AO84: 9.8953691e+08 | AP84: 9.3376308e+08 | AQ84: 1.1047442e+09 | AR84: 1.1276848e+09 | AS84: 1.0671095e+09 | AT84: 1.1602682e+09 | AU84: 1.2750937e+09 | AV84: 1.5019416e+09 | AW84: 1.7247708e+09 | AX84: 1.7597396e+09 | AY84: 2.0176808e+09 | AZ84: 2.3390153e+09 | BA84: 2.4898732e+09 | BB84: 2.2960652e+09 | BC84: 2.3317968e+09 | BD84: 2.5057407e+09 | BE84: 2.4272004e+09 | BF84: 2.6901105e+09 | BG84: 2.9140127e+09 | BH84: 2.573906e+09 | BI84: 2.8132789e+09 | BJ84: 2.9800574e+09 | BK84: 3.1886009e+09 | BL84: 3.2664327e+09 | BM84: 3.2620459e+09 | BN84: 3.6550639e+09 | BO84: 3.5559298e+09
A85: Micronesia, Fed. Sts. | B85: FSM | C85: GDP (current US$) | D85: NY.GDP.MKTP.CD | O85: 19885926 | P85: 21783158 | Q85: 25100928 | R85: 34821467 | S85: 46095175 | T85: 46119184 | U85: 46813193 | V85: 47305560 | W85: 53656834 | X85: 60270778 | Y85: 64186644 | Z85: 76472529 | AA85: 80055706 | AB85: 84110353 | AC85: 84676118 | AD85: 1.0193194e+08 | AE85: 112210000 | AF85: 116700000 | AG85: 124700000 | AH85: 135200000 | AI85: 147200000 | AJ85: 166200000 | AK85: 178100000 | AL85: 198400000 | AM85: 202500000 | AN85: 221575300 | AO85: 218534700 | AP85: 206626300 | AQ85: 218873100 | AR85: 220140500 | AS85: 233271800 | AT85: 240970900 | AU85: 242517200 | AV85: 245432900 | AW85: 240236000 | AX85: 250281900 | AY85: 253541900 | AZ85: 256787200 | BA85: 263145100 | BB85: 280284600 | BC85: 296944100 | BD85: 311301600 | BE85: 327248700 | BF85: 317214400 | BG85: 319271200 | BH85: 316489900 | BI85: 325000000 | BJ85: 359000000 | BK85: 392000000 | BL85: 394000000 | BM85: 372000000 | BN85: 390000000 | BO85: 430000000 | BP85: 460000000
A86: Gabon | B86: GAB | C86: GDP (current US$) | D86: NY.GDP.MKTP.CD | E86: 1.4146898e+08 | F86: 1.6763791e+08 | G86: 1.8279654e+08 | H86: 1.5448024e+08 | I86: 2.1567986e+08 | J86: 2.2647429e+08 | K86: 2.4584978e+08 | L86: 2.7154368e+08 | M86: 2.9446856e+08 | N86: 3.181247e+08 | O86: 3.2380248e+08 | P86: 3.8168707e+08 | Q86: 4.3050836e+08 | R86: 7.227807e+08 | S86: 1.544216e+09 | T86: 2.1575929e+09 | U86: 3.00941e+09 | V86: 2.8093491e+09 | W86: 2.3894793e+09 | X86: 3.0302511e+09 | Y86: 4.2796379e+09 | Z86: 3.8622691e+09 | AA86: 3.6180078e+09 | AB86: 3.3912757e+09 | AC86: 3.5614516e+09 | AD86: 3.3399148e+09 | AE86: 3.4036382e+09 | AF86: 3.281797e+09 | AG86: 3.8345034e+09 | AH86: 4.1864115e+09 | AI86: 5.9522938e+09 | AJ86: 5.4029198e+09 | AK86: 5.5923908e+09 | AL86: 4.3786451e+09 | AM86: 4.1908193e+09 | AN86: 4.9588456e+09 | AO86: 5.69404e+09 | AP86: 5.3268171e+09 | AQ86: 4.4834173e+09 | AR86: 4.662992e+09 | AS86: 5.0804836e+09 | AT86: 5.0232654e+09 | AU86: 5.3354511e+09 | AV86: 6.5119034e+09 | AW86: 7.770219e+09 | AX86: 9.582784e+09 | AY86: 1.0327598e+10 | AZ86: 1.245541e+10 | BA86: 1.5571348e+10 | BB86: 1.2113699e+10 | BC86: 1.4372593e+10 | BD86: 1.8210308e+10 | BE86: 1.7170464e+10 | BF86: 1.7595745e+10 | BG86: 1.8203967e+10 | BH86: 1.4383108e+10 | BI86: 1.402389e+10 | BJ86: 1.4929487e+10 | BK86: 1.6867326e+10 | BL86: 1.6874405e+10 | BM86: 1.5314577e+10 | BN86: 2.0217947e+10 | BO86: 2.1071739e+10 | BP86: 2.0516134e+10
A87: United Kingdom | B87: GBR | C87: GDP (current US$) | D87: NY.GDP.MKTP.CD | E87: 7.3233968e+10 | F87: 7.7741966e+10 | G87: 8.1247564e+10 | H87: 8.6561962e+10 | I87: 9.4407558e+10 | J87: 1.0182476e+11 | K87: 1.0857275e+11 | L87: 1.1311689e+11 | M87: 1.0775991e+11 | N87: 1.164647e+11 | O87: 1.3067195e+11 | P87: 1.481139e+11 | Q87: 1.6996503e+11 | R87: 1.9253797e+11 | S87: 2.0613137e+11 | T87: 2.4175664e+11 | U87: 2.3261456e+11 | V87: 2.6306646e+11 | W87: 3.3588303e+11 | X87: 4.3899407e+11 | Y87: 5.6494771e+11 | Z87: 5.4076568e+11 | AA87: 5.1504892e+11 | AB87: 4.8961801e+11 | AC87: 4.614871e+11 | AD87: 4.8928516e+11 | AE87: 6.0145265e+11 | AF87: 7.4516261e+11 | AG87: 9.1012273e+11 | AH87: 9.2688482e+11 | AI87: 1.0931694e+12 | AJ87: 1.1427972e+12 | AK87: 1.1796595e+12 | AL87: 1.0613887e+12 | AM87: 1.1404897e+12 | AN87: 1.3442402e+12 | AO87: 1.4196459e+12 | AP87: 1.5609119e+12 | AQ87: 1.6536949e+12 | AR87: 1.6878304e+12 | AS87: 1.6655349e+12 | AT87: 1.6498273e+12 | AU87: 1.7857299e+12 | AV87: 2.0544229e+12 | AW87: 2.4215251e+12 | AX87: 2543180000000 | AY87: 2.7084416e+12 | AZ87: 3.0905102e+12 | BA87: 2.9294118e+12 | BB87: 2.41284e+12 | BC87: 2.4854826e+12 | BD87: 2.6638058e+12 | BE87: 2.7070897e+12 | BF87: 2.7848535e+12 | BG87: 3.0647082e+12 | BH87: 2.9279111e+12 | BI87: 2.6891066e+12 | BJ87: 2.6801481e+12 | BK87: 2.8713403e+12 | BL87: 2.8514072e+12 | BM87: 2.6978066e+12 | BN87: 3.1415062e+12 | BO87: 3.0888398e+12 | BP87: 3.3400324e+12
A88: Georgia | B88: GEO | C88: GDP (current US$) | D88: NY.GDP.MKTP.CD | AF88: 11502.633 | AG88: 13825.758 | AH88: 14047.41 | AI88: 7500000000 | AJ88: 6400000000 | AK88: 3730000000 | AL88: 2.7013015e+09 | AM88: 2.5140708e+09 | AN88: 2.6937684e+09 | AO88: 3.0950476e+09 | AP88: 3.5105202e+09 | AQ88: 3.6134973e+09 | AR88: 2.8000259e+09 | AS88: 3.0574753e+09 | AT88: 3.2194623e+09 | AU88: 3.3957667e+09 | AV88: 3.9913779e+09 | AW88: 5.1253652e+09 | AX88: 6.410912e+09 | AY88: 7.7452507e+09 | AZ88: 1.0172931e+10 | BA88: 1.2795145e+10 | BB88: 1.076692e+10 | BC88: 1.2426908e+10 | BD88: 1.547529e+10 | BE88: 1.6894392e+10 | BF88: 1.751766e+10 | BG88: 1.7966015e+10 | BH88: 1.5223796e+10 | BI88: 1.5444549e+10 | BJ88: 1.6473125e+10 | BK88: 1.7902545e+10 | BL88: 1.7638337e+10 | BM88: 1.6010869e+10 | BN88: 1.8853116e+10 | BO88: 2.4984569e+10 | BP88: 3.053553e+10
A89: Ghana | B89: GHA | C89: GDP (current US$) | D89: NY.GDP.MKTP.CD | E89: 1.2239437e+09 | F89: 1.3098592e+09 | G89: 1.3901408e+09 | H89: 1.5492958e+09 | I89: 1.7408451e+09 | J89: 2.0647887e+09 | K89: 2.1380282e+09 | L89: 1.7488372e+09 | M89: 1.6666667e+09 | N89: 1.9617647e+09 | O89: 2.2147059e+09 | P89: 2.4271845e+09 | Q89: 2.1165414e+09 | R89: 3.0181034e+09 | S89: 2.8944099e+09 | T89: 2.8101064e+09 | U89: 2.7652542e+09 | V89: 3.1894286e+09 | W89: 3.6624782e+09 | X89: 4.0202279e+09 | Y89: 4.4452282e+09 | Z89: 4.2224419e+09 | AA89: 4.0359944e+09 | AB89: 4.0572751e+09 | AC89: 4.4122798e+09 | AD89: 4.5043067e+09 | AE89: 5.7356774e+09 | AF89: 5.0748299e+09 | AG89: 5.197765e+09 | AH89: 5.2518584e+09 | AI89: 5.8891066e+09 | AJ89: 6.6031853e+09 | AK89: 6.4161039e+09 | AL89: 5.9689229e+09 | AM89: 5.4463837e+09 | AN89: 6.4643828e+09 | AO89: 6.9329917e+09 | AP89: 6.8914432e+09 | AQ89: 7.4820692e+09 | AR89: 7.71811e+09 | AS89: 4.9828507e+09 | AT89: 5.3148729e+09 | AU89: 6.1661978e+09 | AV89: 7.6327236e+09 | AW89: 8.8814179e+09 | AX89: 1.0744568e+10 | AY89: 2.0885038e+10 | AZ89: 2.4827339e+10 | BA89: 2.8679383e+10 | BB89: 2.604872e+10 | BC89: 3.2197656e+10 | BD89: 3.9336668e+10 | BE89: 4.1271701e+10 | BF89: 6.2824629e+10 | BG89: 5.478332e+10 | BH89: 4.940601e+10 | BI89: 5.6164929e+10 | BJ89: 6.0405924e+10 | BK89: 6.7298915e+10 | BL89: 6.8337969e+10 | BM89: 7.0043096e+10 | BN89: 7.9524422e+10 | BO89: 7.4263364e+10 | BP89: 7.6370394e+10
A90: Gibraltar | B90: GIB | C90: GDP (current US$) | D90: NY.GDP.MKTP.CD
A91: Guinea | B91: GIN | C91: GDP (current US$) | D91: NY.GDP.MKTP.CD | O91: 3.2202246e+09 | P91: 3.5943029e+09 | Q91: 4.203069e+09 | R91: 5.1520804e+09 | S91: 5.6914175e+09 | T91: 6.1027696e+09 | U91: 6.7627819e+09 | V91: 6.9143813e+09 | W91: 8.087306e+09 | X91: 8.8770945e+09 | Y91: 9.7465249e+09 | Z91: 9.6464407e+09 | AA91: 1.1926032e+10 | AB91: 1.5129894e+10 | AC91: 1.8421497e+10 | AD91: 2.2787645e+10 | AE91: 2.9091304e+09 | AF91: 2.976714e+09 | AG91: 3.4764803e+09 | AH91: 3.5460793e+09 | AI91: 3.8883207e+09 | AJ91: 4.3961787e+09 | AK91: 4.7892204e+09 | AL91: 4.7811661e+09 | AM91: 4.9328004e+09 | AN91: 5.3857042e+09 | AO91: 5.6412431e+09 | AP91: 5.5169162e+09 | AQ91: 5.232118e+09 | AR91: 5.0468068e+09 | AS91: 4.3674589e+09 | AT91: 4.1255276e+09 | AU91: 4.3016088e+09 | AV91: 5.025168e+09 | AW91: 5.300768e+09 | AX91: 4.2824686e+09 | AY91: 4.2200192e+09 | AZ91: 6.2819176e+09 | BA91: 6.9641792e+09 | BB91: 6.7169045e+09 | BC91: 6.8534678e+09 | BD91: 6.7851372e+09 | BE91: 7.6380452e+09 | BF91: 8.3766139e+09 | BG91: 8.7784736e+09 | BH91: 8.7942024e+09 | BI91: 8.5959556e+09 | BJ91: 1.0324668e+10 | BK91: 1.185703e+10 | BL91: 1.3442861e+10 | BM91: 1.4177836e+10 | BN91: 1.6091818e+10 | BO91: 2.0999229e+10 | BP91: 2.3612296e+10
A92: Gambia, The | B92: GMB | C92: GDP (current US$) | D92: NY.GDP.MKTP.CD | K92: 44212081 | L92: 46695007 | M92: 41160066 | N92: 45168072 | O92: 52296084 | P92: 55728663 | Q92: 59160569 | R92: 75187749 | S92: 95796022 | T92: 1.1517972e+08 | U92: 1.1219083e+08 | V92: 1.380931e+08 | W92: 1.7183309e+08 | X92: 2.0711263e+08 | Y92: 2.4108309e+08 | Z92: 2.1876774e+08 | AA92: 2.1605055e+08 | AB92: 2.1344858e+08 | AC92: 1.7734088e+08 | AD92: 2.2572636e+08 | AE92: 1.8564699e+08 | AF92: 2.2062648e+08 | AG92: 2.6667221e+08 | AH92: 2.8412033e+08 | AI92: 3.170837e+08 | AJ92: 6.9031108e+08 | AK92: 7.1425426e+08 | AL92: 7.5504097e+08 | AM92: 7.4649395e+08 | AN92: 7.8599986e+08 | AO92: 8.4823945e+08 | AP92: 8.0363334e+08 | AQ92: 8.4028526e+08 | AR92: 8.1472403e+08 | AS92: 7.8291387e+08 | AT92: 6.8741065e+08 | AU92: 5.7823531e+08 | AV92: 4.8703869e+08 | AW92: 9.6190065e+08 | AX92: 1.0277011e+09 | AY92: 1.0541125e+09 | AZ92: 1.279703e+09 | BA92: 1.561767e+09 | BB92: 1.4501425e+09 | BC92: 1.5432949e+09 | BD92: 1.4096936e+09 | BE92: 1.4150047e+09 | BF92: 1.3756095e+09 | BG92: 1.2294617e+09 | BH92: 1.3781766e+09 | BI92: 1.4845789e+09 | BJ92: 1.5049095e+09 | BK92: 1.6706713e+09 | BL92: 1.8136097e+09 | BM92: 1.8121709e+09 | BN92: 2.0141588e+09 | BO92: 2.1750998e+09 | BP92: 2.3399042e+09
A93: Guinea-Bissau | B93: GNB | C93: GDP (current US$) | D93: NY.GDP.MKTP.CD | O93: 2.0467055e+08 | P93: 2.041673e+08 | Q93: 2.279862e+08 | R93: 2.3233128e+08 | S93: 2.5676973e+08 | T93: 2.83312e+08 | U93: 2.9215232e+08 | V93: 2.9887167e+08 | W93: 3.1887655e+08 | X93: 3.0814318e+08 | Y93: 2.8764826e+08 | Z93: 4.0223087e+08 | AA93: 4.3028402e+08 | AB93: 4.2522518e+08 | AC93: 3.5998049e+08 | AD93: 3.7395915e+08 | AE93: 3.3852423e+08 | AF93: 4.5189337e+08 | AG93: 4.2751432e+08 | AH93: 5.540723e+08 | AI93: 6.3418727e+08 | AJ93: 6.6847089e+08 | AK93: 5.8830927e+08 | AL93: 6.1577952e+08 | AM93: 6.1250208e+08 | AN93: 6.601954e+08 | AO93: 7.0296515e+08 | AP93: 6.9810722e+08 | AQ93: 5.9103414e+08 | AR93: 5.7936578e+08 | AS93: 3.913456e+08 | AT93: 4.1261087e+08 | AU93: 4.6677371e+08 | AV93: 5.536148e+08 | AW93: 5.8216984e+08 | AX93: 6.3977604e+08 | AY93: 6.347819e+08 | AZ93: 7.53163e+08 | BA93: 9.5266754e+08 | BB93: 8.9016783e+08 | BC93: 9.4011254e+08 | BD93: 1.1570743e+09 | BE93: 1.0494122e+09 | BF93: 1.1096828e+09 | BG93: 1.1352507e+09 | BH93: 1.1523842e+09 | BI93: 1.2450743e+09 | BJ93: 1.4699786e+09 | BK93: 1.5541336e+09 | BL93: 1.4864766e+09 | BM93: 1.52048e+09 | BN93: 1.7245556e+09 | BO93: 1.7141665e+09 | BP93: 1.9664614e+09
A94: Equatorial Guinea | B94: GNQ | C94: GDP (current US$) | D94: NY.GDP.MKTP.CD | G94: 9122751.5 | H94: 10840095 | I94: 12712471 | J94: 64748333 | K94: 69110000 | L94: 72317447 | M94: 67514286 | N94: 67225714 | O94: 66331429 | P94: 64946955 | Q94: 65429198 | R94: 81203227 | S94: 94159863 | T94: 1.0429564e+08 | U94: 1.0365305e+08 | V94: 1.0398752e+08 | Y94: 50642881 | Z94: 36731423 | AA94: 44294648 | AB94: 44442457 | AC94: 50320914 | AD94: 62118570 | AE94: 76407396 | AF94: 93345860 | AG94: 1.0053466e+08 | AH94: 88265975 | AI94: 1.1211941e+08 | AJ94: 1.1090603e+08 | AK94: 1.3470718e+08 | AL94: 1.3604791e+08 | AM94: 1.00807e+08 | AN94: 1.4185336e+08 | AO94: 2.3246302e+08 | AP94: 4.4233787e+08 | AQ94: 3.7068763e+08 | AR94: 6.2111789e+08 | AS94: 1.0459985e+09 | AT94: 1.461139e+09 | AU94: 1.8067427e+09 | AV94: 2.4847459e+09 | AW94: 4.4107643e+09 | AX94: 8.2173691e+09 | AY94: 1.0086529e+10 | AZ94: 1.3071719e+10 | BA94: 1.9749894e+10 | BB94: 1.5027795e+10 | BC94: 1.6314443e+10 | BD94: 2.1357344e+10 | BE94: 2.2388344e+10 | BF94: 2.1948834e+10 | BG94: 2.1765453e+10 | BH94: 1.3185497e+10 | BI94: 1.1240809e+10 | BJ94: 1.2200914e+10 | BK94: 1.3097012e+10 | BL94: 1.1364134e+10 | BM94: 9.893816e+09 | BN94: 1.2215878e+10 | BO94: 1.3486789e+10 | BP94: 1.2116923e+10
A95: Greece | B95: GRC | C95: GDP (current US$) | D95: NY.GDP.MKTP.CD | E95: 4.3351917e+09 | F95: 4.9613993e+09 | G95: 5.2130432e+09 | H95: 5.8952814e+09 | I95: 6.6696698e+09 | J95: 7.6891484e+09 | K95: 8.5915225e+09 | L95: 9.2756008e+09 | M95: 1.0090675e+10 | N95: 1.1615656e+10 | O95: 1.3139864e+10 | P95: 14591750000 | Q95: 1.6885511e+10 | R95: 2.2347848e+10 | S95: 2.5351307e+10 | T95: 2.8525877e+10 | U95: 3.1152836e+10 | V95: 3.6176235e+10 | W95: 4.4270204e+10 | X95: 5.4481877e+10 | Y95: 5.6829664e+10 | Z95: 5.2346507e+10 | AA95: 5.461799e+10 | AB95: 4.9428874e+10 | AC95: 4.8020024e+10 | AD95: 4.7820851e+10 | AE95: 5.6379593e+10 | AF95: 6.565275e+10 | AG95: 7.6261278e+10 | AH95: 7.9169043e+10 | AI95: 9.7891092e+10 | AJ95: 1.0514323e+11 | AK95: 1.1622467e+11 | AL95: 1.0880906e+11 | AM95: 1.166018e+11 | AN95: 1.3687837e+11 | AO95: 1.4586161e+11 | AP95: 1.431576e+11 | AQ95: 1.4442817e+11 | AR95: 1.4258888e+11 | AS95: 1.3045776e+11 | AT95: 1.363093e+11 | AU95: 1.545642e+11 | AV95: 2.0237014e+11 | AW95: 2.4096356e+11 | AX95: 2.4787542e+11 | AY95: 2.7354673e+11 | AZ95: 3.1890283e+11 | BA95: 3.5590869e+11 | BB95: 3.313085e+11 | BC95: 2.9712496e+11 | BD95: 2.8299594e+11 | BE95: 2.4202931e+11 | BF95: 2.3890769e+11 | BG95: 2.3545813e+11 | BH95: 1.9568353e+11 | BI95: 1.9314815e+11 | BJ95: 1.9984441e+11 | BK95: 2.1204945e+11 | BL95: 2.0525276e+11 | BM95: 1.8848034e+11 | BN95: 2.1466781e+11 | BO95: 2.1758132e+11 | BP95: 2.3820631e+11
A96: Grenada | B96: GRD | C96: GDP (current US$) | D96: NY.GDP.MKTP.CD | V96: 71494495 | W96: 88322386 | X96: 1.0224436e+08 | Y96: 1.1090046e+08 | Z96: 1.1565192e+08 | AA96: 125435590 | AB96: 1.3180355e+08 | AC96: 1.4553331e+08 | AD96: 1.6772846e+08 | AE96: 1.8758952e+08 | AF96: 2.1500957e+08 | AG96: 2.3635752e+08 | AH96: 2.6732764e+08 | AI96: 2.7809876e+08 | AJ96: 3.0075789e+08 | AK96: 3.1016044e+08 | AL96: 3.0981219e+08 | AM96: 3.2511181e+08 | AN96: 3.4217252e+08 | AO96: 3.6691144e+08 | AP96: 3.9219059e+08 | AQ96: 4.4590359e+08 | AR96: 4.8200937e+08 | AS96: 5.2004437e+08 | AT96: 5.2044419e+08 | AU96: 5.4033693e+08 | AV96: 5.9101841e+08 | AW96: 5.9911859e+08 | AX96: 6.9555556e+08 | AY96: 6.9870067e+08 | AZ96: 7.5868359e+08 | BA96: 8.2597604e+08 | BB96: 7.7127556e+08 | BC96: 7.7101481e+08 | BD96: 7.7865556e+08 | BE96: 7.9988148e+08 | BF96: 8.4261852e+08 | BG96: 9.114963e+08 | BH96: 9.9700741e+08 | BI96: 1.0616407e+09 | BJ96: 1.1256852e+09 | BK96: 1.1665148e+09 | BL96: 1.2134852e+09 | BM96: 1.0434111e+09 | BN96: 1122800000 | BO96: 1.2245778e+09 | BP96: 1.3203342e+09
A97: Greenland | B97: GRL | C97: GDP (current US$) | D97: NY.GDP.MKTP.CD | O97: 69520027 | P97: 88466738 | Q97: 1.061013e+08 | R97: 1.4015375e+08 | S97: 1.6991895e+08 | T97: 2.1119063e+08 | U97: 2.4077942e+08 | V97: 2.8226975e+08 | W97: 3.5598743e+08 | X97: 4.2064582e+08 | Y97: 4.7605174e+08 | Z97: 4.3574899e+08 | AA97: 4.0240304e+08 | AB97: 4.1618407e+08 | AC97: 3.793719e+08 | AD97: 4.1287638e+08 | AE97: 6.0301629e+08 | AF97: 7.8739041e+08 | AG97: 8.9860767e+08 | AH97: 9.297999e+08 | AI97: 1.0189773e+09 | AJ97: 1.0165001e+09 | AK97: 1.0379162e+09 | AL97: 9.2721415e+08 | AM97: 1.0058875e+09 | AN97: 1.2089533e+09 | AO97: 1.1975156e+09 | AP97: 1.0721544e+09 | AQ97: 1.1498581e+09 | AR97: 1.1315551e+09 | AS97: 1.068025e+09 | AT97: 1.0861707e+09 | AU97: 1.1691367e+09 | AV97: 1.5587598e+09 | AW97: 1.8224998e+09 | AX97: 1.8498026e+09 | AY97: 2.0131069e+09 | AZ97: 2.2498113e+09 | BA97: 2.4990923e+09 | BB97: 2.5299639e+09 | BC97: 2.5031672e+09 | BD97: 2.6844614e+09 | BE97: 2.6096785e+09 | BF97: 2.684947e+09 | BG97: 2.8420657e+09 | BH97: 2.499113e+09 | BI97: 2.7071395e+09 | BJ97: 2.8516137e+09 | BK97: 3.0557821e+09 | BL97: 2.99731e+09 | BM97: 3.0828847e+09 | BN97: 3.2358095e+09
A98: Guatemala | B98: GTM | C98: GDP (current US$) | D98: NY.GDP.MKTP.CD | E98: 1043599900 | F98: 1076699900 | G98: 1143600000 | H98: 1262800000 | I98: 1299099900 | J98: 1331399900 | K98: 1390700000 | L98: 1453500000 | M98: 1610500000 | N98: 1715399900 | O98: 1904000000 | P98: 1984800000 | Q98: 2101300000 | R98: 2569200100 | S98: 3161499900 | T98: 3645900000 | U98: 4365300200 | V98: 5480500200 | W98: 6070600200 | X98: 6902600200 | Y98: 7878700000 | Z98: 8607500300 | AA98: 8716999700 | AB98: 9050000400 | AC98: 9470000100 | AD98: 9.7216521e+09 | AE98: 7.2319635e+09 | AF98: 7084399840 | AG98: 7.8416028e+09 | AH98: 8.4107244e+09 | AI98: 7.6501968e+09 | AJ98: 9.4061351e+09 | AK98: 1.0440782e+10 | AL98: 1.1400017e+10 | AM98: 1.2983233e+10 | AN98: 1.4655404e+10 | AO98: 1.5674836e+10 | AP98: 1.7790026e+10 | AQ98: 1.9395492e+10 | AR98: 1.8318412e+10 | AS98: 1.9288929e+10 | AT98: 1.840522e+10 | AU98: 2.0444206e+10 | AV98: 2.1576352e+10 | AW98: 2.3577298e+10 | AX98: 2.6783389e+10 | AY98: 2.9744247e+10 | AZ98: 3.3567851e+10 | BA98: 3.850372e+10 | BB98: 3.7126148e+10 | BC98: 4.0676578e+10 | BD98: 4.6876006e+10 | BE98: 4.9593929e+10 | BF98: 5.2996446e+10 | BG98: 5.7852153e+10 | BH98: 6.2186065e+10 | BI98: 6.6053403e+10 | BJ98: 7.1653754e+10 | BK98: 7.3328366e+10 | BL98: 7.7172317e+10 | BM98: 7.7715183e+10 | BN98: 8.6053083e+10 | BO98: 9.500333e+10 | BP98: 1.0205047e+11
A99: Guam | B99: GUM | C99: GDP (current US$) | D99: NY.GDP.MKTP.CD | AU99: 3394000000 | AV99: 3569000000 | AW99: 3869000000 | AX99: 4213000000 | AY99: 4238000000 | AZ99: 4397000000 | BA99: 4658000000 | BB99: 4828000000 | BC99: 4949000000 | BD99: 4984000000 | BE99: 5265000000 | BF99: 5399000000 | BG99: 5610000000 | BH99: 5799000000 | BI99: 5901000000 | BJ99: 6013000000 | BK99: 6051000000 | BL99: 6355000000 | BM99: 5916000000 | BN99: 6234000000 | BO99: 6910000000
A100: Guyana | B100: GUY | C100: GDP (current US$) | D100: NY.GDP.MKTP.CD | E100: 1.7021624e+08 | F100: 1.8584954e+08 | G100: 1.9494951e+08 | H100: 1.7575789e+08 | I100: 1.9477451e+08 | J100: 2.1323529e+08 | K100: 2.2870588e+08 | L100: 2.5017647e+08 | M100: 229750000 | N100: 249300000 | O100: 267800000 | P100: 282050000 | Q100: 2.8538095e+08 | R100: 3.0704762e+08 | S100: 4.3395455e+08 | T100: 4.9479167e+08 | U100: 454440000 | V100: 449880000 | W100: 507080000 | X100: 530440000 | Y100: 603200000 | Z100: 5.7035711e+08 | AA100: 482000000 | AB100: 4.8933333e+08 | AC100: 4.3763161e+08 | AD100: 4.5348837e+08 | AE100: 5.0465114e+08 | AF100: 3.5459185e+08 | AG100: 413799990 | AH100: 3.7977939e+08 | AI100: 3.9658226e+08 | AJ100: 3.4853309e+08 | AK100: 3.7357314e+08 | AL100: 4.5410138e+08 | AM100: 5.4087493e+08 | AN100: 6.2162679e+08 | AO100: 7.05406e+08 | AP100: 7.4913801e+08 | AQ100: 7.1753068e+08 | AR100: 6.9475499e+08 | AS100: 7.126679e+08 | AT100: 7.1216745e+08 | AU100: 7.2613143e+08 | AV100: 7.4306395e+08 | AW100: 7.8781438e+08 | AX100: 8.2488055e+08 | AY100: 2.379818e+09 | AZ100: 2.7309716e+09 | BA100: 3.0251874e+09 | BB100: 3.1656632e+09 | BC100: 3.4329125e+09 | BD100: 3.6913843e+09 | BE100: 4.0630885e+09 | BF100: 4.1678009e+09 | BG100: 4.1276602e+09 | BH100: 4.2798402e+09 | BI100: 4.4826973e+09 | BJ100: 4.7481743e+09 | BK100: 4.787637e+09 | BL100: 5.1737602e+09 | BM100: 5.4712566e+09 | BN100: 8.0413621e+09 | BO100: 1.4718388e+10 | BP100: 1.6786302e+10
A101: High income | B101: HIC | C101: GDP (current US$) | D101: NY.GDP.MKTP.CD | E101: 1.0926819e+12 | F101: 1.1655716e+12 | G101: 1.2605449e+12 | H101: 1.3559134e+12 | I101: 1.4820061e+12 | J101: 1.6108808e+12 | K101: 1.762771e+12 | L101: 1.8832456e+12 | M101: 2.0428199e+12 | N101: 2.2516707e+12 | O101: 2471430871017 | P101: 2.7457455e+12 | Q101: 3.1895018e+12 | R101: 3.8692034e+12 | S101: 4.3748878e+12 | T101: 4.8819687e+12 | U101: 5.3167055e+12 | V101: 6.0176493e+12 | W101: 7.2244232e+12 | X101: 8.3490338e+12 | Y101: 9.3189735e+12 | Z101: 9.4635296e+12 | AA101: 9.3707883e+12 | AB101: 9.6803756e+12 | AC101: 1.009135e+13 | AD101: 1.058966e+13 | AE101: 1.2863824e+13 | AF101: 1.4914231e+13 | AG101: 1.6785556e+13 | AH101: 1.7481687e+13 | AI101: 1.9577046e+13 | AJ101: 2.0659798e+13 | AK101: 2.2119166e+13 | AL101: 2.2272082e+13 | AM101: 2.3818722e+13 | AN101: 2.6430046e+13 | AO101: 2.6643709e+13 | AP101: 2.6208151e+13 | AQ101: 2.6174131e+13 | AR101: 2.7403905e+13 | AS101: 2.8036717e+13 | AT101: 2.7811072e+13 | AU101: 2.902275e+13 | AV101: 3.2574955e+13 | AW101: 3.6387609e+13 | AX101: 3.8623901e+13 | AY101: 40986059390577 | AZ101: 4.5098648e+13 | BA101: 4.8338201e+13 | BB101: 4.4940316e+13 | BC101: 47340327876456 | BD101: 5.1524951e+13 | BE101: 5.1710004e+13 | BF101: 5.2439877e+13 | BG101: 5.3310163e+13 | BH101: 4.9773105e+13 | BI101: 5.0737237e+13 | BJ101: 5.3336789e+13 | BK101: 5.6684557e+13 | BL101: 5.7218295e+13 | BM101: 5.5791129e+13 | BN101: 6.2461026e+13 | BO101: 6.4444446e+13 | BP101: 6.7653743e+13
A102: Hong Kong SAR, China | B102: HKG | C102: GDP (current US$) | D102: NY.GDP.MKTP.CD | E102: 1.3207967e+09 | F102: 1.3836817e+09 | G102: 1.6123464e+09 | H102: 1.9352983e+09 | I102: 2.2064665e+09 | J102: 2.4350785e+09 | K102: 2.489845e+09 | L102: 2.692475e+09 | M102: 2.7169644e+09 | N102: 3.1897401e+09 | O102: 3.8007665e+09 | P102: 4.4760019e+09 | Q102: 5.7100902e+09 | R102: 8.0301176e+09 | S102: 9.3886954e+09 | T102: 1.004809e+10 | U102: 1.2876366e+10 | V102: 1.5719434e+10 | W102: 1.8315136e+10 | X102: 2.2526185e+10 | Y102: 2.8861858e+10 | Z102: 3.1055226e+10 | AA102: 3.2291216e+10 | AB102: 2.9907227e+10 | AC102: 3.3511384e+10 | AD102: 3.5699772e+10 | AE102: 4.1075397e+10 | AF102: 5.0622896e+10 | AG102: 5.9707405e+10 | AH102: 6.8790219e+10 | AI102: 7.6928785e+10 | AJ102: 8.8959998e+10 | AK102: 1.0427251e+11 | AL102: 120354212475 | AM102: 1.3581177e+11 | AN102: 1.446523e+11 | AO102: 1.5971818e+11 | AP102: 1.7735317e+11 | AQ102: 1.6888544e+11 | AR102: 1.657681e+11 | AS102: 1.7166889e+11 | AT102: 1.6940433e+11 | AU102: 1.6634887e+11 | AV102: 1.6138556e+11 | AW102: 1.6909977e+11 | AX102: 1.8156931e+11 | AY102: 1.9353544e+11 | AZ102: 2.1159694e+11 | BA102: 2.1927875e+11 | BB102: 2.140478e+11 | BC102: 2.2863867e+11 | BD102: 2.4851362e+11 | BE102: 2.6262887e+11 | BF102: 2.7569688e+11 | BG102: 2.9146e+11 | BH102: 3.0938562e+11 | BI102: 3.2086032e+11 | BJ102: 3.4127329e+11 | BK102: 3.6173107e+11 | BL102: 3.6307455e+11 | BM102: 3.4494315e+11 | BN102: 3.6895417e+11 | BO102: 3.5869626e+11 | BP102: 3.8205457e+11
...

Sheet totalExpenditure
B1: Expenditure on defense | BA1: Expenditure on public order & safety | CZ1: GDP
A2: WORLD | B2: =B3*CZ2/CZ3 -> 5.2047727e+11 | C2: =C3*DA2/DA3 -> 5.6322895e+11 | D2: =D3*DB2/DB3 -> 6.3985668e+11 | E2: =E3*DC2/DC3 -> 6.9431913e+11 | F2: =F3*DD2/DD3 -> 6.9508391e+11 | G2: =G3*DE2/DE3 -> 7.5774891e+11 | H2: =H3*DF2/DF3 -> 8.544231e+11 | I2: =I3*DG2/DG3 -> 9.8909354e+11 | ... AZ2: =AZ3*EX2/EX3 -> 6.782079e+11 | BA2: =BA3*CZ2/CZ3 -> 9.8499748e+10 | BB2: =BB3*DA2/DA3 -> 1.1889353e+11 | BC2: =BC3*DB2/DB3 -> 1.4361942e+11 | BD2: =BD3*DC2/DC3 -> 1.6773888e+11 | BE2: =BE3*DD2/DD3 -> 1.7702512e+11 | BF2: =BF3*DE2/DE3 -> 1.9642617e+11 | BG2: =BG3*DF2/DF3 -> 2.2709209e+11 | BH2: =BH3*DG2/DG3 -> 2.6092652e+11 | ... CY2: =CY3*EX2/EX3 -> 1.5791109e+12 | CZ2: =gDP!Q265 -> 3.832675e+12 | DA2: =gDP!R265 -> 4.6624913e+12 | DB2: =gDP!S265 -> 5.3589336e+12 | DC2: =gDP!T265 -> 5.9906741e+12 | DD2: =gDP!U265 -> 6.5082763e+12 | DE2: =gDP!V265 -> 7.3567855e+12 | DF2: =gDP!W265 -> 8.7008463e+12 | DG2: =gDP!X265 -> 1.0113431e+13 | ... EX2: =gDP!BO265 -> 101225059591363
A3: SAMPLE TOTAL | B3: =SUMIF(CZ5:CZ270,">0",B5:B270) -> 173703138000 | C3: =SUMIF(DA5:DA270,">0",C5:C270) -> 172185420800 | D3: =SUMIF(DB5:DB270,">0",D5:D270) -> 184502014200 | E3: =SUMIF(DC5:DC270,">0",E5:E270) -> 195280373600 | F3: =SUMIF(DD5:DD270,">0",F5:F270) -> 200080401600 | G3: =SUMIF(DE5:DE270,">0",G5:G270) -> 2.1442808e+11 | H3: =SUMIF(DF5:DF270,">0",H5:H270) -> 2.3092702e+11 | I3: =SUMIF(DG5:DG270,">0",I5:I270) -> 2.5695317e+11 | ... AZ3: =SUMIF(EX5:EX270,">0",AZ5:AZ270) -> 1.4481939e+10 | BA3: =SUMIF(CZ5:CZ270,">0",BA5:BA270) -> 3.2873127e+10 | BB3: =SUMIF(DA5:DA270,">0",BB5:BB270) -> 36347088000 | BC3: =SUMIF(DB5:DB270,">0",BC5:BC270) -> 41412512400 | BD3: =SUMIF(DC5:DC270,">0",BD5:BD270) -> 4.7177312e+10 | BE3: =SUMIF(DD5:DD270,">0",BE5:BE270) -> 50956806400 | BF3: =SUMIF(DE5:DE270,">0",BF5:BF270) -> 5.5584754e+10 | BG3: =SUMIF(DF5:DF270,">0",BG5:BG270) -> 6.1376734e+10 | BH3: =SUMIF(DG5:DG270,">0",BH5:BH270) -> 67785191400 | ... CY3: =SUMIF(EX5:EX270,">0",CY5:CY270) -> 3.3719141e+10 | CZ3: {=SUM(_xlfn.IFNA(CZ5:CZ270,""))} -> 1279110000000 | DA3: {=SUM(_xlfn.IFNA(DA5:DA270,""))} -> 1425376000000 | DB3: {=SUM(_xlfn.IFNA(DB5:DB270,""))} -> 1545243000000 | DC3: {=SUM(_xlfn.IFNA(DC5:DC270,""))} -> 1684904000000 | DD3: {=SUM(_xlfn.IFNA(DD5:DD270,""))} -> 1873412000000 | DE3: {=SUM(_xlfn.IFNA(DE5:DE270,""))} -> 2081826000000 | DF3: {=SUM(_xlfn.IFNA(DF5:DF270,""))} -> 2351599000000 | DG3: {=SUM(_xlfn.IFNA(DG5:DG270,""))} -> 2627333000000 | ... EX3: {=SUM(_xlfn.IFNA(EX5:EX270,""))} -> 2.1614834e+12
A4: Country Code | B4: 1972 | C4: 1973 | D4: 1974 | E4: 1975 | F4: 1976 | G4: 1977 | H4: 1978 | I4: 1979 | J4: 1980 | K4: 1981 | L4: 1982 | M4: 1983 | N4: 1984 | O4: 1985 | P4: 1986 | Q4: 1987 | R4: 1988 | S4: 1989 | T4: 1990 | U4: 1991 | V4: 1992 | W4: 1993 | X4: 1994 | Y4: 1995 | Z4: 1996 | AA4: 1997 | AB4: 1998 | AC4: 1999 | AD4: 2000 | AE4: 2001 | AF4: 2002 | AG4: 2003 | AH4: 2004 | AI4: 2005 | AJ4: 2006 | AK4: 2007 | AL4: 2008 | AM4: 2009 | AN4: 2010 | AO4: 2011 | AP4: 2012 | AQ4: 2013 | AR4: 2014 | AS4: 2015 | AT4: 2016 | AU4: 2017 | AV4: 2018 | AW4: 2019 | AX4: 2020 | AY4: 2021 | AZ4: 2022 | BA4: 1972 | BB4: 1973 | BC4: 1974 | BD4: 1975 | BE4: 1976 | BF4: 1977 | BG4: 1978 | BH4: 1979 | BI4: 1980 | BJ4: 1981 | BK4: 1982 | BL4: 1983 | BM4: 1984 | BN4: 1985 | BO4: 1986 | BP4: 1987 | BQ4: 1988 | BR4: 1989 | BS4: 1990 | BT4: 1991 | BU4: 1992 | BV4: 1993 | BW4: 1994 | BX4: 1995 | BY4: 1996 | BZ4: 1997 | CA4: 1998 | CB4: 1999 | CC4: 2000 | CD4: 2001 | CE4: 2002 | CF4: 2003 | CG4: 2004 | CH4: 2005 | CI4: 2006 | CJ4: 2007 | CK4: 2008 | CL4: 2009 | CM4: 2010 | CN4: 2011 | CO4: 2012 | CP4: 2013 | CQ4: 2014 | CR4: 2015 | CS4: 2016 | CT4: 2017 | CU4: 2018 | CV4: 2019 | CW4: 2020 | CX4: 2021 | CY4: 2022 | CZ4: 1972 | DA4: 1973 | DB4: 1974 | DC4: 1975 | DD4: 1976 | DE4: 1977 | DF4: 1978 | DG4: 1979 | DH4: 1980 | DI4: 1981 | DJ4: 1982 | DK4: 1983 | DL4: 1984 | DM4: 1985 | DN4: 1986 | DO4: 1987 | DP4: 1988 | DQ4: 1989 | DR4: 1990 | DS4: 1991 | DT4: 1992 | DU4: 1993 | DV4: 1994 | DW4: 1995 | DX4: 1996 | DY4: 1997 | DZ4: 1998 | EA4: 1999 | EB4: 2000 | EC4: 2001 | ED4: 2002 | EE4: 2003 | EF4: 2004 | EG4: 2005 | EH4: 2006 | EI4: 2007 | EJ4: 2008 | EK4: 2009 | EL4: 2010 | EM4: 2011 | EN4: 2012 | EO4: 2013 | EP4: 2014 | EQ4: 2015 | ER4: 2016 | ES4: 2017 | ET4: 2018 | EU4: 2019 | EV4: 2020 | EW4: 2021 | EX4: 2022
A5: ABW | B5: =IF(INDEX([2]pivotTable!B$3:B$308,MATCH(totalExpenditure!$A5,[2]pivotTable!$A$3:$A$308,0))/100*INDEX(gDP!Q$6:Q$271,MATCH(totalExpenditure!$A5,gDP!$B$6:$B$271))=0,"",INDEX([2]pivotTable!B$3:B$308,MATCH(totalExpenditure!$A5,[2]pivotTable!$A$3:$A$308,0))/100*INDEX(gDP!Q$6:Q$271,MATCH(totalExpenditure!$A5,gDP!$B$6:$B$271))) -> #N/A | C5: =IF(INDEX([2]pivotTable!C$3:C$308,MATCH(totalExpenditure!$A5,[2]pivotTable!$A$3:$A$308,0))/100*INDEX(gDP!R$6:R$271,MATCH(totalExpenditure!$A5,gDP!$B$6:$B$271))=0,"",INDEX([2]pivotTable!C$3:C$308,MATCH(totalExpenditure!$A5,[2]pivotTable!$A$3:$A$308,0))/100*INDEX(gDP!R$6:R$271,MATCH(totalExpenditure!$A5,gDP!$B$6:$B$271))) -> #N/A | D5: =IF(INDEX([2]pivotTable!D$3:D$308,MATCH(totalExpenditure!$A5,[2]pivotTable!$A$3:$A$308,0))/100*INDEX(gDP!S$6:S$271,MATCH(totalExpenditure!$A5,gDP!$B$6:$B$271))=0,"",INDEX([2]pivotTable!D$3:D$308,MATCH(totalExpenditure!$A5,[2]pivotTable!$A$3:$A$308,0))/100*INDEX(gDP!S$6:S$271,MATCH(totalExpenditure!$A5,gDP!$B$6:$B$271))) -> #N/A | E5: =IF(INDEX([2]pivotTable!E$3:E$308,MATCH(totalExpenditure!$A5,[2]pivotTable!$A$3:$A$308,0))/100*INDEX(gDP!T$6:T$271,MATCH(totalExpenditure!$A5,gDP!$B$6:$B$271))=0,"",INDEX([2]pivotTable!E$3:E$308,MATCH(totalExpenditure!$A5,[2]pivotTable!$A$3:$A$308,0))/100*INDEX(gDP!T$6:T$271,MATCH(totalExpenditure!$A5,gDP!$B$6:$B$271))) -> #N/A | F5: =IF(INDEX([2]pivotTable!F$3:F$308,MATCH(totalExpenditure!$A5,[2]pivotTable!$A$3:$A$308,0))/100*INDEX(gDP!U$6:U$271,MATCH(totalExpenditure!$A5,gDP!$B$6:$B$271))=0,"",INDEX([2]pivotTable!F$3:F$308,MATCH(totalExpenditure!$A5,[2]pivotTable!$A$3:$A$308,0))/100*INDEX(gDP!U$6:U$271,MATCH(totalExpenditure!$A5,gDP!$B$6:$B$271))) -> #N/A | G5: =IF(INDEX([2]pivotTable!G$3:G$308,MATCH(totalExpenditure!$A5,[2]pivotTable!$A$3:$A$308,0))/100*INDEX(gDP!V$6:V$271,MATCH(totalExpenditure!$A5,gDP!$B$6:$B$271))=0,"",INDEX([2]pivotTable!G$3:G$308,MATCH(totalExpenditure!$A5,[2]pivotTable!$A$3:$A$308,0))/100*INDEX(gDP!V$6:V$271,MATCH(totalExpenditure!$A5,gDP!$B$6:$B$271))) -> #N/A | H5: =IF(INDEX([2]pivotTable!H$3:H$308,MATCH(totalExpenditure!$A5,[2]pivotTable!$A$3:$A$308,0))/100*INDEX(gDP!W$6:W$271,MATCH(totalExpenditure!$A5,gDP!$B$6:$B$271))=0,"",INDEX([2]pivotTable!H$3:H$308,MATCH(totalExpenditure!$A5,[2]pivotTable!$A$3:$A$308,0))/100*INDEX(gDP!W$6:W$271,MATCH(totalExpenditure!$A5,gDP!$B$6:$B$271))) -> #N/A | I5: =IF(INDEX([2]pivotTable!I$3:I$308,MATCH(totalExpenditure!$A5,[2]pivotTable!$A$3:$A$308,0))/100*INDEX(gDP!X$6:X$271,MATCH(totalExpenditure!$A5,gDP!$B$6:$B$271))=0,"",INDEX([2]pivotTable!I$3:I$308,MATCH(totalExpenditure!$A5,[2]pivotTable!$A$3:$A$308,0))/100*INDEX(gDP!X$6:X$271,MATCH(totalExpenditure!$A5,gDP!$B$6:$B$271))) -> #N/A | ... AZ5: =IF(INDEX([2]pivotTable!AZ$3:AZ$308,MATCH(totalExpenditure!$A5,[2]pivotTable!$A$3:$A$308,0))/100*INDEX(gDP!BO$6:BO$271,MATCH(totalExpenditure!$A5,gDP!$B$6:$B$271))=0,"",INDEX([2]pivotTable!AZ$3:AZ$308,MATCH(totalExpenditure!$A5,[2]pivotTable!$A$3:$A$308,0))/100*INDEX(gDP!BO$6:BO$271,MATCH(totalExpenditure!$A5,gDP!$B$6:$B$271))) -> #N/A | BA5: =IF(INDEX([2]pivotTable!B$310:B$615,MATCH(totalExpenditure!$A5,[2]pivotTable!$A$310:$A$615,0))/100*INDEX(gDP!Q$6:Q$271,MATCH(totalExpenditure!$A5,gDP!$B$6:$B$271))=0,"",INDEX([2]pivotTable!B$310:B$615,MATCH(totalExpenditure!$A5,[2]pivotTable!$A$310:$A$615,0))/100*INDEX(gDP!Q$6:Q$271,MATCH(totalExpenditure!$A5,gDP!$B$6:$B$271))) -> #N/A | BB5: =IF(INDEX([2]pivotTable!C$310:C$615,MATCH(totalExpenditure!$A5,[2]pivotTable!$A$310:$A$615,0))/100*INDEX(gDP!R$6:R$271,MATCH(totalExpenditure!$A5,gDP!$B$6:$B$271))=0,"",INDEX([2]pivotTable!C$310:C$615,MATCH(totalExpenditure!$A5,[2]pivotTable!$A$310:$A$615,0))/100*INDEX(gDP!R$6:R$271,MATCH(totalExpenditure!$A5,gDP!$B$6:$B$271))) -> #N/A | BC5: =IF(INDEX([2]pivotTable!D$310:D$615,MATCH(totalExpenditure!$A5,[2]pivotTable!$A$310:$A$615,0))/100*INDEX(gDP!S$6:S$271,MATCH(totalExpenditure!$A5,gDP!$B$6:$B$271))=0,"",INDEX([2]pivotTable!D$310:D$615,MATCH(totalExpenditure!$A5,[2]pivotTable!$A$310:$A$615,0))/100*INDEX(gDP!S$6:S$271,MATCH(totalExpenditure!$A5,gDP!$B$6:$B$271))) -> #N/A | BD5: =IF(INDEX([2]pivotTable!E$310:E$615,MATCH(totalExpenditure!$A5,[2]pivotTable!$A$310:$A$615,0))/100*INDEX(gDP!T$6:T$271,MATCH(totalExpenditure!$A5,gDP!$B$6:$B$271))=0,"",INDEX([2]pivotTable!E$310:E$615,MATCH(totalExpenditure!$A5,[2]pivotTable!$A$310:$A$615,0))/100*INDEX(gDP!T$6:T$271,MATCH(totalExpenditure!$A5,gDP!$B$6:$B$271))) -> #N/A | BE5: =IF(INDEX([2]pivotTable!F$310:F$615,MATCH(totalExpenditure!$A5,[2]pivotTable!$A$310:$A$615,0))/100*INDEX(gDP!U$6:U$271,MATCH(totalExpenditure!$A5,gDP!$B$6:$B$271))=0,"",INDEX([2]pivotTable!F$310:F$615,MATCH(totalExpenditure!$A5,[2]pivotTable!$A$310:$A$615,0))/100*INDEX(gDP!U$6:U$271,MATCH(totalExpenditure!$A5,gDP!$B$6:$B$271))) -> #N/A | BF5: =IF(INDEX([2]pivotTable!G$310:G$615,MATCH(totalExpenditure!$A5,[2]pivotTable!$A$310:$A$615,0))/100*INDEX(gDP!V$6:V$271,MATCH(totalExpenditure!$A5,gDP!$B$6:$B$271))=0,"",INDEX([2]pivotTable!G$310:G$615,MATCH(totalExpenditure!$A5,[2]pivotTable!$A$310:$A$615,0))/100*INDEX(gDP!V$6:V$271,MATCH(totalExpenditure!$A5,gDP!$B$6:$B$271))) -> #N/A | BG5: =IF(INDEX([2]pivotTable!H$310:H$615,MATCH(totalExpenditure!$A5,[2]pivotTable!$A$310:$A$615,0))/100*INDEX(gDP!W$6:W$271,MATCH(totalExpenditure!$A5,gDP!$B$6:$B$271))=0,"",INDEX([2]pivotTable!H$310:H$615,MATCH(totalExpenditure!$A5,[2]pivotTable!$A$310:$A$615,0))/100*INDEX(gDP!W$6:W$271,MATCH(totalExpenditure!$A5,gDP!$B$6:$B$271))) -> #N/A | BH5: =IF(INDEX([2]pivotTable!I$310:I$615,MATCH(totalExpenditure!$A5,[2]pivotTable!$A$310:$A$615,0))/100*INDEX(gDP!X$6:X$271,MATCH(totalExpenditure!$A5,gDP!$B$6:$B$271))=0,"",INDEX([2]pivotTable!I$310:I$615,MATCH(totalExpenditure!$A5,[2]pivotTable!$A$310:$A$615,0))/100*INDEX(gDP!X$6:X$271,MATCH(totalExpenditure!$A5,gDP!$B$6:$B$271))) -> #N/A | ... CY5: =IF(INDEX([2]pivotTable!AZ$310:AZ$615,MATCH(totalExpenditure!$A5,[2]pivotTable!$A$310:$A$615,0))/100*INDEX(gDP!BO$6:BO$271,MATCH(totalExpenditure!$A5,gDP!$B$6:$B$271))=0,"",INDEX([2]pivotTable!AZ$310:AZ$615,MATCH(totalExpenditure!$A5,[2]pivotTable!$A$310:$A$615,0))/100*INDEX(gDP!BO$6:BO$271,MATCH(totalExpenditure!$A5,gDP!$B$6:$B$271))) -> #N/A | CZ5: =IF(B5="","",IF(BA5="","",B5-B5+INDEX(gDP!Q$6:Q$271,MATCH(totalExpenditure!$A5,gDP!$B$6:$B$271)))) -> #N/A | DA5: =IF(C5="","",IF(BB5="","",C5-C5+INDEX(gDP!R$6:R$271,MATCH(totalExpenditure!$A5,gDP!$B$6:$B$271)))) -> #N/A | DB5: =IF(D5="","",IF(BC5="","",D5-D5+INDEX(gDP!S$6:S$271,MATCH(totalExpenditure!$A5,gDP!$B$6:$B$271)))) -> #N/A | DC5: =IF(E5="","",IF(BD5="","",E5-E5+INDEX(gDP!T$6:T$271,MATCH(totalExpenditure!$A5,gDP!$B$6:$B$271)))) -> #N/A | DD5: =IF(F5="","",IF(BE5="","",F5-F5+INDEX(gDP!U$6:U$271,MATCH(totalExpenditure!$A5,gDP!$B$6:$B$271)))) -> #N/A | DE5: =IF(G5="","",IF(BF5="","",G5-G5+INDEX(gDP!V$6:V$271,MATCH(totalExpenditure!$A5,gDP!$B$6:$B$271)))) -> #N/A | DF5: =IF(H5="","",IF(BG5="","",H5-H5+INDEX(gDP!W$6:W$271,MATCH(totalExpenditure!$A5,gDP!$B$6:$B$271)))) -> #N/A | DG5: =IF(I5="","",IF(BH5="","",I5-I5+INDEX(gDP!X$6:X$271,MATCH(totalExpenditure!$A5,gDP!$B$6:$B$271)))) -> #N/A | ... EX5: =IF(AZ5="","",IF(CY5="","",AZ5-AZ5+INDEX(gDP!BO$6:BO$271,MATCH(totalExpenditure!$A5,gDP!$B$6:$B$271)))) -> #N/A
A6: AFE | B6: =IF(INDEX([2]pivotTable!B$3:B$308,MATCH(totalExpenditure!$A6,[2]pivotTable!$A$3:$A$308,0))/100*INDEX(gDP!Q$6:Q$271,MATCH(totalExpenditure!$A6,gDP!$B$6:$B$271))=0,"",INDEX([2]pivotTable!B$3:B$308,MATCH(totalExpenditure!$A6,[2]pivotTable!$A$3:$A$308,0))/100*INDEX(gDP!Q$6:Q$271,MATCH(totalExpenditure!$A6,gDP!$B$6:$B$271))) -> #N/A | C6: =IF(INDEX([2]pivotTable!C$3:C$308,MATCH(totalExpenditure!$A6,[2]pivotTable!$A$3:$A$308,0))/100*INDEX(gDP!R$6:R$271,MATCH(totalExpenditure!$A6,gDP!$B$6:$B$271))=0,"",INDEX([2]pivotTable!C$3:C$308,MATCH(totalExpenditure!$A6,[2]pivotTable!$A$3:$A$308,0))/100*INDEX(gDP!R$6:R$271,MATCH(totalExpenditure!$A6,gDP!$B$6:$B$271))) -> #N/A | D6: =IF(INDEX([2]pivotTable!D$3:D$308,MATCH(totalExpenditure!$A6,[2]pivotTable!$A$3:$A$308,0))/100*INDEX(gDP!S$6:S$271,MATCH(totalExpenditure!$A6,gDP!$B$6:$B$271))=0,"",INDEX([2]pivotTable!D$3:D$308,MATCH(totalExpenditure!$A6,[2]pivotTable!$A$3:$A$308,0))/100*INDEX(gDP!S$6:S$271,MATCH(totalExpenditure!$A6,gDP!$B$6:$B$271))) -> #N/A | E6: =IF(INDEX([2]pivotTable!E$3:E$308,MATCH(totalExpenditure!$A6,[2]pivotTable!$A$3:$A$308,0))/100*INDEX(gDP!T$6:T$271,MATCH(totalExpenditure!$A6,gDP!$B$6:$B$271))=0,"",INDEX([2]pivotTable!E$3:E$308,MATCH(totalExpenditure!$A6,[2]pivotTable!$A$3:$A$308,0))/100*INDEX(gDP!T$6:T$271,MATCH(totalExpenditure!$A6,gDP!$B$6:$B$271))) -> #N/A | F6: =IF(INDEX([2]pivotTable!F$3:F$308,MATCH(totalExpenditure!$A6,[2]pivotTable!$A$3:$A$308,0))/100*INDEX(gDP!U$6:U$271,MATCH(totalExpenditure!$A6,gDP!$B$6:$B$271))=0,"",INDEX([2]pivotTable!F$3:F$308,MATCH(totalExpenditure!$A6,[2]pivotTable!$A$3:$A$308,0))/100*INDEX(gDP!U$6:U$271,MATCH(totalExpenditure!$A6,gDP!$B$6:$B$271))) -> #N/A | G6: =IF(INDEX([2]pivotTable!G$3:G$308,MATCH(totalExpenditure!$A6,[2]pivotTable!$A$3:$A$308,0))/100*INDEX(gDP!V$6:V$271,MATCH(totalExpenditure!$A6,gDP!$B$6:$B$271))=0,"",INDEX([2]pivotTable!G$3:G$308,MATCH(totalExpenditure!$A6,[2]pivotTable!$A$3:$A$308,0))/100*INDEX(gDP!V$6:V$271,MATCH(totalExpenditure!$A6,gDP!$B$6:$B$271))) -> #N/A | H6: =IF(INDEX([2]pivotTable!H$3:H$308,MATCH(totalExpenditure!$A6,[2]pivotTable!$A$3:$A$308,0))/100*INDEX(gDP!W$6:W$271,MATCH(totalExpenditure!$A6,gDP!$B$6:$B$271))=0,"",INDEX([2]pivotTable!H$3:H$308,MATCH(totalExpenditure!$A6,[2]pivotTable!$A$3:$A$308,0))/100*INDEX(gDP!W$6:W$271,MATCH(totalExpenditure!$A6,gDP!$B$6:$B$271))) -> #N/A | I6: =IF(INDEX([2]pivotTable!I$3:I$308,MATCH(totalExpenditure!$A6,[2]pivotTable!$A$3:$A$308,0))/100*INDEX(gDP!X$6:X$271,MATCH(totalExpenditure!$A6,gDP!$B$6:$B$271))=0,"",INDEX([2]pivotTable!I$3:I$308,MATCH(totalExpenditure!$A6,[2]pivotTable!$A$3:$A$308,0))/100*INDEX(gDP!X$6:X$271,MATCH(totalExpenditure!$A6,gDP!$B$6:$B$271))) -> #N/A | ... AZ6: =IF(INDEX([2]pivotTable!AZ$3:AZ$308,MATCH(totalExpenditure!$A6,[2]pivotTable!$A$3:$A$308,0))/100*INDEX(gDP!BO$6:BO$271,MATCH(totalExpenditure!$A6,gDP!$B$6:$B$271))=0,"",INDEX([2]pivotTable!AZ$3:AZ$308,MATCH(totalExpenditure!$A6,[2]pivotTable!$A$3:$A$308,0))/100*INDEX(gDP!BO$6:BO$271,MATCH(totalExpenditure!$A6,gDP!$B$6:$B$271))) -> #N/A | BA6: =IF(INDEX([2]pivotTable!B$310:B$615,MATCH(totalExpenditure!$A6,[2]pivotTable!$A$310:$A$615,0))/100*INDEX(gDP!Q$6:Q$271,MATCH(totalExpenditure!$A6,gDP!$B$6:$B$271))=0,"",INDEX([2]pivotTable!B$310:B$615,MATCH(totalExpenditure!$A6,[2]pivotTable!$A$310:$A$615,0))/100*INDEX(gDP!Q$6:Q$271,MATCH(totalExpenditure!$A6,gDP!$B$6:$B$271))) -> #N/A | BB6: =IF(INDEX([2]pivotTable!C$310:C$615,MATCH(totalExpenditure!$A6,[2]pivotTable!$A$310:$A$615,0))/100*INDEX(gDP!R$6:R$271,MATCH(totalExpenditure!$A6,gDP!$B$6:$B$271))=0,"",INDEX([2]pivotTable!C$310:C$615,MATCH(totalExpenditure!$A6,[2]pivotTable!$A$310:$A$615,0))/100*INDEX(gDP!R$6:R$271,MATCH(totalExpenditure!$A6,gDP!$B$6:$B$271))) -> #N/A | BC6: =IF(INDEX([2]pivotTable!D$310:D$615,MATCH(totalExpenditure!$A6,[2]pivotTable!$A$310:$A$615,0))/100*INDEX(gDP!S$6:S$271,MATCH(totalExpenditure!$A6,gDP!$B$6:$B$271))=0,"",INDEX([2]pivotTable!D$310:D$615,MATCH(totalExpenditure!$A6,[2]pivotTable!$A$310:$A$615,0))/100*INDEX(gDP!S$6:S$271,MATCH(totalExpenditure!$A6,gDP!$B$6:$B$271))) -> #N/A | BD6: =IF(INDEX([2]pivotTable!E$310:E$615,MATCH(totalExpenditure!$A6,[2]pivotTable!$A$310:$A$615,0))/100*INDEX(gDP!T$6:T$271,MATCH(totalExpenditure!$A6,gDP!$B$6:$B$271))=0,"",INDEX([2]pivotTable!E$310:E$615,MATCH(totalExpenditure!$A6,[2]pivotTable!$A$310:$A$615,0))/100*INDEX(gDP!T$6:T$271,MATCH(totalExpenditure!$A6,gDP!$B$6:$B$271))) -> #N/A | BE6: =IF(INDEX([2]pivotTable!F$310:F$615,MATCH(totalExpenditure!$A6,[2]pivotTable!$A$310:$A$615,0))/100*INDEX(gDP!U$6:U$271,MATCH(totalExpenditure!$A6,gDP!$B$6:$B$271))=0,"",INDEX([2]pivotTable!F$310:F$615,MATCH(totalExpenditure!$A6,[2]pivotTable!$A$310:$A$615,0))/100*INDEX(gDP!U$6:U$271,MATCH(totalExpenditure!$A6,gDP!$B$6:$B$271))) -> #N/A | BF6: =IF(INDEX([2]pivotTable!G$310:G$615,MATCH(totalExpenditure!$A6,[2]pivotTable!$A$310:$A$615,0))/100*INDEX(gDP!V$6:V$271,MATCH(totalExpenditure!$A6,gDP!$B$6:$B$271))=0,"",INDEX([2]pivotTable!G$310:G$615,MATCH(totalExpenditure!$A6,[2]pivotTable!$A$310:$A$615,0))/100*INDEX(gDP!V$6:V$271,MATCH(totalExpenditure!$A6,gDP!$B$6:$B$271))) -> #N/A | BG6: =IF(INDEX([2]pivotTable!H$310:H$615,MATCH(totalExpenditure!$A6,[2]pivotTable!$A$310:$A$615,0))/100*INDEX(gDP!W$6:W$271,MATCH(totalExpenditure!$A6,gDP!$B$6:$B$271))=0,"",INDEX([2]pivotTable!H$310:H$615,MATCH(totalExpenditure!$A6,[2]pivotTable!$A$310:$A$615,0))/100*INDEX(gDP!W$6:W$271,MATCH(totalExpenditure!$A6,gDP!$B$6:$B$271))) -> #N/A | BH6: =IF(INDEX([2]pivotTable!I$310:I$615,MATCH(totalExpenditure!$A6,[2]pivotTable!$A$310:$A$615,0))/100*INDEX(gDP!X$6:X$271,MATCH(totalExpenditure!$A6,gDP!$B$6:$B$271))=0,"",INDEX([2]pivotTable!I$310:I$615,MATCH(totalExpenditure!$A6,[2]pivotTable!$A$310:$A$615,0))/100*INDEX(gDP!X$6:X$271,MATCH(totalExpenditure!$A6,gDP!$B$6:$B$271))) -> #N/A | ... CY6: =IF(INDEX([2]pivotTable!AZ$310:AZ$615,MATCH(totalExpenditure!$A6,[2]pivotTable!$A$310:$A$615,0))/100*INDEX(gDP!BO$6:BO$271,MATCH(totalExpenditure!$A6,gDP!$B$6:$B$271))=0,"",INDEX([2]pivotTable!AZ$310:AZ$615,MATCH(totalExpenditure!$A6,[2]pivotTable!$A$310:$A$615,0))/100*INDEX(gDP!BO$6:BO$271,MATCH(totalExpenditure!$A6,gDP!$B$6:$B$271))) -> #N/A | CZ6: =IF(B6="","",IF(BA6="","",B6-B6+INDEX(gDP!Q$6:Q$271,MATCH(totalExpenditure!$A6,gDP!$B$6:$B$271)))) -> #N/A | DA6: =IF(C6="","",IF(BB6="","",C6-C6+INDEX(gDP!R$6:R$271,MATCH(totalExpenditure!$A6,gDP!$B$6:$B$271)))) -> #N/A | DB6: =IF(D6="","",IF(BC6="","",D6-D6+INDEX(gDP!S$6:S$271,MATCH(totalExpenditure!$A6,gDP!$B$6:$B$271)))) -> #N/A | DC6: =IF(E6="","",IF(BD6="","",E6-E6+INDEX(gDP!T$6:T$271,MATCH(totalExpenditure!$A6,gDP!$B$6:$B$271)))) -> #N/A | DD6: =IF(F6="","",IF(BE6="","",F6-F6+INDEX(gDP!U$6:U$271,MATCH(totalExpenditure!$A6,gDP!$B$6:$B$271)))) -> #N/A | DE6: =IF(G6="","",IF(BF6="","",G6-G6+INDEX(gDP!V$6:V$271,MATCH(totalExpenditure!$A6,gDP!$B$6:$B$271)))) -> #N/A | DF6: =IF(H6="","",IF(BG6="","",H6-H6+INDEX(gDP!W$6:W$271,MATCH(totalExpenditure!$A6,gDP!$B$6:$B$271)))) -> #N/A | DG6: =IF(I6="","",IF(BH6="","",I6-I6+INDEX(gDP!X$6:X$271,MATCH(totalExpenditure!$A6,gDP!$B$6:$B$271)))) -> #N/A | ... EX6: =IF(AZ6="","",IF(CY6="","",AZ6-AZ6+INDEX(gDP!BO$6:BO$271,MATCH(totalExpenditure!$A6,gDP!$B$6:$B$271)))) -> #N/A
A7: AFG | B7: =IF(INDEX([2]pivotTable!B$3:B$308,MATCH(totalExpenditure!$A7,[2]pivotTable!$A$3:$A$308,0))/100*INDEX(gDP!Q$6:Q$271,MATCH(totalExpenditure!$A7,gDP!$B$6:$B$271))=0,"",INDEX([2]pivotTable!B$3:B$308,MATCH(totalExpenditure!$A7,[2]pivotTable!$A$3:$A$308,0))/100*INDEX(gDP!Q$6:Q$271,MATCH(totalExpenditure!$A7,gDP!$B$6:$B$271))) | C7: =IF(INDEX([2]pivotTable!C$3:C$308,MATCH(totalExpenditure!$A7,[2]pivotTable!$A$3:$A$308,0))/100*INDEX(gDP!R$6:R$271,MATCH(totalExpenditure!$A7,gDP!$B$6:$B$271))=0,"",INDEX([2]pivotTable!C$3:C$308,MATCH(totalExpenditure!$A7,[2]pivotTable!$A$3:$A$308,0))/100*INDEX(gDP!R$6:R$271,MATCH(totalExpenditure!$A7,gDP!$B$6:$B$271))) | D7: =IF(INDEX([2]pivotTable!D$3:D$308,MATCH(totalExpenditure!$A7,[2]pivotTable!$A$3:$A$308,0))/100*INDEX(gDP!S$6:S$271,MATCH(totalExpenditure!$A7,gDP!$B$6:$B$271))=0,"",INDEX([2]pivotTable!D$3:D$308,MATCH(totalExpenditure!$A7,[2]pivotTable!$A$3:$A$308,0))/100*INDEX(gDP!S$6:S$271,MATCH(totalExpenditure!$A7,gDP!$B$6:$B$271))) | E7: =IF(INDEX([2]pivotTable!E$3:E$308,MATCH(totalExpenditure!$A7,[2]pivotTable!$A$3:$A$308,0))/100*INDEX(gDP!T$6:T$271,MATCH(totalExpenditure!$A7,gDP!$B$6:$B$271))=0,"",INDEX([2]pivotTable!E$3:E$308,MATCH(totalExpenditure!$A7,[2]pivotTable!$A$3:$A$308,0))/100*INDEX(gDP!T$6:T$271,MATCH(totalExpenditure!$A7,gDP!$B$6:$B$271))) | F7: =IF(INDEX([2]pivotTable!F$3:F$308,MATCH(totalExpenditure!$A7,[2]pivotTable!$A$3:$A$308,0))/100*INDEX(gDP!U$6:U$271,MATCH(totalExpenditure!$A7,gDP!$B$6:$B$271))=0,"",INDEX([2]pivotTable!F$3:F$308,MATCH(totalExpenditure!$A7,[2]pivotTable!$A$3:$A$308,0))/100*INDEX(gDP!U$6:U$271,MATCH(totalExpenditure!$A7,gDP!$B$6:$B$271))) | G7: =IF(INDEX([2]pivotTable!G$3:G$308,MATCH(totalExpenditure!$A7,[2]pivotTable!$A$3:$A$308,0))/100*INDEX(gDP!V$6:V$271,MATCH(totalExpenditure!$A7,gDP!$B$6:$B$271))=0,"",INDEX([2]pivotTable!G$3:G$308,MATCH(totalExpenditure!$A7,[2]pivotTable!$A$3:$A$308,0))/100*INDEX(gDP!V$6:V$271,MATCH(totalExpenditure!$A7,gDP!$B$6:$B$271))) | H7: =IF(INDEX([2]pivotTable!H$3:H$308,MATCH(totalExpenditure!$A7,[2]pivotTable!$A$3:$A$308,0))/100*INDEX(gDP!W$6:W$271,MATCH(totalExpenditure!$A7,gDP!$B$6:$B$271))=0,"",INDEX([2]pivotTable!H$3:H$308,MATCH(totalExpenditure!$A7,[2]pivotTable!$A$3:$A$308,0))/100*INDEX(gDP!W$6:W$271,MATCH(totalExpenditure!$A7,gDP!$B$6:$B$271))) | I7: =IF(INDEX([2]pivotTable!I$3:I$308,MATCH(totalExpenditure!$A7,[2]pivotTable!$A$3:$A$308,0))/100*INDEX(gDP!X$6:X$271,MATCH(totalExpenditure!$A7,gDP!$B$6:$B$271))=0,"",INDEX([2]pivotTable!I$3:I$308,MATCH(totalExpenditure!$A7,[2]pivotTable!$A$3:$A$308,0))/100*INDEX(gDP!X$6:X$271,MATCH(totalExpenditure!$A7,gDP!$B$6:$B$271))) | ... AZ7: =IF(INDEX([2]pivotTable!AZ$3:AZ$308,MATCH(totalExpenditure!$A7,[2]pivotTable!$A$3:$A$308,0))/100*INDEX(gDP!BO$6:BO$271,MATCH(totalExpenditure!$A7,gDP!$B$6:$B$271))=0,"",INDEX([2]pivotTable!AZ$3:AZ$308,MATCH(totalExpenditure!$A7,[2]pivotTable!$A$3:$A$308,0))/100*INDEX(gDP!BO$6:BO$271,MATCH(totalExpenditure!$A7,gDP!$B$6:$B$271))) | BA7: =IF(INDEX([2]pivotTable!B$310:B$615,MATCH(totalExpenditure!$A7,[2]pivotTable!$A$310:$A$615,0))/100*INDEX(gDP!Q$6:Q$271,MATCH(totalExpenditure!$A7,gDP!$B$6:$B$271))=0,"",INDEX([2]pivotTable!B$310:B$615,MATCH(totalExpenditure!$A7,[2]pivotTable!$A$310:$A$615,0))/100*INDEX(gDP!Q$6:Q$271,MATCH(totalExpenditure!$A7,gDP!$B$6:$B$271))) | BB7: =IF(INDEX([2]pivotTable!C$310:C$615,MATCH(totalExpenditure!$A7,[2]pivotTable!$A$310:$A$615,0))/100*INDEX(gDP!R$6:R$271,MATCH(totalExpenditure!$A7,gDP!$B$6:$B$271))=0,"",INDEX([2]pivotTable!C$310:C$615,MATCH(totalExpenditure!$A7,[2]pivotTable!$A$310:$A$615,0))/100*INDEX(gDP!R$6:R$271,MATCH(totalExpenditure!$A7,gDP!$B$6:$B$271))) | BC7: =IF(INDEX([2]pivotTable!D$310:D$615,MATCH(totalExpenditure!$A7,[2]pivotTable!$A$310:$A$615,0))/100*INDEX(gDP!S$6:S$271,MATCH(totalExpenditure!$A7,gDP!$B$6:$B$271))=0,"",INDEX([2]pivotTable!D$310:D$615,MATCH(totalExpenditure!$A7,[2]pivotTable!$A$310:$A$615,0))/100*INDEX(gDP!S$6:S$271,MATCH(totalExpenditure!$A7,gDP!$B$6:$B$271))) | BD7: =IF(INDEX([2]pivotTable!E$310:E$615,MATCH(totalExpenditure!$A7,[2]pivotTable!$A$310:$A$615,0))/100*INDEX(gDP!T$6:T$271,MATCH(totalExpenditure!$A7,gDP!$B$6:$B$271))=0,"",INDEX([2]pivotTable!E$310:E$615,MATCH(totalExpenditure!$A7,[2]pivotTable!$A$310:$A$615,0))/100*INDEX(gDP!T$6:T$271,MATCH(totalExpenditure!$A7,gDP!$B$6:$B$271))) | BE7: =IF(INDEX([2]pivotTable!F$310:F$615,MATCH(totalExpenditure!$A7,[2]pivotTable!$A$310:$A$615,0))/100*INDEX(gDP!U$6:U$271,MATCH(totalExpenditure!$A7,gDP!$B$6:$B$271))=0,"",INDEX([2]pivotTable!F$310:F$615,MATCH(totalExpenditure!$A7,[2]pivotTable!$A$310:$A$615,0))/100*INDEX(gDP!U$6:U$271,MATCH(totalExpenditure!$A7,gDP!$B$6:$B$271))) | BF7: =IF(INDEX([2]pivotTable!G$310:G$615,MATCH(totalExpenditure!$A7,[2]pivotTable!$A$310:$A$615,0))/100*INDEX(gDP!V$6:V$271,MATCH(totalExpenditure!$A7,gDP!$B$6:$B$271))=0,"",INDEX([2]pivotTable!G$310:G$615,MATCH(totalExpenditure!$A7,[2]pivotTable!$A$310:$A$615,0))/100*INDEX(gDP!V$6:V$271,MATCH(totalExpenditure!$A7,gDP!$B$6:$B$271))) | BG7: =IF(INDEX([2]pivotTable!H$310:H$615,MATCH(totalExpenditure!$A7,[2]pivotTable!$A$310:$A$615,0))/100*INDEX(gDP!W$6:W$271,MATCH(totalExpenditure!$A7,gDP!$B$6:$B$271))=0,"",INDEX([2]pivotTable!H$310:H$615,MATCH(totalExpenditure!$A7,[2]pivotTable!$A$310:$A$615,0))/100*INDEX(gDP!W$6:W$271,MATCH(totalExpenditure!$A7,gDP!$B$6:$B$271))) | BH7: =IF(INDEX([2]pivotTable!I$310:I$615,MATCH(totalExpenditure!$A7,[2]pivotTable!$A$310:$A$615,0))/100*INDEX(gDP!X$6:X$271,MATCH(totalExpenditure!$A7,gDP!$B$6:$B$271))=0,"",INDEX([2]pivotTable!I$310:I$615,MATCH(totalExpenditure!$A7,[2]pivotTable!$A$310:$A$615,0))/100*INDEX(gDP!X$6:X$271,MATCH(totalExpenditure!$A7,gDP!$B$6:$B$271))) | ... CY7: =IF(INDEX([2]pivotTable!AZ$310:AZ$615,MATCH(totalExpenditure!$A7,[2]pivotTable!$A$310:$A$615,0))/100*INDEX(gDP!BO$6:BO$271,MATCH(totalExpenditure!$A7,gDP!$B$6:$B$271))=0,"",INDEX([2]pivotTable!AZ$310:AZ$615,MATCH(totalExpenditure!$A7,[2]pivotTable!$A$310:$A$615,0))/100*INDEX(gDP!BO$6:BO$271,MATCH(totalExpenditure!$A7,gDP!$B$6:$B$271))) | CZ7: =IF(B7="","",IF(BA7="","",B7-B7+INDEX(gDP!Q$6:Q$271,MATCH(totalExpenditure!$A7,gDP!$B$6:$B$271)))) | DA7: =IF(C7="","",IF(BB7="","",C7-C7+INDEX(gDP!R$6:R$271,MATCH(totalExpenditure!$A7,gDP!$B$6:$B$271)))) | DB7: =IF(D7="","",IF(BC7="","",D7-D7+INDEX(gDP!S$6:S$271,MATCH(totalExpenditure!$A7,gDP!$B$6:$B$271)))) | DC7: =IF(E7="","",IF(BD7="","",E7-E7+INDEX(gDP!T$6:T$271,MATCH(totalExpenditure!$A7,gDP!$B$6:$B$271)))) | DD7: =IF(F7="","",IF(BE7="","",F7-F7+INDEX(gDP!U$6:U$271,MATCH(totalExpenditure!$A7,gDP!$B$6:$B$271)))) | DE7: =IF(G7="","",IF(BF7="","",G7-G7+INDEX(gDP!V$6:V$271,MATCH(totalExpenditure!$A7,gDP!$B$6:$B$271)))) | DF7: =IF(H7="","",IF(BG7="","",H7-H7+INDEX(gDP!W$6:W$271,MATCH(totalExpenditure!$A7,gDP!$B$6:$B$271)))) | DG7: =IF(I7="","",IF(BH7="","",I7-I7+INDEX(gDP!X$6:X$271,MATCH(totalExpenditure!$A7,gDP!$B$6:$B$271)))) | ... EX7: =IF(AZ7="","",IF(CY7="","",AZ7-AZ7+INDEX(gDP!BO$6:BO$271,MATCH(totalExpenditure!$A7,gDP!$B$6:$B$271))))
A8: AFW | B8: =IF(INDEX([2]pivotTable!B$3:B$308,MATCH(totalExpenditure!$A8,[2]pivotTable!$A$3:$A$308,0))/100*INDEX(gDP!Q$6:Q$271,MATCH(totalExpenditure!$A8,gDP!$B$6:$B$271))=0,"",INDEX([2]pivotTable!B$3:B$308,MATCH(totalExpenditure!$A8,[2]pivotTable!$A$3:$A$308,0))/100*INDEX(gDP!Q$6:Q$271,MATCH(totalExpenditure!$A8,gDP!$B$6:$B$271))) -> #N/A | C8: =IF(INDEX([2]pivotTable!C$3:C$308,MATCH(totalExpenditure!$A8,[2]pivotTable!$A$3:$A$308,0))/100*INDEX(gDP!R$6:R$271,MATCH(totalExpenditure!$A8,gDP!$B$6:$B$271))=0,"",INDEX([2]pivotTable!C$3:C$308,MATCH(totalExpenditure!$A8,[2]pivotTable!$A$3:$A$308,0))/100*INDEX(gDP!R$6:R$271,MATCH(totalExpenditure!$A8,gDP!$B$6:$B$271))) -> #N/A | D8: =IF(INDEX([2]pivotTable!D$3:D$308,MATCH(totalExpenditure!$A8,[2]pivotTable!$A$3:$A$308,0))/100*INDEX(gDP!S$6:S$271,MATCH(totalExpenditure!$A8,gDP!$B$6:$B$271))=0,"",INDEX([2]pivotTable!D$3:D$308,MATCH(totalExpenditure!$A8,[2]pivotTable!$A$3:$A$308,0))/100*INDEX(gDP!S$6:S$271,MATCH(totalExpenditure!$A8,gDP!$B$6:$B$271))) -> #N/A | E8: =IF(INDEX([2]pivotTable!E$3:E$308,MATCH(totalExpenditure!$A8,[2]pivotTable!$A$3:$A$308,0))/100*INDEX(gDP!T$6:T$271,MATCH(totalExpenditure!$A8,gDP!$B$6:$B$271))=0,"",INDEX([2]pivotTable!E$3:E$308,MATCH(totalExpenditure!$A8,[2]pivotTable!$A$3:$A$308,0))/100*INDEX(gDP!T$6:T$271,MATCH(totalExpenditure!$A8,gDP!$B$6:$B$271))) -> #N/A | F8: =IF(INDEX([2]pivotTable!F$3:F$308,MATCH(totalExpenditure!$A8,[2]pivotTable!$A$3:$A$308,0))/100*INDEX(gDP!U$6:U$271,MATCH(totalExpenditure!$A8,gDP!$B$6:$B$271))=0,"",INDEX([2]pivotTable!F$3:F$308,MATCH(totalExpenditure!$A8,[2]pivotTable!$A$3:$A$308,0))/100*INDEX(gDP!U$6:U$271,MATCH(totalExpenditure!$A8,gDP!$B$6:$B$271))) -> #N/A | G8: =IF(INDEX([2]pivotTable!G$3:G$308,MATCH(totalExpenditure!$A8,[2]pivotTable!$A$3:$A$308,0))/100*INDEX(gDP!V$6:V$271,MATCH(totalExpenditure!$A8,gDP!$B$6:$B$271))=0,"",INDEX([2]pivotTable!G$3:G$308,MATCH(totalExpenditure!$A8,[2]pivotTable!$A$3:$A$308,0))/100*INDEX(gDP!V$6:V$271,MATCH(totalExpenditure!$A8,gDP!$B$6:$B$271))) -> #N/A | H8: =IF(INDEX([2]pivotTable!H$3:H$308,MATCH(totalExpenditure!$A8,[2]pivotTable!$A$3:$A$308,0))/100*INDEX(gDP!W$6:W$271,MATCH(totalExpenditure!$A8,gDP!$B$6:$B$271))=0,"",INDEX([2]pivotTable!H$3:H$308,MATCH(totalExpenditure!$A8,[2]pivotTable!$A$3:$A$308,0))/100*INDEX(gDP!W$6:W$271,MATCH(totalExpenditure!$A8,gDP!$B$6:$B$271))) -> #N/A | I8: =IF(INDEX([2]pivotTable!I$3:I$308,MATCH(totalExpenditure!$A8,[2]pivotTable!$A$3:$A$308,0))/100*INDEX(gDP!X$6:X$271,MATCH(totalExpenditure!$A8,gDP!$B$6:$B$271))=0,"",INDEX([2]pivotTable!I$3:I$308,MATCH(totalExpenditure!$A8,[2]pivotTable!$A$3:$A$308,0))/100*INDEX(gDP!X$6:X$271,MATCH(totalExpenditure!$A8,gDP!$B$6:$B$271))) -> #N/A | ... AZ8: =IF(INDEX([2]pivotTable!AZ$3:AZ$308,MATCH(totalExpenditure!$A8,[2]pivotTable!$A$3:$A$308,0))/100*INDEX(gDP!BO$6:BO$271,MATCH(totalExpenditure!$A8,gDP!$B$6:$B$271))=0,"",INDEX([2]pivotTable!AZ$3:AZ$308,MATCH(totalExpenditure!$A8,[2]pivotTable!$A$3:$A$308,0))/100*INDEX(gDP!BO$6:BO$271,MATCH(totalExpenditure!$A8,gDP!$B$6:$B$271))) -> #N/A | BA8: =IF(INDEX([2]pivotTable!B$310:B$615,MATCH(totalExpenditure!$A8,[2]pivotTable!$A$310:$A$615,0))/100*INDEX(gDP!Q$6:Q$271,MATCH(totalExpenditure!$A8,gDP!$B$6:$B$271))=0,"",INDEX([2]pivotTable!B$310:B$615,MATCH(totalExpenditure!$A8,[2]pivotTable!$A$310:$A$615,0))/100*INDEX(gDP!Q$6:Q$271,MATCH(totalExpenditure!$A8,gDP!$B$6:$B$271))) -> #N/A | BB8: =IF(INDEX([2]pivotTable!C$310:C$615,MATCH(totalExpenditure!$A8,[2]pivotTable!$A$310:$A$615,0))/100*INDEX(gDP!R$6:R$271,MATCH(totalExpenditure!$A8,gDP!$B$6:$B$271))=0,"",INDEX([2]pivotTable!C$310:C$615,MATCH(totalExpenditure!$A8,[2]pivotTable!$A$310:$A$615,0))/100*INDEX(gDP!R$6:R$271,MATCH(totalExpenditure!$A8,gDP!$B$6:$B$271))) -> #N/A | BC8: =IF(INDEX([2]pivotTable!D$310:D$615,MATCH(totalExpenditure!$A8,[2]pivotTable!$A$310:$A$615,0))/100*INDEX(gDP!S$6:S$271,MATCH(totalExpenditure!$A8,gDP!$B$6:$B$271))=0,"",INDEX([2]pivotTable!D$310:D$615,MATCH(totalExpenditure!$A8,[2]pivotTable!$A$310:$A$615,0))/100*INDEX(gDP!S$6:S$271,MATCH(totalExpenditure!$A8,gDP!$B$6:$B$271))) -> #N/A | BD8: =IF(INDEX([2]pivotTable!E$310:E$615,MATCH(totalExpenditure!$A8,[2]pivotTable!$A$310:$A$615,0))/100*INDEX(gDP!T$6:T$271,MATCH(totalExpenditure!$A8,gDP!$B$6:$B$271))=0,"",INDEX([2]pivotTable!E$310:E$615,MATCH(totalExpenditure!$A8,[2]pivotTable!$A$310:$A$615,0))/100*INDEX(gDP!T$6:T$271,MATCH(totalExpenditure!$A8,gDP!$B$6:$B$271))) -> #N/A | BE8: =IF(INDEX([2]pivotTable!F$310:F$615,MATCH(totalExpenditure!$A8,[2]pivotTable!$A$310:$A$615,0))/100*INDEX(gDP!U$6:U$271,MATCH(totalExpenditure!$A8,gDP!$B$6:$B$271))=0,"",INDEX([2]pivotTable!F$310:F$615,MATCH(totalExpenditure!$A8,[2]pivotTable!$A$310:$A$615,0))/100*INDEX(gDP!U$6:U$271,MATCH(totalExpenditure!$A8,gDP!$B$6:$B$271))) -> #N/A | BF8: =IF(INDEX([2]pivotTable!G$310:G$615,MATCH(totalExpenditure!$A8,[2]pivotTable!$A$310:$A$615,0))/100*INDEX(gDP!V$6:V$271,MATCH(totalExpenditure!$A8,gDP!$B$6:$B$271))=0,"",INDEX([2]pivotTable!G$310:G$615,MATCH(totalExpenditure!$A8,[2]pivotTable!$A$310:$A$615,0))/100*INDEX(gDP!V$6:V$271,MATCH(totalExpenditure!$A8,gDP!$B$6:$B$271))) -> #N/A | BG8: =IF(INDEX([2]pivotTable!H$310:H$615,MATCH(totalExpenditure!$A8,[2]pivotTable!$A$310:$A$615,0))/100*INDEX(gDP!W$6:W$271,MATCH(totalExpenditure!$A8,gDP!$B$6:$B$271))=0,"",INDEX([2]pivotTable!H$310:H$615,MATCH(totalExpenditure!$A8,[2]pivotTable!$A$310:$A$615,0))/100*INDEX(gDP!W$6:W$271,MATCH(totalExpenditure!$A8,gDP!$B$6:$B$271))) -> #N/A | BH8: =IF(INDEX([2]pivotTable!I$310:I$615,MATCH(totalExpenditure!$A8,[2]pivotTable!$A$310:$A$615,0))/100*INDEX(gDP!X$6:X$271,MATCH(totalExpenditure!$A8,gDP!$B$6:$B$271))=0,"",INDEX([2]pivotTable!I$310:I$615,MATCH(totalExpenditure!$A8,[2]pivotTable!$A$310:$A$615,0))/100*INDEX(gDP!X$6:X$271,MATCH(totalExpenditure!$A8,gDP!$B$6:$B$271))) -> #N/A | ... CY8: =IF(INDEX([2]pivotTable!AZ$310:AZ$615,MATCH(totalExpenditure!$A8,[2]pivotTable!$A$310:$A$615,0))/100*INDEX(gDP!BO$6:BO$271,MATCH(totalExpenditure!$A8,gDP!$B$6:$B$271))=0,"",INDEX([2]pivotTable!AZ$310:AZ$615,MATCH(totalExpenditure!$A8,[2]pivotTable!$A$310:$A$615,0))/100*INDEX(gDP!BO$6:BO$271,MATCH(totalExpenditure!$A8,gDP!$B$6:$B$271))) -> #N/A | CZ8: =IF(B8="","",IF(BA8="","",B8-B8+INDEX(gDP!Q$6:Q$271,MATCH(totalExpenditure!$A8,gDP!$B$6:$B$271)))) -> #N/A | DA8: =IF(C8="","",IF(BB8="","",C8-C8+INDEX(gDP!R$6:R$271,MATCH(totalExpenditure!$A8,gDP!$B$6:$B$271)))) -> #N/A | DB8: =IF(D8="","",IF(BC8="","",D8-D8+INDEX(gDP!S$6:S$271,MATCH(totalExpenditure!$A8,gDP!$B$6:$B$271)))) -> #N/A | DC8: =IF(E8="","",IF(BD8="","",E8-E8+INDEX(gDP!T$6:T$271,MATCH(totalExpenditure!$A8,gDP!$B$6:$B$271)))) -> #N/A | DD8: =IF(F8="","",IF(BE8="","",F8-F8+INDEX(gDP!U$6:U$271,MATCH(totalExpenditure!$A8,gDP!$B$6:$B$271)))) -> #N/A | DE8: =IF(G8="","",IF(BF8="","",G8-G8+INDEX(gDP!V$6:V$271,MATCH(totalExpenditure!$A8,gDP!$B$6:$B$271)))) -> #N/A | DF8: =IF(H8="","",IF(BG8="","",H8-H8+INDEX(gDP!W$6:W$271,MATCH(totalExpenditure!$A8,gDP!$B$6:$B$271)))) -> #N/A | DG8: =IF(I8="","",IF(BH8="","",I8-I8+INDEX(gDP!X$6:X$271,MATCH(totalExpenditure!$A8,gDP!$B$6:$B$271)))) -> #N/A | ... EX8: =IF(AZ8="","",IF(CY8="","",AZ8-AZ8+INDEX(gDP!BO$6:BO$271,MATCH(totalExpenditure!$A8,gDP!$B$6:$B$271)))) -> #N/A
A9: AGO | B9: =IF(INDEX([2]pivotTable!B$3:B$308,MATCH(totalExpenditure!$A9,[2]pivotTable!$A$3:$A$308,0))/100*INDEX(gDP!Q$6:Q$271,MATCH(totalExpenditure!$A9,gDP!$B$6:$B$271))=0,"",INDEX([2]pivotTable!B$3:B$308,MATCH(totalExpenditure!$A9,[2]pivotTable!$A$3:$A$308,0))/100*INDEX(gDP!Q$6:Q$271,MATCH(totalExpenditure!$A9,gDP!$B$6:$B$271))) | C9: =IF(INDEX([2]pivotTable!C$3:C$308,MATCH(totalExpenditure!$A9,[2]pivotTable!$A$3:$A$308,0))/100*INDEX(gDP!R$6:R$271,MATCH(totalExpenditure!$A9,gDP!$B$6:$B$271))=0,"",INDEX([2]pivotTable!C$3:C$308,MATCH(totalExpenditure!$A9,[2]pivotTable!$A$3:$A$308,0))/100*INDEX(gDP!R$6:R$271,MATCH(totalExpenditure!$A9,gDP!$B$6:$B$271))) | D9: =IF(INDEX([2]pivotTable!D$3:D$308,MATCH(totalExpenditure!$A9,[2]pivotTable!$A$3:$A$308,0))/100*INDEX(gDP!S$6:S$271,MATCH(totalExpenditure!$A9,gDP!$B$6:$B$271))=0,"",INDEX([2]pivotTable!D$3:D$308,MATCH(totalExpenditure!$A9,[2]pivotTable!$A$3:$A$308,0))/100*INDEX(gDP!S$6:S$271,MATCH(totalExpenditure!$A9,gDP!$B$6:$B$271))) | E9: =IF(INDEX([2]pivotTable!E$3:E$308,MATCH(totalExpenditure!$A9,[2]pivotTable!$A$3:$A$308,0))/100*INDEX(gDP!T$6:T$271,MATCH(totalExpenditure!$A9,gDP!$B$6:$B$271))=0,"",INDEX([2]pivotTable!E$3:E$308,MATCH(totalExpenditure!$A9,[2]pivotTable!$A$3:$A$308,0))/100*INDEX(gDP!T$6:T$271,MATCH(totalExpenditure!$A9,gDP!$B$6:$B$271))) | F9: =IF(INDEX([2]pivotTable!F$3:F$308,MATCH(totalExpenditure!$A9,[2]pivotTable!$A$3:$A$308,0))/100*INDEX(gDP!U$6:U$271,MATCH(totalExpenditure!$A9,gDP!$B$6:$B$271))=0,"",INDEX([2]pivotTable!F$3:F$308,MATCH(totalExpenditure!$A9,[2]pivotTable!$A$3:$A$308,0))/100*INDEX(gDP!U$6:U$271,MATCH(totalExpenditure!$A9,gDP!$B$6:$B$271))) | G9: =IF(INDEX([2]pivotTable!G$3:G$308,MATCH(totalExpenditure!$A9,[2]pivotTable!$A$3:$A$308,0))/100*INDEX(gDP!V$6:V$271,MATCH(totalExpenditure!$A9,gDP!$B$6:$B$271))=0,"",INDEX([2]pivotTable!G$3:G$308,MATCH(totalExpenditure!$A9,[2]pivotTable!$A$3:$A$308,0))/100*INDEX(gDP!V$6:V$271,MATCH(totalExpenditure!$A9,gDP!$B$6:$B$271))) | H9: =IF(INDEX([2]pivotTable!H$3:H$308,MATCH(totalExpenditure!$A9,[2]pivotTable!$A$3:$A$308,0))/100*INDEX(gDP!W$6:W$271,MATCH(totalExpenditure!$A9,gDP!$B$6:$B$271))=0,"",INDEX([2]pivotTable!H$3:H$308,MATCH(totalExpenditure!$A9,[2]pivotTable!$A$3:$A$308,0))/100*INDEX(gDP!W$6:W$271,MATCH(totalExpenditure!$A9,gDP!$B$6:$B$271))) | I9: =IF(INDEX([2]pivotTable!I$3:I$308,MATCH(totalExpenditure!$A9,[2]pivotTable!$A$3:$A$308,0))/100*INDEX(gDP!X$6:X$271,MATCH(totalExpenditure!$A9,gDP!$B$6:$B$271))=0,"",INDEX([2]pivotTable!I$3:I$308,MATCH(totalExpenditure!$A9,[2]pivotTable!$A$3:$A$308,0))/100*INDEX(gDP!X$6:X$271,MATCH(totalExpenditure!$A9,gDP!$B$6:$B$271))) | ... AZ9: =IF(INDEX([2]pivotTable!AZ$3:AZ$308,MATCH(totalExpenditure!$A9,[2]pivotTable!$A$3:$A$308,0))/100*INDEX(gDP!BO$6:BO$271,MATCH(totalExpenditure!$A9,gDP!$B$6:$B$271))=0,"",INDEX([2]pivotTable!AZ$3:AZ$308,MATCH(totalExpenditure!$A9,[2]pivotTable!$A$3:$A$308,0))/100*INDEX(gDP!BO$6:BO$271,MATCH(totalExpenditure!$A9,gDP!$B$6:$B$271))) | BA9: =IF(INDEX([2]pivotTable!B$310:B$615,MATCH(totalExpenditure!$A9,[2]pivotTable!$A$310:$A$615,0))/100*INDEX(gDP!Q$6:Q$271,MATCH(totalExpenditure!$A9,gDP!$B$6:$B$271))=0,"",INDEX([2]pivotTable!B$310:B$615,MATCH(totalExpenditure!$A9,[2]pivotTable!$A$310:$A$615,0))/100*INDEX(gDP!Q$6:Q$271,MATCH(totalExpenditure!$A9,gDP!$B$6:$B$271))) | BB9: =IF(INDEX([2]pivotTable!C$310:C$615,MATCH(totalExpenditure!$A9,[2]pivotTable!$A$310:$A$615,0))/100*INDEX(gDP!R$6:R$271,MATCH(totalExpenditure!$A9,gDP!$B$6:$B$271))=0,"",INDEX([2]pivotTable!C$310:C$615,MATCH(totalExpenditure!$A9,[2]pivotTable!$A$310:$A$615,0))/100*INDEX(gDP!R$6:R$271,MATCH(totalExpenditure!$A9,gDP!$B$6:$B$271))) | BC9: =IF(INDEX([2]pivotTable!D$310:D$615,MATCH(totalExpenditure!$A9,[2]pivotTable!$A$310:$A$615,0))/100*INDEX(gDP!S$6:S$271,MATCH(totalExpenditure!$A9,gDP!$B$6:$B$271))=0,"",INDEX([2]pivotTable!D$310:D$615,MATCH(totalExpenditure!$A9,[2]pivotTable!$A$310:$A$615,0))/100*INDEX(gDP!S$6:S$271,MATCH(totalExpenditure!$A9,gDP!$B$6:$B$271))) | BD9: =IF(INDEX([2]pivotTable!E$310:E$615,MATCH(totalExpenditure!$A9,[2]pivotTable!$A$310:$A$615,0))/100*INDEX(gDP!T$6:T$271,MATCH(totalExpenditure!$A9,gDP!$B$6:$B$271))=0,"",INDEX([2]pivotTable!E$310:E$615,MATCH(totalExpenditure!$A9,[2]pivotTable!$A$310:$A$615,0))/100*INDEX(gDP!T$6:T$271,MATCH(totalExpenditure!$A9,gDP!$B$6:$B$271))) | BE9: =IF(INDEX([2]pivotTable!F$310:F$615,MATCH(totalExpenditure!$A9,[2]pivotTable!$A$310:$A$615,0))/100*INDEX(gDP!U$6:U$271,MATCH(totalExpenditure!$A9,gDP!$B$6:$B$271))=0,"",INDEX([2]pivotTable!F$310:F$615,MATCH(totalExpenditure!$A9,[2]pivotTable!$A$310:$A$615,0))/100*INDEX(gDP!U$6:U$271,MATCH(totalExpenditure!$A9,gDP!$B$6:$B$271))) | BF9: =IF(INDEX([2]pivotTable!G$310:G$615,MATCH(totalExpenditure!$A9,[2]pivotTable!$A$310:$A$615,0))/100*INDEX(gDP!V$6:V$271,MATCH(totalExpenditure!$A9,gDP!$B$6:$B$271))=0,"",INDEX([2]pivotTable!G$310:G$615,MATCH(totalExpenditure!$A9,[2]pivotTable!$A$310:$A$615,0))/100*INDEX(gDP!V$6:V$271,MATCH(totalExpenditure!$A9,gDP!$B$6:$B$271))) | BG9: =IF(INDEX([2]pivotTable!H$310:H$615,MATCH(totalExpenditure!$A9,[2]pivotTable!$A$310:$A$615,0))/100*INDEX(gDP!W$6:W$271,MATCH(totalExpenditure!$A9,gDP!$B$6:$B$271))=0,"",INDEX([2]pivotTable!H$310:H$615,MATCH(totalExpenditure!$A9,[2]pivotTable!$A$310:$A$615,0))/100*INDEX(gDP!W$6:W$271,MATCH(totalExpenditure!$A9,gDP!$B$6:$B$271))) | BH9: =IF(INDEX([2]pivotTable!I$310:I$615,MATCH(totalExpenditure!$A9,[2]pivotTable!$A$310:$A$615,0))/100*INDEX(gDP!X$6:X$271,MATCH(totalExpenditure!$A9,gDP!$B$6:$B$271))=0,"",INDEX([2]pivotTable!I$310:I$615,MATCH(totalExpenditure!$A9,[2]pivotTable!$A$310:$A$615,0))/100*INDEX(gDP!X$6:X$271,MATCH(totalExpenditure!$A9,gDP!$B$6:$B$271))) | ... CY9: =IF(INDEX([2]pivotTable!AZ$310:AZ$615,MATCH(totalExpenditure!$A9,[2]pivotTable!$A$310:$A$615,0))/100*INDEX(gDP!BO$6:BO$271,MATCH(totalExpenditure!$A9,gDP!$B$6:$B$271))=0,"",INDEX([2]pivotTable!AZ$310:AZ$615,MATCH(totalExpenditure!$A9,[2]pivotTable!$A$310:$A$615,0))/100*INDEX(gDP!BO$6:BO$271,MATCH(totalExpenditure!$A9,gDP!$B$6:$B$271))) | CZ9: =IF(B9="","",IF(BA9="","",B9-B9+INDEX(gDP!Q$6:Q$271,MATCH(totalExpenditure!$A9,gDP!$B$6:$B$271)))) | DA9: =IF(C9="","",IF(BB9="","",C9-C9+INDEX(gDP!R$6:R$271,MATCH(totalExpenditure!$A9,gDP!$B$6:$B$271)))) | DB9: =IF(D9="","",IF(BC9="","",D9-D9+INDEX(gDP!S$6:S$271,MATCH(totalExpenditure!$A9,gDP!$B$6:$B$271)))) | DC9: =IF(E9="","",IF(BD9="","",E9-E9+INDEX(gDP!T$6:T$271,MATCH(totalExpenditure!$A9,gDP!$B$6:$B$271)))) | DD9: =IF(F9="","",IF(BE9="","",F9-F9+INDEX(gDP!U$6:U$271,MATCH(totalExpenditure!$A9,gDP!$B$6:$B$271)))) | DE9: =IF(G9="","",IF(BF9="","",G9-G9+INDEX(gDP!V$6:V$271,MATCH(totalExpenditure!$A9,gDP!$B$6:$B$271)))) | DF9: =IF(H9="","",IF(BG9="","",H9-H9+INDEX(gDP!W$6:W$271,MATCH(totalExpenditure!$A9,gDP!$B$6:$B$271)))) | DG9: =IF(I9="","",IF(BH9="","",I9-I9+INDEX(gDP!X$6:X$271,MATCH(totalExpenditure!$A9,gDP!$B$6:$B$271)))) | ... EX9: =IF(AZ9="","",IF(CY9="","",AZ9-AZ9+INDEX(gDP!BO$6:BO$271,MATCH(totalExpenditure!$A9,gDP!$B$6:$B$271))))
A10: ALB | B10: =IF(INDEX([2]pivotTable!B$3:B$308,MATCH(totalExpenditure!$A10,[2]pivotTable!$A$3:$A$308,0))/100*INDEX(gDP!Q$6:Q$271,MATCH(totalExpenditure!$A10,gDP!$B$6:$B$271))=0,"",INDEX([2]pivotTable!B$3:B$308,MATCH(totalExpenditure!$A10,[2]pivotTable!$A$3:$A$308,0))/100*INDEX(gDP!Q$6:Q$271,MATCH(totalExpenditure!$A10,gDP!$B$6:$B$271))) | C10: =IF(INDEX([2]pivotTable!C$3:C$308,MATCH(totalExpenditure!$A10,[2]pivotTable!$A$3:$A$308,0))/100*INDEX(gDP!R$6:R$271,MATCH(totalExpenditure!$A10,gDP!$B$6:$B$271))=0,"",INDEX([2]pivotTable!C$3:C$308,MATCH(totalExpenditure!$A10,[2]pivotTable!$A$3:$A$308,0))/100*INDEX(gDP!R$6:R$271,MATCH(totalExpenditure!$A10,gDP!$B$6:$B$271))) | D10: =IF(INDEX([2]pivotTable!D$3:D$308,MATCH(totalExpenditure!$A10,[2]pivotTable!$A$3:$A$308,0))/100*INDEX(gDP!S$6:S$271,MATCH(totalExpenditure!$A10,gDP!$B$6:$B$271))=0,"",INDEX([2]pivotTable!D$3:D$308,MATCH(totalExpenditure!$A10,[2]pivotTable!$A$3:$A$308,0))/100*INDEX(gDP!S$6:S$271,MATCH(totalExpenditure!$A10,gDP!$B$6:$B$271))) | E10: =IF(INDEX([2]pivotTable!E$3:E$308,MATCH(totalExpenditure!$A10,[2]pivotTable!$A$3:$A$308,0))/100*INDEX(gDP!T$6:T$271,MATCH(totalExpenditure!$A10,gDP!$B$6:$B$271))=0,"",INDEX([2]pivotTable!E$3:E$308,MATCH(totalExpenditure!$A10,[2]pivotTable!$A$3:$A$308,0))/100*INDEX(gDP!T$6:T$271,MATCH(totalExpenditure!$A10,gDP!$B$6:$B$271))) | F10: =IF(INDEX([2]pivotTable!F$3:F$308,MATCH(totalExpenditure!$A10,[2]pivotTable!$A$3:$A$308,0))/100*INDEX(gDP!U$6:U$271,MATCH(totalExpenditure!$A10,gDP!$B$6:$B$271))=0,"",INDEX([2]pivotTable!F$3:F$308,MATCH(totalExpenditure!$A10,[2]pivotTable!$A$3:$A$308,0))/100*INDEX(gDP!U$6:U$271,MATCH(totalExpenditure!$A10,gDP!$B$6:$B$271))) | G10: =IF(INDEX([2]pivotTable!G$3:G$308,MATCH(totalExpenditure!$A10,[2]pivotTable!$A$3:$A$308,0))/100*INDEX(gDP!V$6:V$271,MATCH(totalExpenditure!$A10,gDP!$B$6:$B$271))=0,"",INDEX([2]pivotTable!G$3:G$308,MATCH(totalExpenditure!$A10,[2]pivotTable!$A$3:$A$308,0))/100*INDEX(gDP!V$6:V$271,MATCH(totalExpenditure!$A10,gDP!$B$6:$B$271))) | H10: =IF(INDEX([2]pivotTable!H$3:H$308,MATCH(totalExpenditure!$A10,[2]pivotTable!$A$3:$A$308,0))/100*INDEX(gDP!W$6:W$271,MATCH(totalExpenditure!$A10,gDP!$B$6:$B$271))=0,"",INDEX([2]pivotTable!H$3:H$308,MATCH(totalExpenditure!$A10,[2]pivotTable!$A$3:$A$308,0))/100*INDEX(gDP!W$6:W$271,MATCH(totalExpenditure!$A10,gDP!$B$6:$B$271))) | I10: =IF(INDEX([2]pivotTable!I$3:I$308,MATCH(totalExpenditure!$A10,[2]pivotTable!$A$3:$A$308,0))/100*INDEX(gDP!X$6:X$271,MATCH(totalExpenditure!$A10,gDP!$B$6:$B$271))=0,"",INDEX([2]pivotTable!I$3:I$308,MATCH(totalExpenditure!$A10,[2]pivotTable!$A$3:$A$308,0))/100*INDEX(gDP!X$6:X$271,MATCH(totalExpenditure!$A10,gDP!$B$6:$B$271))) | ... AZ10: =IF(INDEX([2]pivotTable!AZ$3:AZ$308,MATCH(totalExpenditure!$A10,[2]pivotTable!$A$3:$A$308,0))/100*INDEX(gDP!BO$6:BO$271,MATCH(totalExpenditure!$A10,gDP!$B$6:$B$271))=0,"",INDEX([2]pivotTable!AZ$3:AZ$308,MATCH(totalExpenditure!$A10,[2]pivotTable!$A$3:$A$308,0))/100*INDEX(gDP!BO$6:BO$271,MATCH(totalExpenditure!$A10,gDP!$B$6:$B$271))) | BA10: =IF(INDEX([2]pivotTable!B$310:B$615,MATCH(totalExpenditure!$A10,[2]pivotTable!$A$310:$A$615,0))/100*INDEX(gDP!Q$6:Q$271,MATCH(totalExpenditure!$A10,gDP!$B$6:$B$271))=0,"",INDEX([2]pivotTable!B$310:B$615,MATCH(totalExpenditure!$A10,[2]pivotTable!$A$310:$A$615,0))/100*INDEX(gDP!Q$6:Q$271,MATCH(totalExpenditure!$A10,gDP!$B$6:$B$271))) | BB10: =IF(INDEX([2]pivotTable!C$310:C$615,MATCH(totalExpenditure!$A10,[2]pivotTable!$A$310:$A$615,0))/100*INDEX(gDP!R$6:R$271,MATCH(totalExpenditure!$A10,gDP!$B$6:$B$271))=0,"",INDEX([2]pivotTable!C$310:C$615,MATCH(totalExpenditure!$A10,[2]pivotTable!$A$310:$A$615,0))/100*INDEX(gDP!R$6:R$271,MATCH(totalExpenditure!$A10,gDP!$B$6:$B$271))) | BC10: =IF(INDEX([2]pivotTable!D$310:D$615,MATCH(totalExpenditure!$A10,[2]pivotTable!$A$310:$A$615,0))/100*INDEX(gDP!S$6:S$271,MATCH(totalExpenditure!$A10,gDP!$B$6:$B$271))=0,"",INDEX([2]pivotTable!D$310:D$615,MATCH(totalExpenditure!$A10,[2]pivotTable!$A$310:$A$615,0))/100*INDEX(gDP!S$6:S$271,MATCH(totalExpenditure!$A10,gDP!$B$6:$B$271))) | BD10: =IF(INDEX([2]pivotTable!E$310:E$615,MATCH(totalExpenditure!$A10,[2]pivotTable!$A$310:$A$615,0))/100*INDEX(gDP!T$6:T$271,MATCH(totalExpenditure!$A10,gDP!$B$6:$B$271))=0,"",INDEX([2]pivotTable!E$310:E$615,MATCH(totalExpenditure!$A10,[2]pivotTable!$A$310:$A$615,0))/100*INDEX(gDP!T$6:T$271,MATCH(totalExpenditure!$A10,gDP!$B$6:$B$271))) | BE10: =IF(INDEX([2]pivotTable!F$310:F$615,MATCH(totalExpenditure!$A10,[2]pivotTable!$A$310:$A$615,0))/100*INDEX(gDP!U$6:U$271,MATCH(totalExpenditure!$A10,gDP!$B$6:$B$271))=0,"",INDEX([2]pivotTable!F$310:F$615,MATCH(totalExpenditure!$A10,[2]pivotTable!$A$310:$A$615,0))/100*INDEX(gDP!U$6:U$271,MATCH(totalExpenditure!$A10,gDP!$B$6:$B$271))) | BF10: =IF(INDEX([2]pivotTable!G$310:G$615,MATCH(totalExpenditure!$A10,[2]pivotTable!$A$310:$A$615,0))/100*INDEX(gDP!V$6:V$271,MATCH(totalExpenditure!$A10,gDP!$B$6:$B$271))=0,"",INDEX([2]pivotTable!G$310:G$615,MATCH(totalExpenditure!$A10,[2]pivotTable!$A$310:$A$615,0))/100*INDEX(gDP!V$6:V$271,MATCH(totalExpenditure!$A10,gDP!$B$6:$B$271))) | BG10: =IF(INDEX([2]pivotTable!H$310:H$615,MATCH(totalExpenditure!$A10,[2]pivotTable!$A$310:$A$615,0))/100*INDEX(gDP!W$6:W$271,MATCH(totalExpenditure!$A10,gDP!$B$6:$B$271))=0,"",INDEX([2]pivotTable!H$310:H$615,MATCH(totalExpenditure!$A10,[2]pivotTable!$A$310:$A$615,0))/100*INDEX(gDP!W$6:W$271,MATCH(totalExpenditure!$A10,gDP!$B$6:$B$271))) | BH10: =IF(INDEX([2]pivotTable!I$310:I$615,MATCH(totalExpenditure!$A10,[2]pivotTable!$A$310:$A$615,0))/100*INDEX(gDP!X$6:X$271,MATCH(totalExpenditure!$A10,gDP!$B$6:$B$271))=0,"",INDEX([2]pivotTable!I$310:I$615,MATCH(totalExpenditure!$A10,[2]pivotTable!$A$310:$A$615,0))/100*INDEX(gDP!X$6:X$271,MATCH(totalExpenditure!$A10,gDP!$B$6:$B$271))) | ... CY10: =IF(INDEX([2]pivotTable!AZ$310:AZ$615,MATCH(totalExpenditure!$A10,[2]pivotTable!$A$310:$A$615,0))/100*INDEX(gDP!BO$6:BO$271,MATCH(totalExpenditure!$A10,gDP!$B$6:$B$271))=0,"",INDEX([2]pivotTable!AZ$310:AZ$615,MATCH(totalExpenditure!$A10,[2]pivotTable!$A$310:$A$615,0))/100*INDEX(gDP!BO$6:BO$271,MATCH(totalExpenditure!$A10,gDP!$B$6:$B$271))) | CZ10: =IF(B10="","",IF(BA10="","",B10-B10+INDEX(gDP!Q$6:Q$271,MATCH(totalExpenditure!$A10,gDP!$B$6:$B$271)))) | DA10: =IF(C10="","",IF(BB10="","",C10-C10+INDEX(gDP!R$6:R$271,MATCH(totalExpenditure!$A10,gDP!$B$6:$B$271)))) | DB10: =IF(D10="","",IF(BC10="","",D10-D10+INDEX(gDP!S$6:S$271,MATCH(totalExpenditure!$A10,gDP!$B$6:$B$271)))) | DC10: =IF(E10="","",IF(BD10="","",E10-E10+INDEX(gDP!T$6:T$271,MATCH(totalExpenditure!$A10,gDP!$B$6:$B$271)))) | DD10: =IF(F10="","",IF(BE10="","",F10-F10+INDEX(gDP!U$6:U$271,MATCH(totalExpenditure!$A10,gDP!$B$6:$B$271)))) | DE10: =IF(G10="","",IF(BF10="","",G10-G10+INDEX(gDP!V$6:V$271,MATCH(totalExpenditure!$A10,gDP!$B$6:$B$271)))) | DF10: =IF(H10="","",IF(BG10="","",H10-H10+INDEX(gDP!W$6:W$271,MATCH(totalExpenditure!$A10,gDP!$B$6:$B$271)))) | DG10: =IF(I10="","",IF(BH10="","",I10-I10+INDEX(gDP!X$6:X$271,MATCH(totalExpenditure!$A10,gDP!$B$6:$B$271)))) | ... EX10: =IF(AZ10="","",IF(CY10="","",AZ10-AZ10+INDEX(gDP!BO$6:BO$271,MATCH(totalExpenditure!$A10,gDP!$B$6:$B$271))))
A11: AND | B11: =IF(INDEX([2]pivotTable!B$3:B$308,MATCH(totalExpenditure!$A11,[2]pivotTable!$A$3:$A$308,0))/100*INDEX(gDP!Q$6:Q$271,MATCH(totalExpenditure!$A11,gDP!$B$6:$B$271))=0,"",INDEX([2]pivotTable!B$3:B$308,MATCH(totalExpenditure!$A11,[2]pivotTable!$A$3:$A$308,0))/100*INDEX(gDP!Q$6:Q$271,MATCH(totalExpenditure!$A11,gDP!$B$6:$B$271))) -> #N/A | C11: =IF(INDEX([2]pivotTable!C$3:C$308,MATCH(totalExpenditure!$A11,[2]pivotTable!$A$3:$A$308,0))/100*INDEX(gDP!R$6:R$271,MATCH(totalExpenditure!$A11,gDP!$B$6:$B$271))=0,"",INDEX([2]pivotTable!C$3:C$308,MATCH(totalExpenditure!$A11,[2]pivotTable!$A$3:$A$308,0))/100*INDEX(gDP!R$6:R$271,MATCH(totalExpenditure!$A11,gDP!$B$6:$B$271))) -> #N/A | D11: =IF(INDEX([2]pivotTable!D$3:D$308,MATCH(totalExpenditure!$A11,[2]pivotTable!$A$3:$A$308,0))/100*INDEX(gDP!S$6:S$271,MATCH(totalExpenditure!$A11,gDP!$B$6:$B$271))=0,"",INDEX([2]pivotTable!D$3:D$308,MATCH(totalExpenditure!$A11,[2]pivotTable!$A$3:$A$308,0))/100*INDEX(gDP!S$6:S$271,MATCH(totalExpenditure!$A11,gDP!$B$6:$B$271))) -> #N/A | E11: =IF(INDEX([2]pivotTable!E$3:E$308,MATCH(totalExpenditure!$A11,[2]pivotTable!$A$3:$A$308,0))/100*INDEX(gDP!T$6:T$271,MATCH(totalExpenditure!$A11,gDP!$B$6:$B$271))=0,"",INDEX([2]pivotTable!E$3:E$308,MATCH(totalExpenditure!$A11,[2]pivotTable!$A$3:$A$308,0))/100*INDEX(gDP!T$6:T$271,MATCH(totalExpenditure!$A11,gDP!$B$6:$B$271))) -> #N/A | F11: =IF(INDEX([2]pivotTable!F$3:F$308,MATCH(totalExpenditure!$A11,[2]pivotTable!$A$3:$A$308,0))/100*INDEX(gDP!U$6:U$271,MATCH(totalExpenditure!$A11,gDP!$B$6:$B$271))=0,"",INDEX([2]pivotTable!F$3:F$308,MATCH(totalExpenditure!$A11,[2]pivotTable!$A$3:$A$308,0))/100*INDEX(gDP!U$6:U$271,MATCH(totalExpenditure!$A11,gDP!$B$6:$B$271))) -> #N/A | G11: =IF(INDEX([2]pivotTable!G$3:G$308,MATCH(totalExpenditure!$A11,[2]pivotTable!$A$3:$A$308,0))/100*INDEX(gDP!V$6:V$271,MATCH(totalExpenditure!$A11,gDP!$B$6:$B$271))=0,"",INDEX([2]pivotTable!G$3:G$308,MATCH(totalExpenditure!$A11,[2]pivotTable!$A$3:$A$308,0))/100*INDEX(gDP!V$6:V$271,MATCH(totalExpenditure!$A11,gDP!$B$6:$B$271))) -> #N/A | H11: =IF(INDEX([2]pivotTable!H$3:H$308,MATCH(totalExpenditure!$A11,[2]pivotTable!$A$3:$A$308,0))/100*INDEX(gDP!W$6:W$271,MATCH(totalExpenditure!$A11,gDP!$B$6:$B$271))=0,"",INDEX([2]pivotTable!H$3:H$308,MATCH(totalExpenditure!$A11,[2]pivotTable!$A$3:$A$308,0))/100*INDEX(gDP!W$6:W$271,MATCH(totalExpenditure!$A11,gDP!$B$6:$B$271))) -> #N/A | I11: =IF(INDEX([2]pivotTable!I$3:I$308,MATCH(totalExpenditure!$A11,[2]pivotTable!$A$3:$A$308,0))/100*INDEX(gDP!X$6:X$271,MATCH(totalExpenditure!$A11,gDP!$B$6:$B$271))=0,"",INDEX([2]pivotTable!I$3:I$308,MATCH(totalExpenditure!$A11,[2]pivotTable!$A$3:$A$308,0))/100*INDEX(gDP!X$6:X$271,MATCH(totalExpenditure!$A11,gDP!$B$6:$B$271))) -> #N/A | ... AZ11: =IF(INDEX([2]pivotTable!AZ$3:AZ$308,MATCH(totalExpenditure!$A11,[2]pivotTable!$A$3:$A$308,0))/100*INDEX(gDP!BO$6:BO$271,MATCH(totalExpenditure!$A11,gDP!$B$6:$B$271))=0,"",INDEX([2]pivotTable!AZ$3:AZ$308,MATCH(totalExpenditure!$A11,[2]pivotTable!$A$3:$A$308,0))/100*INDEX(gDP!BO$6:BO$271,MATCH(totalExpenditure!$A11,gDP!$B$6:$B$271))) -> #N/A | BA11: =IF(INDEX([2]pivotTable!B$310:B$615,MATCH(totalExpenditure!$A11,[2]pivotTable!$A$310:$A$615,0))/100*INDEX(gDP!Q$6:Q$271,MATCH(totalExpenditure!$A11,gDP!$B$6:$B$271))=0,"",INDEX([2]pivotTable!B$310:B$615,MATCH(totalExpenditure!$A11,[2]pivotTable!$A$310:$A$615,0))/100*INDEX(gDP!Q$6:Q$271,MATCH(totalExpenditure!$A11,gDP!$B$6:$B$271))) -> #N/A | BB11: =IF(INDEX([2]pivotTable!C$310:C$615,MATCH(totalExpenditure!$A11,[2]pivotTable!$A$310:$A$615,0))/100*INDEX(gDP!R$6:R$271,MATCH(totalExpenditure!$A11,gDP!$B$6:$B$271))=0,"",INDEX([2]pivotTable!C$310:C$615,MATCH(totalExpenditure!$A11,[2]pivotTable!$A$310:$A$615,0))/100*INDEX(gDP!R$6:R$271,MATCH(totalExpenditure!$A11,gDP!$B$6:$B$271))) -> #N/A | BC11: =IF(INDEX([2]pivotTable!D$310:D$615,MATCH(totalExpenditure!$A11,[2]pivotTable!$A$310:$A$615,0))/100*INDEX(gDP!S$6:S$271,MATCH(totalExpenditure!$A11,gDP!$B$6:$B$271))=0,"",INDEX([2]pivotTable!D$310:D$615,MATCH(totalExpenditure!$A11,[2]pivotTable!$A$310:$A$615,0))/100*INDEX(gDP!S$6:S$271,MATCH(totalExpenditure!$A11,gDP!$B$6:$B$271))) -> #N/A | BD11: =IF(INDEX([2]pivotTable!E$310:E$615,MATCH(totalExpenditure!$A11,[2]pivotTable!$A$310:$A$615,0))/100*INDEX(gDP!T$6:T$271,MATCH(totalExpenditure!$A11,gDP!$B$6:$B$271))=0,"",INDEX([2]pivotTable!E$310:E$615,MATCH(totalExpenditure!$A11,[2]pivotTable!$A$310:$A$615,0))/100*INDEX(gDP!T$6:T$271,MATCH(totalExpenditure!$A11,gDP!$B$6:$B$271))) -> #N/A | BE11: =IF(INDEX([2]pivotTable!F$310:F$615,MATCH(totalExpenditure!$A11,[2]pivotTable!$A$310:$A$615,0))/100*INDEX(gDP!U$6:U$271,MATCH(totalExpenditure!$A11,gDP!$B$6:$B$271))=0,"",INDEX([2]pivotTable!F$310:F$615,MATCH(totalExpenditure!$A11,[2]pivotTable!$A$310:$A$615,0))/100*INDEX(gDP!U$6:U$271,MATCH(totalExpenditure!$A11,gDP!$B$6:$B$271))) -> #N/A | BF11: =IF(INDEX([2]pivotTable!G$310:G$615,MATCH(totalExpenditure!$A11,[2]pivotTable!$A$310:$A$615,0))/100*INDEX(gDP!V$6:V$271,MATCH(totalExpenditure!$A11,gDP!$B$6:$B$271))=0,"",INDEX([2]pivotTable!G$310:G$615,MATCH(totalExpenditure!$A11,[2]pivotTable!$A$310:$A$615,0))/100*INDEX(gDP!V$6:V$271,MATCH(totalExpenditure!$A11,gDP!$B$6:$B$271))) -> #N/A | BG11: =IF(INDEX([2]pivotTable!H$310:H$615,MATCH(totalExpenditure!$A11,[2]pivotTable!$A$310:$A$615,0))/100*INDEX(gDP!W$6:W$271,MATCH(totalExpenditure!$A11,gDP!$B$6:$B$271))=0,"",INDEX([2]pivotTable!H$310:H$615,MATCH(totalExpenditure!$A11,[2]pivotTable!$A$310:$A$615,0))/100*INDEX(gDP!W$6:W$271,MATCH(totalExpenditure!$A11,gDP!$B$6:$B$271))) -> #N/A | BH11: =IF(INDEX([2]pivotTable!I$310:I$615,MATCH(totalExpenditure!$A11,[2]pivotTable!$A$310:$A$615,0))/100*INDEX(gDP!X$6:X$271,MATCH(totalExpenditure!$A11,gDP!$B$6:$B$271))=0,"",INDEX([2]pivotTable!I$310:I$615,MATCH(totalExpenditure!$A11,[2]pivotTable!$A$310:$A$615,0))/100*INDEX(gDP!X$6:X$271,MATCH(totalExpenditure!$A11,gDP!$B$6:$B$271))) -> #N/A | ... CY11: =IF(INDEX([2]pivotTable!AZ$310:AZ$615,MATCH(totalExpenditure!$A11,[2]pivotTable!$A$310:$A$615,0))/100*INDEX(gDP!BO$6:BO$271,MATCH(totalExpenditure!$A11,gDP!$B$6:$B$271))=0,"",INDEX([2]pivotTable!AZ$310:AZ$615,MATCH(totalExpenditure!$A11,[2]pivotTable!$A$310:$A$615,0))/100*INDEX(gDP!BO$6:BO$271,MATCH(totalExpenditure!$A11,gDP!$B$6:$B$271))) -> #N/A | CZ11: =IF(B11="","",IF(BA11="","",B11-B11+INDEX(gDP!Q$6:Q$271,MATCH(totalExpenditure!$A11,gDP!$B$6:$B$271)))) -> #N/A | DA11: =IF(C11="","",IF(BB11="","",C11-C11+INDEX(gDP!R$6:R$271,MATCH(totalExpenditure!$A11,gDP!$B$6:$B$271)))) -> #N/A | DB11: =IF(D11="","",IF(BC11="","",D11-D11+INDEX(gDP!S$6:S$271,MATCH(totalExpenditure!$A11,gDP!$B$6:$B$271)))) -> #N/A | DC11: =IF(E11="","",IF(BD11="","",E11-E11+INDEX(gDP!T$6:T$271,MATCH(totalExpenditure!$A11,gDP!$B$6:$B$271)))) -> #N/A | DD11: =IF(F11="","",IF(BE11="","",F11-F11+INDEX(gDP!U$6:U$271,MATCH(totalExpenditure!$A11,gDP!$B$6:$B$271)))) -> #N/A | DE11: =IF(G11="","",IF(BF11="","",G11-G11+INDEX(gDP!V$6:V$271,MATCH(totalExpenditure!$A11,gDP!$B$6:$B$271)))) -> #N/A | DF11: =IF(H11="","",IF(BG11="","",H11-H11+INDEX(gDP!W$6:W$271,MATCH(totalExpenditure!$A11,gDP!$B$6:$B$271)))) -> #N/A | DG11: =IF(I11="","",IF(BH11="","",I11-I11+INDEX(gDP!X$6:X$271,MATCH(totalExpenditure!$A11,gDP!$B$6:$B$271)))) -> #N/A | ... EX11: =IF(AZ11="","",IF(CY11="","",AZ11-AZ11+INDEX(gDP!BO$6:BO$271,MATCH(totalExpenditure!$A11,gDP!$B$6:$B$271)))) -> #N/A
A12: ARB | B12: =IF(INDEX([2]pivotTable!B$3:B$308,MATCH(totalExpenditure!$A12,[2]pivotTable!$A$3:$A$308,0))/100*INDEX(gDP!Q$6:Q$271,MATCH(totalExpenditure!$A12,gDP!$B$6:$B$271))=0,"",INDEX([2]pivotTable!B$3:B$308,MATCH(totalExpenditure!$A12,[2]pivotTable!$A$3:$A$308,0))/100*INDEX(gDP!Q$6:Q$271,MATCH(totalExpenditure!$A12,gDP!$B$6:$B$271))) -> #N/A | C12: =IF(INDEX([2]pivotTable!C$3:C$308,MATCH(totalExpenditure!$A12,[2]pivotTable!$A$3:$A$308,0))/100*INDEX(gDP!R$6:R$271,MATCH(totalExpenditure!$A12,gDP!$B$6:$B$271))=0,"",INDEX([2]pivotTable!C$3:C$308,MATCH(totalExpenditure!$A12,[2]pivotTable!$A$3:$A$308,0))/100*INDEX(gDP!R$6:R$271,MATCH(totalExpenditure!$A12,gDP!$B$6:$B$271))) -> #N/A | D12: =IF(INDEX([2]pivotTable!D$3:D$308,MATCH(totalExpenditure!$A12,[2]pivotTable!$A$3:$A$308,0))/100*INDEX(gDP!S$6:S$271,MATCH(totalExpenditure!$A12,gDP!$B$6:$B$271))=0,"",INDEX([2]pivotTable!D$3:D$308,MATCH(totalExpenditure!$A12,[2]pivotTable!$A$3:$A$308,0))/100*INDEX(gDP!S$6:S$271,MATCH(totalExpenditure!$A12,gDP!$B$6:$B$271))) -> #N/A | E12: =IF(INDEX([2]pivotTable!E$3:E$308,MATCH(totalExpenditure!$A12,[2]pivotTable!$A$3:$A$308,0))/100*INDEX(gDP!T$6:T$271,MATCH(totalExpenditure!$A12,gDP!$B$6:$B$271))=0,"",INDEX([2]pivotTable!E$3:E$308,MATCH(totalExpenditure!$A12,[2]pivotTable!$A$3:$A$308,0))/100*INDEX(gDP!T$6:T$271,MATCH(totalExpenditure!$A12,gDP!$B$6:$B$271))) -> #N/A | F12: =IF(INDEX([2]pivotTable!F$3:F$308,MATCH(totalExpenditure!$A12,[2]pivotTable!$A$3:$A$308,0))/100*INDEX(gDP!U$6:U$271,MATCH(totalExpenditure!$A12,gDP!$B$6:$B$271))=0,"",INDEX([2]pivotTable!F$3:F$308,MATCH(totalExpenditure!$A12,[2]pivotTable!$A$3:$A$308,0))/100*INDEX(gDP!U$6:U$271,MATCH(totalExpenditure!$A12,gDP!$B$6:$B$271))) -> #N/A | G12: =IF(INDEX([2]pivotTable!G$3:G$308,MATCH(totalExpenditure!$A12,[2]pivotTable!$A$3:$A$308,0))/100*INDEX(gDP!V$6:V$271,MATCH(totalExpenditure!$A12,gDP!$B$6:$B$271))=0,"",INDEX([2]pivotTable!G$3:G$308,MATCH(totalExpenditure!$A12,[2]pivotTable!$A$3:$A$308,0))/100*INDEX(gDP!V$6:V$271,MATCH(totalExpenditure!$A12,gDP!$B$6:$B$271))) -> #N/A | H12: =IF(INDEX([2]pivotTable!H$3:H$308,MATCH(totalExpenditure!$A12,[2]pivotTable!$A$3:$A$308,0))/100*INDEX(gDP!W$6:W$271,MATCH(totalExpenditure!$A12,gDP!$B$6:$B$271))=0,"",INDEX([2]pivotTable!H$3:H$308,MATCH(totalExpenditure!$A12,[2]pivotTable!$A$3:$A$308,0))/100*INDEX(gDP!W$6:W$271,MATCH(totalExpenditure!$A12,gDP!$B$6:$B$271))) -> #N/A | I12: =IF(INDEX([2]pivotTable!I$3:I$308,MATCH(totalExpenditure!$A12,[2]pivotTable!$A$3:$A$308,0))/100*INDEX(gDP!X$6:X$271,MATCH(totalExpenditure!$A12,gDP!$B$6:$B$271))=0,"",INDEX([2]pivotTable!I$3:I$308,MATCH(totalExpenditure!$A12,[2]pivotTable!$A$3:$A$308,0))/100*INDEX(gDP!X$6:X$271,MATCH(totalExpenditure!$A12,gDP!$B$6:$B$271))) -> #N/A | ... AZ12: =IF(INDEX([2]pivotTable!AZ$3:AZ$308,MATCH(totalExpenditure!$A12,[2]pivotTable!$A$3:$A$308,0))/100*INDEX(gDP!BO$6:BO$271,MATCH(totalExpenditure!$A12,gDP!$B$6:$B$271))=0,"",INDEX([2]pivotTable!AZ$3:AZ$308,MATCH(totalExpenditure!$A12,[2]pivotTable!$A$3:$A$308,0))/100*INDEX(gDP!BO$6:BO$271,MATCH(totalExpenditure!$A12,gDP!$B$6:$B$271))) -> #N/A | BA12: =IF(INDEX([2]pivotTable!B$310:B$615,MATCH(totalExpenditure!$A12,[2]pivotTable!$A$310:$A$615,0))/100*INDEX(gDP!Q$6:Q$271,MATCH(totalExpenditure!$A12,gDP!$B$6:$B$271))=0,"",INDEX([2]pivotTable!B$310:B$615,MATCH(totalExpenditure!$A12,[2]pivotTable!$A$310:$A$615,0))/100*INDEX(gDP!Q$6:Q$271,MATCH(totalExpenditure!$A12,gDP!$B$6:$B$271))) -> #N/A | BB12: =IF(INDEX([2]pivotTable!C$310:C$615,MATCH(totalExpenditure!$A12,[2]pivotTable!$A$310:$A$615,0))/100*INDEX(gDP!R$6:R$271,MATCH(totalExpenditure!$A12,gDP!$B$6:$B$271))=0,"",INDEX([2]pivotTable!C$310:C$615,MATCH(totalExpenditure!$A12,[2]pivotTable!$A$310:$A$615,0))/100*INDEX(gDP!R$6:R$271,MATCH(totalExpenditure!$A12,gDP!$B$6:$B$271))) -> #N/A | BC12: =IF(INDEX([2]pivotTable!D$310:D$615,MATCH(totalExpenditure!$A12,[2]pivotTable!$A$310:$A$615,0))/100*INDEX(gDP!S$6:S$271,MATCH(totalExpenditure!$A12,gDP!$B$6:$B$271))=0,"",INDEX([2]pivotTable!D$310:D$615,MATCH(totalExpenditure!$A12,[2]pivotTable!$A$310:$A$615,0))/100*INDEX(gDP!S$6:S$271,MATCH(totalExpenditure!$A12,gDP!$B$6:$B$271))) -> #N/A | BD12: =IF(INDEX([2]pivotTable!E$310:E$615,MATCH(totalExpenditure!$A12,[2]pivotTable!$A$310:$A$615,0))/100*INDEX(gDP!T$6:T$271,MATCH(totalExpenditure!$A12,gDP!$B$6:$B$271))=0,"",INDEX([2]pivotTable!E$310:E$615,MATCH(totalExpenditure!$A12,[2]pivotTable!$A$310:$A$615,0))/100*INDEX(gDP!T$6:T$271,MATCH(totalExpenditure!$A12,gDP!$B$6:$B$271))) -> #N/A | BE12: =IF(INDEX([2]pivotTable!F$310:F$615,MATCH(totalExpenditure!$A12,[2]pivotTable!$A$310:$A$615,0))/100*INDEX(gDP!U$6:U$271,MATCH(totalExpenditure!$A12,gDP!$B$6:$B$271))=0,"",INDEX([2]pivotTable!F$310:F$615,MATCH(totalExpenditure!$A12,[2]pivotTable!$A$310:$A$615,0))/100*INDEX(gDP!U$6:U$271,MATCH(totalExpenditure!$A12,gDP!$B$6:$B$271))) -> #N/A | BF12: =IF(INDEX([2]pivotTable!G$310:G$615,MATCH(totalExpenditure!$A12,[2]pivotTable!$A$310:$A$615,0))/100*INDEX(gDP!V$6:V$271,MATCH(totalExpenditure!$A12,gDP!$B$6:$B$271))=0,"",INDEX([2]pivotTable!G$310:G$615,MATCH(totalExpenditure!$A12,[2]pivotTable!$A$310:$A$615,0))/100*INDEX(gDP!V$6:V$271,MATCH(totalExpenditure!$A12,gDP!$B$6:$B$271))) -> #N/A | BG12: =IF(INDEX([2]pivotTable!H$310:H$615,MATCH(totalExpenditure!$A12,[2]pivotTable!$A$310:$A$615,0))/100*INDEX(gDP!W$6:W$271,MATCH(totalExpenditure!$A12,gDP!$B$6:$B$271))=0,"",INDEX([2]pivotTable!H$310:H$615,MATCH(totalExpenditure!$A12,[2]pivotTable!$A$310:$A$615,0))/100*INDEX(gDP!W$6:W$271,MATCH(totalExpenditure!$A12,gDP!$B$6:$B$271))) -> #N/A | BH12: =IF(INDEX([2]pivotTable!I$310:I$615,MATCH(totalExpenditure!$A12,[2]pivotTable!$A$310:$A$615,0))/100*INDEX(gDP!X$6:X$271,MATCH(totalExpenditure!$A12,gDP!$B$6:$B$271))=0,"",INDEX([2]pivotTable!I$310:I$615,MATCH(totalExpenditure!$A12,[2]pivotTable!$A$310:$A$615,0))/100*INDEX(gDP!X$6:X$271,MATCH(totalExpenditure!$A12,gDP!$B$6:$B$271))) -> #N/A | ... CY12: =IF(INDEX([2]pivotTable!AZ$310:AZ$615,MATCH(totalExpenditure!$A12,[2]pivotTable!$A$310:$A$615,0))/100*INDEX(gDP!BO$6:BO$271,MATCH(totalExpenditure!$A12,gDP!$B$6:$B$271))=0,"",INDEX([2]pivotTable!AZ$310:AZ$615,MATCH(totalExpenditure!$A12,[2]pivotTable!$A$310:$A$615,0))/100*INDEX(gDP!BO$6:BO$271,MATCH(totalExpenditure!$A12,gDP!$B$6:$B$271))) -> #N/A | CZ12: =IF(B12="","",IF(BA12="","",B12-B12+INDEX(gDP!Q$6:Q$271,MATCH(totalExpenditure!$A12,gDP!$B$6:$B$271)))) -> #N/A | DA12: =IF(C12="","",IF(BB12="","",C12-C12+INDEX(gDP!R$6:R$271,MATCH(totalExpenditure!$A12,gDP!$B$6:$B$271)))) -> #N/A | DB12: =IF(D12="","",IF(BC12="","",D12-D12+INDEX(gDP!S$6:S$271,MATCH(totalExpenditure!$A12,gDP!$B$6:$B$271)))) -> #N/A | DC12: =IF(E12="","",IF(BD12="","",E12-E12+INDEX(gDP!T$6:T$271,MATCH(totalExpenditure!$A12,gDP!$B$6:$B$271)))) -> #N/A | DD12: =IF(F12="","",IF(BE12="","",F12-F12+INDEX(gDP!U$6:U$271,MATCH(totalExpenditure!$A12,gDP!$B$6:$B$271)))) -> #N/A | DE12: =IF(G12="","",IF(BF12="","",G12-G12+INDEX(gDP!V$6:V$271,MATCH(totalExpenditure!$A12,gDP!$B$6:$B$271)))) -> #N/A | DF12: =IF(H12="","",IF(BG12="","",H12-H12+INDEX(gDP!W$6:W$271,MATCH(totalExpenditure!$A12,gDP!$B$6:$B$271)))) -> #N/A | DG12: =IF(I12="","",IF(BH12="","",I12-I12+INDEX(gDP!X$6:X$271,MATCH(totalExpenditure!$A12,gDP!$B$6:$B$271)))) -> #N/A | ... EX12: =IF(AZ12="","",IF(CY12="","",AZ12-AZ12+INDEX(gDP!BO$6:BO$271,MATCH(totalExpenditure!$A12,gDP!$B$6:$B$271)))) -> #N/A
A13: ARE | B13: =IF(INDEX([2]pivotTable!B$3:B$308,MATCH(totalExpenditure!$A13,[2]pivotTable!$A$3:$A$308,0))/100*INDEX(gDP!Q$6:Q$271,MATCH(totalExpenditure!$A13,gDP!$B$6:$B$271))=0,"",INDEX([2]pivotTable!B$3:B$308,MATCH(totalExpenditure!$A13,[2]pivotTable!$A$3:$A$308,0))/100*INDEX(gDP!Q$6:Q$271,MATCH(totalExpenditure!$A13,gDP!$B$6:$B$271))) | C13: =IF(INDEX([2]pivotTable!C$3:C$308,MATCH(totalExpenditure!$A13,[2]pivotTable!$A$3:$A$308,0))/100*INDEX(gDP!R$6:R$271,MATCH(totalExpenditure!$A13,gDP!$B$6:$B$271))=0,"",INDEX([2]pivotTable!C$3:C$308,MATCH(totalExpenditure!$A13,[2]pivotTable!$A$3:$A$308,0))/100*INDEX(gDP!R$6:R$271,MATCH(totalExpenditure!$A13,gDP!$B$6:$B$271))) | D13: =IF(INDEX([2]pivotTable!D$3:D$308,MATCH(totalExpenditure!$A13,[2]pivotTable!$A$3:$A$308,0))/100*INDEX(gDP!S$6:S$271,MATCH(totalExpenditure!$A13,gDP!$B$6:$B$271))=0,"",INDEX([2]pivotTable!D$3:D$308,MATCH(totalExpenditure!$A13,[2]pivotTable!$A$3:$A$308,0))/100*INDEX(gDP!S$6:S$271,MATCH(totalExpenditure!$A13,gDP!$B$6:$B$271))) | E13: =IF(INDEX([2]pivotTable!E$3:E$308,MATCH(totalExpenditure!$A13,[2]pivotTable!$A$3:$A$308,0))/100*INDEX(gDP!T$6:T$271,MATCH(totalExpenditure!$A13,gDP!$B$6:$B$271))=0,"",INDEX([2]pivotTable!E$3:E$308,MATCH(totalExpenditure!$A13,[2]pivotTable!$A$3:$A$308,0))/100*INDEX(gDP!T$6:T$271,MATCH(totalExpenditure!$A13,gDP!$B$6:$B$271))) | F13: =IF(INDEX([2]pivotTable!F$3:F$308,MATCH(totalExpenditure!$A13,[2]pivotTable!$A$3:$A$308,0))/100*INDEX(gDP!U$6:U$271,MATCH(totalExpenditure!$A13,gDP!$B$6:$B$271))=0,"",INDEX([2]pivotTable!F$3:F$308,MATCH(totalExpenditure!$A13,[2]pivotTable!$A$3:$A$308,0))/100*INDEX(gDP!U$6:U$271,MATCH(totalExpenditure!$A13,gDP!$B$6:$B$271))) | G13: =IF(INDEX([2]pivotTable!G$3:G$308,MATCH(totalExpenditure!$A13,[2]pivotTable!$A$3:$A$308,0))/100*INDEX(gDP!V$6:V$271,MATCH(totalExpenditure!$A13,gDP!$B$6:$B$271))=0,"",INDEX([2]pivotTable!G$3:G$308,MATCH(totalExpenditure!$A13,[2]pivotTable!$A$3:$A$308,0))/100*INDEX(gDP!V$6:V$271,MATCH(totalExpenditure!$A13,gDP!$B$6:$B$271))) | H13: =IF(INDEX([2]pivotTable!H$3:H$308,MATCH(totalExpenditure!$A13,[2]pivotTable!$A$3:$A$308,0))/100*INDEX(gDP!W$6:W$271,MATCH(totalExpenditure!$A13,gDP!$B$6:$B$271))=0,"",INDEX([2]pivotTable!H$3:H$308,MATCH(totalExpenditure!$A13,[2]pivotTable!$A$3:$A$308,0))/100*INDEX(gDP!W$6:W$271,MATCH(totalExpenditure!$A13,gDP!$B$6:$B$271))) | I13: =IF(INDEX([2]pivotTable!I$3:I$308,MATCH(totalExpenditure!$A13,[2]pivotTable!$A$3:$A$308,0))/100*INDEX(gDP!X$6:X$271,MATCH(totalExpenditure!$A13,gDP!$B$6:$B$271))=0,"",INDEX([2]pivotTable!I$3:I$308,MATCH(totalExpenditure!$A13,[2]pivotTable!$A$3:$A$308,0))/100*INDEX(gDP!X$6:X$271,MATCH(totalExpenditure!$A13,gDP!$B$6:$B$271))) | ... AZ13: =IF(INDEX([2]pivotTable!AZ$3:AZ$308,MATCH(totalExpenditure!$A13,[2]pivotTable!$A$3:$A$308,0))/100*INDEX(gDP!BO$6:BO$271,MATCH(totalExpenditure!$A13,gDP!$B$6:$B$271))=0,"",INDEX([2]pivotTable!AZ$3:AZ$308,MATCH(totalExpenditure!$A13,[2]pivotTable!$A$3:$A$308,0))/100*INDEX(gDP!BO$6:BO$271,MATCH(totalExpenditure!$A13,gDP!$B$6:$B$271))) | BA13: =IF(INDEX([2]pivotTable!B$310:B$615,MATCH(totalExpenditure!$A13,[2]pivotTable!$A$310:$A$615,0))/100*INDEX(gDP!Q$6:Q$271,MATCH(totalExpenditure!$A13,gDP!$B$6:$B$271))=0,"",INDEX([2]pivotTable!B$310:B$615,MATCH(totalExpenditure!$A13,[2]pivotTable!$A$310:$A$615,0))/100*INDEX(gDP!Q$6:Q$271,MATCH(totalExpenditure!$A13,gDP!$B$6:$B$271))) | BB13: =IF(INDEX([2]pivotTable!C$310:C$615,MATCH(totalExpenditure!$A13,[2]pivotTable!$A$310:$A$615,0))/100*INDEX(gDP!R$6:R$271,MATCH(totalExpenditure!$A13,gDP!$B$6:$B$271))=0,"",INDEX([2]pivotTable!C$310:C$615,MATCH(totalExpenditure!$A13,[2]pivotTable!$A$310:$A$615,0))/100*INDEX(gDP!R$6:R$271,MATCH(totalExpenditure!$A13,gDP!$B$6:$B$271))) | BC13: =IF(INDEX([2]pivotTable!D$310:D$615,MATCH(totalExpenditure!$A13,[2]pivotTable!$A$310:$A$615,0))/100*INDEX(gDP!S$6:S$271,MATCH(totalExpenditure!$A13,gDP!$B$6:$B$271))=0,"",INDEX([2]pivotTable!D$310:D$615,MATCH(totalExpenditure!$A13,[2]pivotTable!$A$310:$A$615,0))/100*INDEX(gDP!S$6:S$271,MATCH(totalExpenditure!$A13,gDP!$B$6:$B$271))) | BD13: =IF(INDEX([2]pivotTable!E$310:E$615,MATCH(totalExpenditure!$A13,[2]pivotTable!$A$310:$A$615,0))/100*INDEX(gDP!T$6:T$271,MATCH(totalExpenditure!$A13,gDP!$B$6:$B$271))=0,"",INDEX([2]pivotTable!E$310:E$615,MATCH(totalExpenditure!$A13,[2]pivotTable!$A$310:$A$615,0))/100*INDEX(gDP!T$6:T$271,MATCH(totalExpenditure!$A13,gDP!$B$6:$B$271))) | BE13: =IF(INDEX([2]pivotTable!F$310:F$615,MATCH(totalExpenditure!$A13,[2]pivotTable!$A$310:$A$615,0))/100*INDEX(gDP!U$6:U$271,MATCH(totalExpenditure!$A13,gDP!$B$6:$B$271))=0,"",INDEX([2]pivotTable!F$310:F$615,MATCH(totalExpenditure!$A13,[2]pivotTable!$A$310:$A$615,0))/100*INDEX(gDP!U$6:U$271,MATCH(totalExpenditure!$A13,gDP!$B$6:$B$271))) | BF13: =IF(INDEX([2]pivotTable!G$310:G$615,MATCH(totalExpenditure!$A13,[2]pivotTable!$A$310:$A$615,0))/100*INDEX(gDP!V$6:V$271,MATCH(totalExpenditure!$A13,gDP!$B$6:$B$271))=0,"",INDEX([2]pivotTable!G$310:G$615,MATCH(totalExpenditure!$A13,[2]pivotTable!$A$310:$A$615,0))/100*INDEX(gDP!V$6:V$271,MATCH(totalExpenditure!$A13,gDP!$B$6:$B$271))) | BG13: =IF(INDEX([2]pivotTable!H$310:H$615,MATCH(totalExpenditure!$A13,[2]pivotTable!$A$310:$A$615,0))/100*INDEX(gDP!W$6:W$271,MATCH(totalExpenditure!$A13,gDP!$B$6:$B$271))=0,"",INDEX([2]pivotTable!H$310:H$615,MATCH(totalExpenditure!$A13,[2]pivotTable!$A$310:$A$615,0))/100*INDEX(gDP!W$6:W$271,MATCH(totalExpenditure!$A13,gDP!$B$6:$B$271))) | BH13: =IF(INDEX([2]pivotTable!I$310:I$615,MATCH(totalExpenditure!$A13,[2]pivotTable!$A$310:$A$615,0))/100*INDEX(gDP!X$6:X$271,MATCH(totalExpenditure!$A13,gDP!$B$6:$B$271))=0,"",INDEX([2]pivotTable!I$310:I$615,MATCH(totalExpenditure!$A13,[2]pivotTable!$A$310:$A$615,0))/100*INDEX(gDP!X$6:X$271,MATCH(totalExpenditure!$A13,gDP!$B$6:$B$271))) | ... CY13: =IF(INDEX([2]pivotTable!AZ$310:AZ$615,MATCH(totalExpenditure!$A13,[2]pivotTable!$A$310:$A$615,0))/100*INDEX(gDP!BO$6:BO$271,MATCH(totalExpenditure!$A13,gDP!$B$6:$B$271))=0,"",INDEX([2]pivotTable!AZ$310:AZ$615,MATCH(totalExpenditure!$A13,[2]pivotTable!$A$310:$A$615,0))/100*INDEX(gDP!BO$6:BO$271,MATCH(totalExpenditure!$A13,gDP!$B$6:$B$271))) | CZ13: =IF(B13="","",IF(BA13="","",B13-B13+INDEX(gDP!Q$6:Q$271,MATCH(totalExpenditure!$A13,gDP!$B$6:$B$271)))) | DA13: =IF(C13="","",IF(BB13="","",C13-C13+INDEX(gDP!R$6:R$271,MATCH(totalExpenditure!$A13,gDP!$B$6:$B$271)))) | DB13: =IF(D13="","",IF(BC13="","",D13-D13+INDEX(gDP!S$6:S$271,MATCH(totalExpenditure!$A13,gDP!$B$6:$B$271)))) | DC13: =IF(E13="","",IF(BD13="","",E13-E13+INDEX(gDP!T$6:T$271,MATCH(totalExpenditure!$A13,gDP!$B$6:$B$271)))) | DD13: =IF(F13="","",IF(BE13="","",F13-F13+INDEX(gDP!U$6:U$271,MATCH(totalExpenditure!$A13,gDP!$B$6:$B$271)))) | DE13: =IF(G13="","",IF(BF13="","",G13-G13+INDEX(gDP!V$6:V$271,MATCH(totalExpenditure!$A13,gDP!$B$6:$B$271)))) | DF13: =IF(H13="","",IF(BG13="","",H13-H13+INDEX(gDP!W$6:W$271,MATCH(totalExpenditure!$A13,gDP!$B$6:$B$271)))) | DG13: =IF(I13="","",IF(BH13="","",I13-I13+INDEX(gDP!X$6:X$271,MATCH(totalExpenditure!$A13,gDP!$B$6:$B$271)))) | ... EX13: =IF(AZ13="","",IF(CY13="","",AZ13-AZ13+INDEX(gDP!BO$6:BO$271,MATCH(totalExpenditure!$A13,gDP!$B$6:$B$271))))
A14: ARG | B14: =IF(INDEX([2]pivotTable!B$3:B$308,MATCH(totalExpenditure!$A14,[2]pivotTable!$A$3:$A$308,0))/100*INDEX(gDP!Q$6:Q$271,MATCH(totalExpenditure!$A14,gDP!$B$6:$B$271))=0,"",INDEX([2]pivotTable!B$3:B$308,MATCH(totalExpenditure!$A14,[2]pivotTable!$A$3:$A$308,0))/100*INDEX(gDP!Q$6:Q$271,MATCH(totalExpenditure!$A14,gDP!$B$6:$B$271))) | C14: =IF(INDEX([2]pivotTable!C$3:C$308,MATCH(totalExpenditure!$A14,[2]pivotTable!$A$3:$A$308,0))/100*INDEX(gDP!R$6:R$271,MATCH(totalExpenditure!$A14,gDP!$B$6:$B$271))=0,"",INDEX([2]pivotTable!C$3:C$308,MATCH(totalExpenditure!$A14,[2]pivotTable!$A$3:$A$308,0))/100*INDEX(gDP!R$6:R$271,MATCH(totalExpenditure!$A14,gDP!$B$6:$B$271))) | D14: =IF(INDEX([2]pivotTable!D$3:D$308,MATCH(totalExpenditure!$A14,[2]pivotTable!$A$3:$A$308,0))/100*INDEX(gDP!S$6:S$271,MATCH(totalExpenditure!$A14,gDP!$B$6:$B$271))=0,"",INDEX([2]pivotTable!D$3:D$308,MATCH(totalExpenditure!$A14,[2]pivotTable!$A$3:$A$308,0))/100*INDEX(gDP!S$6:S$271,MATCH(totalExpenditure!$A14,gDP!$B$6:$B$271))) | E14: =IF(INDEX([2]pivotTable!E$3:E$308,MATCH(totalExpenditure!$A14,[2]pivotTable!$A$3:$A$308,0))/100*INDEX(gDP!T$6:T$271,MATCH(totalExpenditure!$A14,gDP!$B$6:$B$271))=0,"",INDEX([2]pivotTable!E$3:E$308,MATCH(totalExpenditure!$A14,[2]pivotTable!$A$3:$A$308,0))/100*INDEX(gDP!T$6:T$271,MATCH(totalExpenditure!$A14,gDP!$B$6:$B$271))) | F14: =IF(INDEX([2]pivotTable!F$3:F$308,MATCH(totalExpenditure!$A14,[2]pivotTable!$A$3:$A$308,0))/100*INDEX(gDP!U$6:U$271,MATCH(totalExpenditure!$A14,gDP!$B$6:$B$271))=0,"",INDEX([2]pivotTable!F$3:F$308,MATCH(totalExpenditure!$A14,[2]pivotTable!$A$3:$A$308,0))/100*INDEX(gDP!U$6:U$271,MATCH(totalExpenditure!$A14,gDP!$B$6:$B$271))) | G14: =IF(INDEX([2]pivotTable!G$3:G$308,MATCH(totalExpenditure!$A14,[2]pivotTable!$A$3:$A$308,0))/100*INDEX(gDP!V$6:V$271,MATCH(totalExpenditure!$A14,gDP!$B$6:$B$271))=0,"",INDEX([2]pivotTable!G$3:G$308,MATCH(totalExpenditure!$A14,[2]pivotTable!$A$3:$A$308,0))/100*INDEX(gDP!V$6:V$271,MATCH(totalExpenditure!$A14,gDP!$B$6:$B$271))) | H14: =IF(INDEX([2]pivotTable!H$3:H$308,MATCH(totalExpenditure!$A14,[2]pivotTable!$A$3:$A$308,0))/100*INDEX(gDP!W$6:W$271,MATCH(totalExpenditure!$A14,gDP!$B$6:$B$271))=0,"",INDEX([2]pivotTable!H$3:H$308,MATCH(totalExpenditure!$A14,[2]pivotTable!$A$3:$A$308,0))/100*INDEX(gDP!W$6:W$271,MATCH(totalExpenditure!$A14,gDP!$B$6:$B$271))) | I14: =IF(INDEX([2]pivotTable!I$3:I$308,MATCH(totalExpenditure!$A14,[2]pivotTable!$A$3:$A$308,0))/100*INDEX(gDP!X$6:X$271,MATCH(totalExpenditure!$A14,gDP!$B$6:$B$271))=0,"",INDEX([2]pivotTable!I$3:I$308,MATCH(totalExpenditure!$A14,[2]pivotTable!$A$3:$A$308,0))/100*INDEX(gDP!X$6:X$271,MATCH(totalExpenditure!$A14,gDP!$B$6:$B$271))) | ... AZ14: =IF(INDEX([2]pivotTable!AZ$3:AZ$308,MATCH(totalExpenditure!$A14,[2]pivotTable!$A$3:$A$308,0))/100*INDEX(gDP!BO$6:BO$271,MATCH(totalExpenditure!$A14,gDP!$B$6:$B$271))=0,"",INDEX([2]pivotTable!AZ$3:AZ$308,MATCH(totalExpenditure!$A14,[2]pivotTable!$A$3:$A$308,0))/100*INDEX(gDP!BO$6:BO$271,MATCH(totalExpenditure!$A14,gDP!$B$6:$B$271))) | BA14: =IF(INDEX([2]pivotTable!B$310:B$615,MATCH(totalExpenditure!$A14,[2]pivotTable!$A$310:$A$615,0))/100*INDEX(gDP!Q$6:Q$271,MATCH(totalExpenditure!$A14,gDP!$B$6:$B$271))=0,"",INDEX([2]pivotTable!B$310:B$615,MATCH(totalExpenditure!$A14,[2]pivotTable!$A$310:$A$615,0))/100*INDEX(gDP!Q$6:Q$271,MATCH(totalExpenditure!$A14,gDP!$B$6:$B$271))) | BB14: =IF(INDEX([2]pivotTable!C$310:C$615,MATCH(totalExpenditure!$A14,[2]pivotTable!$A$310:$A$615,0))/100*INDEX(gDP!R$6:R$271,MATCH(totalExpenditure!$A14,gDP!$B$6:$B$271))=0,"",INDEX([2]pivotTable!C$310:C$615,MATCH(totalExpenditure!$A14,[2]pivotTable!$A$310:$A$615,0))/100*INDEX(gDP!R$6:R$271,MATCH(totalExpenditure!$A14,gDP!$B$6:$B$271))) | BC14: =IF(INDEX([2]pivotTable!D$310:D$615,MATCH(totalExpenditure!$A14,[2]pivotTable!$A$310:$A$615,0))/100*INDEX(gDP!S$6:S$271,MATCH(totalExpenditure!$A14,gDP!$B$6:$B$271))=0,"",INDEX([2]pivotTable!D$310:D$615,MATCH(totalExpenditure!$A14,[2]pivotTable!$A$310:$A$615,0))/100*INDEX(gDP!S$6:S$271,MATCH(totalExpenditure!$A14,gDP!$B$6:$B$271))) | BD14: =IF(INDEX([2]pivotTable!E$310:E$615,MATCH(totalExpenditure!$A14,[2]pivotTable!$A$310:$A$615,0))/100*INDEX(gDP!T$6:T$271,MATCH(totalExpenditure!$A14,gDP!$B$6:$B$271))=0,"",INDEX([2]pivotTable!E$310:E$615,MATCH(totalExpenditure!$A14,[2]pivotTable!$A$310:$A$615,0))/100*INDEX(gDP!T$6:T$271,MATCH(totalExpenditure!$A14,gDP!$B$6:$B$271))) | BE14: =IF(INDEX([2]pivotTable!F$310:F$615,MATCH(totalExpenditure!$A14,[2]pivotTable!$A$310:$A$615,0))/100*INDEX(gDP!U$6:U$271,MATCH(totalExpenditure!$A14,gDP!$B$6:$B$271))=0,"",INDEX([2]pivotTable!F$310:F$615,MATCH(totalExpenditure!$A14,[2]pivotTable!$A$310:$A$615,0))/100*INDEX(gDP!U$6:U$271,MATCH(totalExpenditure!$A14,gDP!$B$6:$B$271))) | BF14: =IF(INDEX([2]pivotTable!G$310:G$615,MATCH(totalExpenditure!$A14,[2]pivotTable!$A$310:$A$615,0))/100*INDEX(gDP!V$6:V$271,MATCH(totalExpenditure!$A14,gDP!$B$6:$B$271))=0,"",INDEX([2]pivotTable!G$310:G$615,MATCH(totalExpenditure!$A14,[2]pivotTable!$A$310:$A$615,0))/100*INDEX(gDP!V$6:V$271,MATCH(totalExpenditure!$A14,gDP!$B$6:$B$271))) | BG14: =IF(INDEX([2]pivotTable!H$310:H$615,MATCH(totalExpenditure!$A14,[2]pivotTable!$A$310:$A$615,0))/100*INDEX(gDP!W$6:W$271,MATCH(totalExpenditure!$A14,gDP!$B$6:$B$271))=0,"",INDEX([2]pivotTable!H$310:H$615,MATCH(totalExpenditure!$A14,[2]pivotTable!$A$310:$A$615,0))/100*INDEX(gDP!W$6:W$271,MATCH(totalExpenditure!$A14,gDP!$B$6:$B$271))) | BH14: =IF(INDEX([2]pivotTable!I$310:I$615,MATCH(totalExpenditure!$A14,[2]pivotTable!$A$310:$A$615,0))/100*INDEX(gDP!X$6:X$271,MATCH(totalExpenditure!$A14,gDP!$B$6:$B$271))=0,"",INDEX([2]pivotTable!I$310:I$615,MATCH(totalExpenditure!$A14,[2]pivotTable!$A$310:$A$615,0))/100*INDEX(gDP!X$6:X$271,MATCH(totalExpenditure!$A14,gDP!$B$6:$B$271))) | ... CY14: =IF(INDEX([2]pivotTable!AZ$310:AZ$615,MATCH(totalExpenditure!$A14,[2]pivotTable!$A$310:$A$615,0))/100*INDEX(gDP!BO$6:BO$271,MATCH(totalExpenditure!$A14,gDP!$B$6:$B$271))=0,"",INDEX([2]pivotTable!AZ$310:AZ$615,MATCH(totalExpenditure!$A14,[2]pivotTable!$A$310:$A$615,0))/100*INDEX(gDP!BO$6:BO$271,MATCH(totalExpenditure!$A14,gDP!$B$6:$B$271))) | CZ14: =IF(B14="","",IF(BA14="","",B14-B14+INDEX(gDP!Q$6:Q$271,MATCH(totalExpenditure!$A14,gDP!$B$6:$B$271)))) | DA14: =IF(C14="","",IF(BB14="","",C14-C14+INDEX(gDP!R$6:R$271,MATCH(totalExpenditure!$A14,gDP!$B$6:$B$271)))) | DB14: =IF(D14="","",IF(BC14="","",D14-D14+INDEX(gDP!S$6:S$271,MATCH(totalExpenditure!$A14,gDP!$B$6:$B$271)))) | DC14: =IF(E14="","",IF(BD14="","",E14-E14+INDEX(gDP!T$6:T$271,MATCH(totalExpenditure!$A14,gDP!$B$6:$B$271)))) | DD14: =IF(F14="","",IF(BE14="","",F14-F14+INDEX(gDP!U$6:U$271,MATCH(totalExpenditure!$A14,gDP!$B$6:$B$271)))) | DE14: =IF(G14="","",IF(BF14="","",G14-G14+INDEX(gDP!V$6:V$271,MATCH(totalExpenditure!$A14,gDP!$B$6:$B$271)))) | DF14: =IF(H14="","",IF(BG14="","",H14-H14+INDEX(gDP!W$6:W$271,MATCH(totalExpenditure!$A14,gDP!$B$6:$B$271)))) | DG14: =IF(I14="","",IF(BH14="","",I14-I14+INDEX(gDP!X$6:X$271,MATCH(totalExpenditure!$A14,gDP!$B$6:$B$271)))) | ... EX14: =IF(AZ14="","",IF(CY14="","",AZ14-AZ14+INDEX(gDP!BO$6:BO$271,MATCH(totalExpenditure!$A14,gDP!$B$6:$B$271))))
